Workbook

Sheet Data
A1: Data | B1: Ultimo | C1: Apertura | D1: Massimo | E1: Minimo | F1: Vol. | G1: Var. % | J1: Data | K1: Ultimo | L1: Apertura | M1: Massimo | N1: Minimo | O1: Vol. | P1: Var. % | S1: S&P 500 | T1: Data | U1: Ultimo | V1: Apertura | W1: Massimo | X1: Minimo | Y1: Vol. | Z1: Var. %
A2: 42006 | B2: 23.57 | C2: 23.7 | D2: 23.89 | E2: 23.24 | F2: 395,71K | G2: -0.0004 | J2: 42008 | K2: 23.87 | L2: 23.39 | M2: 23.95 | N2: 21.98 | O2: 5,17M | P2: 0.0127 | T2: 42008 | U2: 2044.8 | V2: 2054.4 | W2: 2064.4 | X2: 1992.4 | Z2: -0.0065
A3: 42009 | B3: 22.85 | C3: 23.39 | D3: 23.46 | E3: 22.54 | F3: 982,71K | G3: -0.0305 | J3: 42015 | K3: 23.95 | L3: 23.85 | M3: 24.35 | N3: 23.11 | O3: 6,36M | P3: 0.0034 | T3: 42015 | U3: 2019.4 | V3: 2046.1 | W3: 2056.9 | X3: 1988.1 | Z3: -0.0124
A4: 42010 | B4: 22.13 | C4: 22.51 | D4: 22.81 | E4: 21.98 | F4: 1,20M | G4: -0.0315 | J4: 42022 | K4: 24.62 | L4: 24.03 | M4: 25.17 | N4: 23.48 | O4: 3,72M | P4: 0.028 | T4: 42022 | U4: 2051.8 | V4: 2020.8 | W4: 2064.6 | X4: 2004.5 | Z4: 0.016
A5: 42011 | B5: 22.78 | C5: 22.3 | D5: 23.09 | E5: 22.22 | F5: 1,05M | G5: 0.0294 | J5: 42029 | K5: 24.87 | L5: 24.62 | M5: 25.58 | N5: 24.52 | O5: 5,29M | P5: 0.0102 | T5: 42029 | U5: 1995 | V5: 2050.4 | W5: 2057.6 | X5: 1989.2 | Z5: -0.0277
A6: 42012 | B6: 23.82 | C6: 23.01 | D6: 23.83 | E6: 22.79 | F6: 890,73K | G6: 0.0457 | J6: 42036 | K6: 24.3 | L6: 24.9 | M6: 25.8 | N6: 23.72 | O6: 7,00M | P6: -0.0229 | T6: 42036 | U6: 2055.5 | V6: 1996.7 | W6: 2072.4 | X6: 1980.9 | Z6: 0.0303
A7: 42013 | B7: 23.87 | C7: 23.8 | D7: 23.95 | E7: 23.66 | F7: 1,04M | G7: 0.0021 | J7: 42043 | K7: 23.7 | L7: 24.29 | M7: 24.4 | N7: 23.04 | O7: 9,02M | P7: -0.0247 | T7: 42043 | U7: 2097 | V7: 2053.5 | W7: 2097 | X7: 2041.9 | Z7: 0.0202
A8: 42016 | B8: 23.44 | C8: 23.85 | D8: 23.85 | E8: 23.35 | F8: 1,10M | G8: -0.018 | J8: 42050 | K8: 23.5 | L8: 23.78 | M8: 23.9 | N8: 23.03 | O8: 3,97M | P8: -0.0084 | T8: 42050 | U8: 2110.3 | V8: 2096.5 | W8: 2110.6 | X8: 2085.4 | Z8: 0.0063
A9: 42017 | B9: 23.96 | C9: 23.67 | D9: 24 | E9: 23.45 | F9: 2,11M | G9: 0.0222 | J9: 42057 | K9: 23.32 | L9: 23.43 | M9: 23.78 | N9: 22.85 | O9: 6,63M | P9: -0.0077 | T9: 42057 | U9: 2104.5 | V9: 2109.8 | W9: 2119.6 | X9: 2103 | Z9: -0.0027
A10: 42018 | B10: 24.1 | C10: 23.63 | D10: 24.26 | E10: 23.45 | F10: 1,22M | G10: 0.0058 | J10: 42064 | K10: 22.28 | L10: 23.38 | M10: 23.52 | N10: 22 | O10: 7,11M | P10: -0.0446 | T10: 42064 | U10: 2071.3 | V10: 2105.2 | W10: 2117.5 | X10: 2067.3 | Z10: -0.0158
A11: 42019 | B11: 23.52 | C11: 24.11 | D11: 24.35 | E11: 23.3 | F11: 1,06M | G11: -0.0241 | J11: 42071 | K11: 22.53 | L11: 22.32 | M11: 22.6 | N11: 21.49 | O11: 5,72M | P11: 0.0112 | T11: 42071 | U11: 2053.4 | V11: 2072.2 | W11: 2083.5 | X11: 2039.7 | Z11: -0.0086
A12: 42020 | B12: 23.95 | C12: 23.55 | D12: 24.05 | E12: 23.11 | F12: 865,65K | G12: 0.0183 | J12: 42078 | K12: 22.24 | L12: 22.66 | M12: 22.77 | N12: 21.86 | O12: 4,24M | P12: -0.0129 | T12: 42078 | U12: 2108.1 | V12: 2055.3 | W12: 2113.9 | X12: 2055.3 | Z12: 0.0266
A13: 42024 | B13: 23.92 | C13: 24.03 | D13: 24.08 | E13: 23.48 | F13: 656,46K | G13: -0.0013 | J13: 42085 | K13: 21.07 | L13: 22.23 | M13: 22.43 | N13: 20.96 | O13: 6,86M | P13: -0.0526 | T13: 42085 | U13: 2061 | V13: 2108 | W13: 2114.9 | X13: 2045.5 | Z13: -0.0223
... A523: 42762 | B523: 21.18 | C523: 21.25 | D523: 21.31 | E523: 21.09 | F523: 1,79M | G523: -0.0231 | J523: 45655 | K523: 169.06 | L523: 167.95 | M523: 169.43 | N523: 163.05 | O523: 10,99M | P523: -0.0072 | T523: 45655 | U523: 5942.47 | V523: 5920.67 | W523: 5949.34 | X523: 5829.53 | Z523: -0.0048
A524: 42765 | B524: 21.03 | C524: 21.14 | D524: 21.14 | E524: 20.88 | F524: 849,15K | G524: -0.0071
A525: 42766 | B525: 21.24 | C525: 20.87 | D525: 21.45 | E525: 20.75 | F525: 811,12K | G525: 0.01
A526: 42767 | B526: 21.43 | C526: 21.29 | D526: 21.7 | E526: 21.02 | F526: 638,20K | G526: 0.0089
A527: 42768 | B527: 21.7 | C527: 21.48 | D527: 21.71 | E527: 21.21 | F527: 969,50K | G527: 0.0126
A528: 42769 | B528: 22.13 | C528: 22.32 | D528: 22.45 | E528: 21.81 | F528: 1,80M | G528: 0.0198
A529: 42772 | B529: 22.14 | C529: 22.33 | D529: 22.45 | E529: 22.14 | F529: 1,64M | G529: 0.0005
A530: 42773 | B530: 22.81 | C530: 22.35 | D530: 22.93 | E530: 22.21 | F530: 2,18M | G530: 0.0303
A531: 42774 | B531: 22.91 | C531: 22.91 | D531: 23.39 | E531: 22.6 | F531: 2,46M | G531: 0.0044
A532: 42775 | B532: 23.55 | C532: 23.43 | D532: 24 | E532: 23.2 | F532: 1,66M | G532: 0.0279
A533: 42776 | B533: 23.62 | C533: 23.8 | D533: 23.84 | E533: 23.34 | F533: 1,98M | G533: 0.003
A534: 42779 | B534: 23.34 | C534: 23.83 | D534: 23.93 | E534: 23.33 | F534: 1,24M | G534: -0.0119
A535: 42780 | B535: 23.34 | C535: 23.31 | D535: 23.47 | E535: 23.08 | F535: 919,49K | G535: 0
... A2517: 45657 | B2517: 165.16 | C2517: 167 | D2517: 167.6 | E2517: 164.93 | F2517: 2,82M | G2517: -0.0081

Sheet Statistics 1
B4: EQUITY | D4: Change % by day | G4: Time span | J4: Returns statistics | M4: Frequency table | U4: Normal distribution
B5: Date | C5: Price | D5: Var % | E5: Ln Var % | G5: Start date: | H5: 42005 | J5: Average price | K5: =AVERAGE(C6:C3709) -> 49.433474 | M5: Class | N5: Abs Freq | O5: Rel Freq | P5: Cum Freq | Q5: Cum Rel Freq | R5: Sum Data | U5: Abs | V5: Cum | AJ5: Date | AK5: 1 + var % | AM5: Avg var % 90d | AN5: Volat 90d | AQ5: Avg var % 90d | AR5: Volat 90d | AT5: Geometric mean | AW5: Quartile var %
B6: 42006 | C6: 23.57 | G6: Last date: | H6: 45657 | J6: Average Var % | K6: =AVERAGE(D7:D3709) -> 0.0010357652 | M6: =MIN(D7:D2521) -> -0.15901235 | N6: {=FREQUENCY($D$7:$D$3709,M6:M26)} -> 1 | O6: =N6/$K$16 -> 0.00039761431 | P6: =N6 -> 1 | Q6: =P6/$K$16 -> 0.00039761431 | U6: =_xlfn.NORM.DIST(M6,$K$6,$K$8,FALSE) -> 4.5386211e-10 | V6: =_xlfn.NORM.DIST(M6,$K$6,$K$8,TRUE) -> 1.4614981e-12 | AJ6: 42006 | AP6: Avg | AQ6: =AVERAGE(AM7:AM3709) -> 0.0010214753 | AR6: =AVERAGE(AN7:AN3709) -> 0.021249974 | AT6: =GEOMEAN(AL7:AL3709)-1 -> #NUM! | AW6: 1 | AX6: =QUARTILE(D7:D3709,AW6) -> -0.0099019379
B7: 42009 | C7: 22.85 | D7: =((C7-C6)/C6) -> -0.030547306 | E7: =IF(C7=C6, 0, LN(C7/C6)) -> -0.0310236 | J7: Median | K7: =MEDIAN(C6:C3709) -> 40.715 | M7: =M6+$K$8 -> -0.13608734 | N7: 0 | O7: =N7/$K$16 -> 0 | P7: =P6+N7 -> 1 | Q7: =P7/$K$16 -> 0.00039761431 | U7: =_xlfn.NORM.DIST(M7,$K$6,$K$8,FALSE) -> 2.9631281e-07 | V7: =_xlfn.NORM.DIST(M7,$K$6,$K$8,TRUE) -> 1.1062918e-09 | AJ7: 42009 | AK7: =1 + D7 -> 0.96945269 | AL7: =1 + E7 -> 0.9689764 | AM7: =AVERAGE(D7:D97) -> -0.00082143167 | AN7: =STDEV(D7:D97) -> 0.014707578 | AP7: Std dev | AQ7: =STDEV(AM7:AM3708) -> 0.0021004301 | AR7: =STDEV(AN7:AN3708) -> 0.0088252081 | AW7: 2 | AX7: =QUARTILE(D8:D3710,AW7) -> 0.0012895159
B8: 42010 | C8: 22.13 | D8: =((C8-C7)/C7) -> -0.031509847 | E8: =IF(C8=C7, 0, LN(C8/C7)) -> -0.032016963 | J8: Standard Deviation | K8: =_xlfn.STDEV.S(D7:D3709) -> 0.022925004 | M8: =M7+$K$8 -> -0.11316234 | N8: 2 | O8: =N8/$K$16 -> 0.00079522863 | P8: =P7+N8 -> 3 | Q8: =P8/$K$16 -> 0.0011928429 | U8: =_xlfn.NORM.DIST(M8,$K$6,$K$8,FALSE) -> 7.1167621e-05 | V8: =_xlfn.NORM.DIST(M8,$K$6,$K$8,TRUE) -> 3.1566614e-07 | AJ8: 42010 | AK8: =1 + D8 -> 0.96849015 | AL8: =1 + E8 -> 0.96798304 | AM8: =AVERAGE(D8:D98) -> -0.00037920533 | AN8: =STDEV(D8:D98) -> 0.01440576 | AP8: Max | AQ8: =MAX(AM7:AM3708) -> 0.0091809583 | AR8: =MAX(AN7:AN3708) -> 0.06260939 | AT8: Harmonic mean | AW8: 3 | AX8: =QUARTILE(D9:D3711,AW8) -> 0.012353706
B9: 42011 | C9: 22.78 | D9: =((C9-C8)/C8) -> 0.029371893 | E9: =IF(C9=C8, 0, LN(C9/C8)) -> 0.028948804 | J9: Kurtosis | K9: =KURT(D7:D3709) -> 12.587162 | M9: =M8+$K$8 -> -0.090237333 | N9: 5 | O9: =N9/$K$16 -> 0.0019880716 | P9: =P8+N9 -> 8 | Q9: =P9/$K$16 -> 0.0031809145 | U9: =_xlfn.NORM.DIST(M9,$K$6,$K$8,FALSE) -> 0.006288108 | V9: =_xlfn.NORM.DIST(M9,$K$6,$K$8,TRUE) -> 3.4258508e-05 | AJ9: 42011 | AK9: =1 + D9 -> 1.0293719 | AL9: =1 + E9 -> 1.0289488 | AM9: =AVERAGE(D9:D99) -> -0.00010831372 | AN9: =STDEV(D9:D99) -> 0.014041021 | AP9: Min | AQ9: =MIN(AM7:AM3708) -> -0.017901165 | AR9: =MIN(AN7:AN3708) -> 0.0085069386 | AT9: =HARMEAN(AK7:AK3709)-1 -> 0.00051341009 | AW9: 4 | AX9: =QUARTILE(D10:D3712,AW9) -> 0.26237263
B10: 42012 | C10: 23.82 | D10: =((C10-C9)/C9) -> 0.045654083 | E10: =IF(C10=C9, 0, LN(C10/C9)) -> 0.044642606 | J10: Skewness | K10: =_xlfn.SKEW.P(D7:D3709) -> 0.50435697 | M10: =M9+$K$8 -> -0.067312328 | N10: 10 | O10: =N10/$K$16 -> 0.0039761431 | P10: =P9+N10 -> 18 | Q10: =P10/$K$16 -> 0.0071570577 | U10: =_xlfn.NORM.DIST(M10,$K$6,$K$8,FALSE) -> 0.2043916 | V10: =_xlfn.NORM.DIST(M10,$K$6,$K$8,TRUE) -> 0.0014347739 | AJ10: 42012 | AK10: =1 + D10 -> 1.0456541 | AL10: =1 + E10 -> 1.0446426 | AM10: =AVERAGE(D10:D100) -> -0.00051203214 | AN10: =STDEV(D10:D100) -> 0.013708185
B11: 42013 | C11: 23.87 | D11: =((C11-C10)/C10) -> 0.0020990764 | E11: =IF(C11=C10, 0, LN(C11/C10)) -> 0.0020968764 | J11: Minimum | K11: =MIN(D7:D3709) -> -0.15901235 | M11: =M10+$K$8 -> -0.044387324 | N11: 40 | O11: =N11/$K$16 -> 0.015904573 | P11: =P10+N11 -> 58 | Q11: =P11/$K$16 -> 0.02306163 | U11: =_xlfn.NORM.DIST(M11,$K$6,$K$8,FALSE) -> 2.4440587 | V11: =_xlfn.NORM.DIST(M11,$K$6,$K$8,TRUE) -> 0.023774475 | AJ11: 42013 | AK11: =1 + D11 -> 1.0020991 | AL11: =1 + E11 -> 1.0020969 | AM11: =AVERAGE(D11:D101) -> -0.0008913987 | AN11: =STDEV(D11:D101) -> 0.012868333
B12: 42016 | C12: 23.44 | D12: =((C12-C11)/C11) -> -0.018014244 | E12: =IF(C12=C11, 0, LN(C12/C11)) -> -0.018178476 | J12: Maximum | K12: =MAX(D7:D3709) -> 0.26237263 | M12: =M11+$K$8 -> -0.021462319 | N12: 236 | O12: =N12/$K$16 -> 0.093836978 | P12: =P11+N12 -> 294 | Q12: =P12/$K$16 -> 0.11689861 | U12: =_xlfn.NORM.DIST(M12,$K$6,$K$8,FALSE) -> 10.751417 | V12: =_xlfn.NORM.DIST(M12,$K$6,$K$8,TRUE) -> 0.1632033 | AJ12: 42016 | AK12: =1 + D12 -> 0.98198576 | AL12: =1 + E12 -> 0.98182152 | AM12: =AVERAGE(D12:D102) -> -0.00097495544 | AN12: =STDEV(D12:D102) -> 0.012873385
B13: 42017 | C13: 23.96 | D13: =((C13-C12)/C12) -> 0.0221843 | E13: =IF(C13=C12, 0, LN(C13/C12)) -> 0.021941809 | J13: Range | K13: =K12-K11 -> 0.42138498 | M13: =M12+$K$8 -> 0.001462685 | N13: 976 | O13: =N13/$K$16 -> 0.38807157 | P13: =P12+N13 -> 1270 | Q13: =P13/$K$16 -> 0.50497018 | U13: =_xlfn.NORM.DIST(M13,$K$6,$K$8,FALSE) -> 17.399042 | V13: =_xlfn.NORM.DIST(M13,$K$6,$K$8,TRUE) -> 0.50742885 | AJ13: 42017 | AK13: =1 + D13 -> 1.0221843 | AL13: =1 + E13 -> 1.0219418 | AM13: =AVERAGE(D13:D103) -> -0.00074151559 | AN13: =STDEV(D13:D103) -> 0.012753012
B14: 42018 | C14: 24.1 | D14: =((C14-C13)/C13) -> 0.0058430718 | E14: =IF(C14=C13, 0, LN(C14/C13)) -> 0.0058260672 | J14: Sample Variance | K14: =VARPA(D7:D3709) -> 0.00052534686 | M14: =M13+$K$8 -> 0.024387689 | N14: 982 | O14: =N14/$K$16 -> 0.39045726 | P14: =P13+N14 -> 2252 | Q14: =P14/$K$16 -> 0.89542744 | U14: =_xlfn.NORM.DIST(M14,$K$6,$K$8,FALSE) -> 10.358347 | V14: =_xlfn.NORM.DIST(M14,$K$6,$K$8,TRUE) -> 0.84580888 | AJ14: 42018 | AK14: =1 + D14 -> 1.0058431 | AL14: =1 + E14 -> 1.0058261 | AM14: =AVERAGE(D14:D104) -> -0.00096003702 | AN14: =STDEV(D14:D104) -> 0.01252413
B15: 42019 | C15: 23.52 | D15: =((C15-C14)/C14) -> -0.02406639 | E15: =IF(C15=C14, 0, LN(C15/C14)) -> -0.024360717 | J15: Standard Error | K15: =_xlfn.STDEV.S(D7:D3709)/SQRT(K16) -> 0.00045713075 | M15: =M14+$K$8 -> 0.047312694 | N15: 209 | O15: =N15/$K$16 -> 0.083101392 | P15: =P14+N15 -> 2461 | Q15: =P15/$K$16 -> 0.97852883 | U15: =_xlfn.NORM.DIST(M15,$K$6,$K$8,FALSE) -> 2.2686166 | V15: =_xlfn.NORM.DIST(M15,$K$6,$K$8,TRUE) -> 0.97823676 | AJ15: 42019 | AK15: =1 + D15 -> 0.97593361 | AL15: =1 + E15 -> 0.97563928 | AM15: =AVERAGE(D15:D105) -> -0.00093855248 | AN15: =STDEV(D15:D105) -> 0.012537599
B16: 42020 | C16: 23.95 | D16: =((C16-C15)/C15) -> 0.018282313 | E16: =IF(C16=C15, 0, LN(C16/C15)) -> 0.018117201 | J16: Count | K16: =COUNTA(D6:D3709) -> 2515 | M16: =M15+$K$8 -> 0.070237698 | N16: 44 | O16: =N16/$K$16 -> 0.01749503 | P16: =P15+N16 -> 2505 | Q16: =P16/$K$16 -> 0.99602386 | U16: =_xlfn.NORM.DIST(M16,$K$6,$K$8,FALSE) -> 0.18278362 | V16: =_xlfn.NORM.DIST(M16,$K$6,$K$8,TRUE) -> 0.99873037 | AJ16: 42020 | AK16: =1 + D16 -> 1.0182823 | AL16: =1 + E16 -> 1.0181172 | AM16: =AVERAGE(D16:D106) -> -0.00053903736 | AN16: =STDEV(D16:D106) -> 0.012370568
B17: 42024 | C17: 23.92 | D17: =((C17-C16)/C16) -> -0.0012526096 | E17: =IF(C17=C16, 0, LN(C17/C16)) -> -0.0012533948 | M17: =M16+$K$8 -> 0.093162702 | N17: 5 | O17: =N17/$K$16 -> 0.0019880716 | P17: =P16+N17 -> 2510 | Q17: =P17/$K$16 -> 0.99801193 | U17: =_xlfn.NORM.DIST(M17,$K$6,$K$8,FALSE) -> 0.0054177501 | V17: =_xlfn.NORM.DIST(M17,$K$6,$K$8,TRUE) -> 0.99997073 | AJ17: 42024 | AK17: =1 + D17 -> 0.99874739 | AL17: =1 + E17 -> 0.99874661 | AM17: =AVERAGE(D17:D107) -> -0.00075970631 | AN17: =STDEV(D17:D107) -> 0.012209148
B18: 42025 | C18: 24.23 | D18: =((C18-C17)/C17) -> 0.012959866 | E18: =IF(C18=C17, 0, LN(C18/C17)) -> 0.012876606 | M18: =M17+$K$8 -> 0.11608771 | N18: 1 | O18: =N18/$K$16 -> 0.00039761431 | P18: =P17+N18 -> 2511 | Q18: =P18/$K$16 -> 0.99840954 | U18: =_xlfn.NORM.DIST(M18,$K$6,$K$8,FALSE) -> 5.9075332e-05 | V18: =_xlfn.NORM.DIST(M18,$K$6,$K$8,TRUE) -> 0.99999974 | AJ18: 42025 | AK18: =1 + D18 -> 1.0129599 | AL18: =1 + E18 -> 1.0128766 | AM18: =AVERAGE(D18:D108) -> -0.00070634133 | AN18: =STDEV(D18:D108) -> 0.01221758
B19: 42026 | C19: 24.79 | D19: =((C19-C18)/C18) -> 0.023111845 | E19: =IF(C19=C18, 0, LN(C19/C18)) -> 0.022848811 | M19: =M18+$K$8 -> 0.13901271 | N19: 1 | O19: =N19/$K$16 -> 0.00039761431 | P19: =P18+N19 -> 2512 | Q19: =P19/$K$16 -> 0.99880716 | U19: =_xlfn.NORM.DIST(M19,$K$6,$K$8,FALSE) -> 2.3697301e-07 | V19: =_xlfn.NORM.DIST(M19,$K$6,$K$8,TRUE) -> 1 | AJ19: 42026 | AK19: =1 + D19 -> 1.0231118 | AL19: =1 + E19 -> 1.0228488 | AM19: =AVERAGE(D19:D109) -> -0.00078957067 | AN19: =STDEV(D19:D109) -> 0.012149053
B20: 42027 | C20: 24.62 | D20: =((C20-C19)/C19) -> -0.0068576039 | E20: =IF(C20=C19, 0, LN(C20/C19)) -> -0.0068812253 | M20: =M19+$K$8 -> 0.16193772 | N20: 1 | O20: =N20/$K$16 -> 0.00039761431 | P20: =P19+N20 -> 2513 | Q20: =P20/$K$16 -> 0.99920477 | U20: =_xlfn.NORM.DIST(M20,$K$6,$K$8,FALSE) -> 3.4970121e-10 | V20: =_xlfn.NORM.DIST(M20,$K$6,$K$8,TRUE) -> 1 | AJ20: 42027 | AK20: =1 + D20 -> 0.9931424 | AL20: =1 + E20 -> 0.99311877 | AM20: =AVERAGE(D20:D110) -> -0.00080316237 | AN20: =STDEV(D20:D110) -> 0.01212268
B21: 42030 | C21: 25.16 | D21: =((C21-C20)/C20) -> 0.021933387 | E21: =IF(C21=C20, 0, LN(C21/C20)) -> 0.021696311 | M21: =M20+$K$8 -> 0.18486272 | N21: 0 | O21: =N21/$K$16 -> 0 | P21: =P20+N21 -> 2513 | Q21: =P21/$K$16 -> 0.99920477 | U21: =_xlfn.NORM.DIST(M21,$K$6,$K$8,FALSE) -> 1.8984575e-13 | V21: =_xlfn.NORM.DIST(M21,$K$6,$K$8,TRUE) -> 1 | AJ21: 42030 | AK21: =1 + D21 -> 1.0219334 | AL21: =1 + E21 -> 1.0216963 | AM21: =AVERAGE(D21:D111) -> -0.00080461674 | AN21: =STDEV(D21:D111) -> 0.012123422
B22: 42031 | C22: 25.26 | D22: =((C22-C21)/C21) -> 0.0039745628 | E22: =IF(C22=C21, 0, LN(C22/C21)) -> 0.0039666851 | M22: =M21+$K$8 -> 0.20778772 | N22: 1 | O22: =N22/$K$16 -> 0.00039761431 | P22: =P21+N22 -> 2514 | Q22: =P22/$K$16 -> 0.99960239 | U22: =_xlfn.NORM.DIST(M22,$K$6,$K$8,FALSE) -> 3.7914922e-17 | V22: =_xlfn.NORM.DIST(M22,$K$6,$K$8,TRUE) -> 1 | AJ22: 42031 | AK22: =1 + D22 -> 1.0039746 | AL22: =1 + E22 -> 1.0039667 | AM22: =AVERAGE(D22:D112) -> -0.0011955151 | AN22: =STDEV(D22:D112) -> 0.011954426
B23: 42032 | C23: 25.21 | D23: =((C23-C22)/C22) -> -0.0019794141 | E23: =IF(C23=C22, 0, LN(C23/C22)) -> -0.0019813757 | M23: =M22+$K$8 -> 0.23071273 | N23: 0 | O23: =N23/$K$16 -> 0 | P23: =P22+N23 -> 2514 | Q23: =P23/$K$16 -> 0.99960239 | U23: =_xlfn.NORM.DIST(M23,$K$6,$K$8,FALSE) -> 2.7856398e-21 | V23: =_xlfn.NORM.DIST(M23,$K$6,$K$8,TRUE) -> 1 | AJ23: 42032 | AK23: =1 + D23 -> 0.99802059 | AL23: =1 + E23 -> 0.99801862 | AM23: =AVERAGE(D23:D113) -> -0.0013470231 | AN23: =STDEV(D23:D113) -> 0.011975523
B24: 42033 | C24: 25.05 | D24: =((C24-C23)/C23) -> -0.0063466878 | E24: =IF(C24=C23, 0, LN(C24/C23)) -> -0.0063669137 | M24: =M23+$K$8 -> 0.25363773 | N24: 0 | O24: =N24/$K$16 -> 0 | P24: =P23+N24 -> 2514 | Q24: =P24/$K$16 -> 0.99960239 | U24: =_xlfn.NORM.DIST(M24,$K$6,$K$8,FALSE) -> 7.5291382e-26 | V24: =_xlfn.NORM.DIST(M24,$K$6,$K$8,TRUE) -> 1 | AJ24: 42033 | AK24: =1 + D24 -> 0.99365331 | AL24: =1 + E24 -> 0.99363309 | AM24: =AVERAGE(D24:D114) -> -0.0017014717 | AN24: =STDEV(D24:D114) -> 0.012461906
B25: 42034 | C25: 24.87 | D25: =((C25-C24)/C24) -> -0.0071856287 | E25: =IF(C25=C24, 0, LN(C25/C24)) -> -0.0072115697 | M25: =M24+$K$8 -> 0.27656274 | N25: 1 | O25: =N25/$K$16 -> 0.00039761431 | P25: =P24+N25 -> 2515 | Q25: =P25/$K$16 -> 1 | U25: =_xlfn.NORM.DIST(M25,$K$6,$K$8,FALSE) -> 7.4863667e-31 | V25: =_xlfn.NORM.DIST(M25,$K$6,$K$8,TRUE) -> 1 | AJ25: 42034 | AK25: =1 + D25 -> 0.99281437 | AL25: =1 + E25 -> 0.99278843 | AM25: =AVERAGE(D25:D115) -> -0.0016061005 | AN25: =STDEV(D25:D115) -> 0.01245917
B26: 42037 | C26: 24.84 | D26: =((C26-C25)/C25) -> -0.0012062726 | E26: =IF(C26=C25, 0, LN(C26/C25)) -> -0.0012070008 | M26: =M25+$K$8 -> 0.29948774 | N26: 0 | O26: =N26/$K$16 -> 0 | P26: =P25+N26 -> 2515 | Q26: =P26/$K$16 -> 1 | U26: =_xlfn.NORM.DIST(M26,$K$6,$K$8,FALSE) -> 2.7384351e-36 | V26: =_xlfn.NORM.DIST(M26,$K$6,$K$8,TRUE) -> 1 | AJ26: 42037 | AK26: =1 + D26 -> 0.99879373 | AL26: =1 + E26 -> 0.998793 | AM26: =AVERAGE(D26:D116) -> -0.0015015698 | AN26: =STDEV(D26:D116) -> 0.01245174
B27: 42038 | C27: 25.69 | D27: =((C27-C26)/C26) -> 0.034219002 | E27: =IF(C27=C26, 0, LN(C27/C26)) -> 0.033646554 | AJ27: 42038 | AK27: =1 + D27 -> 1.034219 | AL27: =1 + E27 -> 1.0336466 | AM27: =AVERAGE(D27:D117) -> -0.0015546359 | AN27: =STDEV(D27:D117) -> 0.012460754
B28: 42039 | C28: 25.16 | D28: =((C28-C27)/C27) -> -0.020630596 | E28: =IF(C28=C27, 0, LN(C28/C27)) -> -0.020846379 | AJ28: 42039 | AK28: =1 + D28 -> 0.9793694 | AL28: =1 + E28 -> 0.97915362 | AM28: =AVERAGE(D28:D118) -> -0.0019871281 | AN28: =STDEV(D28:D118) -> 0.011874529
B29: 42040 | C29: 24.55 | D29: =((C29-C28)/C28) -> -0.024244833 | E29: =IF(C29=C28, 0, LN(C29/C28)) -> -0.024543578 | AJ29: 42040 | AK29: =1 + D29 -> 0.97575517 | AL29: =1 + E29 -> 0.97545642 | AM29: =AVERAGE(D29:D119) -> -0.0017655774 | AN29: =STDEV(D29:D119) -> 0.011709757
B30: 42041 | C30: 24.3 | D30: =((C30-C29)/C29) -> -0.010183299 | E30: =IF(C30=C29, 0, LN(C30/C29)) -> -0.010235504 | AJ30: 42041 | AK30: =1 + D30 -> 0.9898167 | AL30: =1 + E30 -> 0.9897645 | AM30: =AVERAGE(D30:D120) -> -0.0014888275 | AN30: =STDEV(D30:D120) -> 0.011467678
B31: 42044 | C31: 23.93 | D31: =((C31-C30)/C30) -> -0.015226337 | E31: =IF(C31=C30, 0, LN(C31/C30)) -> -0.015343448 | AJ31: 42044 | AK31: =1 + D31 -> 0.98477366 | AL31: =1 + E31 -> 0.98465655 | AM31: =AVERAGE(D31:D121) -> -0.0012119074 | AN31: =STDEV(D31:D121) -> 0.011559286
B32: 42045 | C32: 23.76 | D32: =((C32-C31)/C31) -> -0.0071040535 | E32: =IF(C32=C31, 0, LN(C32/C31)) -> -0.0071294074 | AJ32: 42045 | AK32: =1 + D32 -> 0.99289595 | AL32: =1 + E32 -> 0.99287059 | AM32: =AVERAGE(D32:D122) -> -0.0010242632 | AN32: =STDEV(D32:D122) -> 0.011467491
B33: 42046 | C33: 24.03 | D33: =((C33-C32)/C32) -> 0.011363636 | E33: =IF(C33=C32, 0, LN(C33/C32)) -> 0.011299555 | AJ33: 42046 | AK33: =1 + D33 -> 1.0113636 | AL33: =1 + E33 -> 1.0112996 | AM33: =AVERAGE(D33:D123) -> -0.00063686139 | AN33: =STDEV(D33:D123) -> 0.011848952
B34: 42047 | C34: 23.34 | D34: =((C34-C33)/C33) -> -0.028714107 | E34: =IF(C34=C33, 0, LN(C34/C33)) -> -0.029134423 | AJ34: 42047 | AK34: =1 + D34 -> 0.97128589 | AL34: =1 + E34 -> 0.97086558 | AM34: =AVERAGE(D34:D124) -> -0.00057924396 | AN34: =STDEV(D34:D124) -> 0.011920486
B35: 42048 | C35: 23.7 | D35: =((C35-C34)/C34) -> 0.015424165 | E35: =IF(C35=C34, 0, LN(C35/C34)) -> 0.015306421 | AJ35: 42048 | AK35: =1 + D35 -> 1.0154242 | AL35: =1 + E35 -> 1.0153064 | AM35: =AVERAGE(D35:D125) -> -0.00029766594 | AN35: =STDEV(D35:D125) -> 0.011545245
B36: 42052 | C36: 23.68 | D36: =((C36-C35)/C35) -> -0.00084388186 | E36: =IF(C36=C35, 0, LN(C36/C35)) -> -0.00084423813 | AJ36: 42052 | AK36: =1 + D36 -> 0.99915612 | AL36: =1 + E36 -> 0.99915576 | AM36: =AVERAGE(D36:D126) -> -0.00044282875 | AN36: =STDEV(D36:D126) -> 0.01142782
B37: 42053 | C37: 23.33 | D37: =((C37-C36)/C36) -> -0.014780405 | E37: =IF(C37=C36, 0, LN(C37/C36)) -> -0.014890724 | AJ37: 42053 | AK37: =1 + D37 -> 0.98521959 | AL37: =1 + E37 -> 0.98510928 | AM37: =AVERAGE(D37:D127) -> -0.00054038619 | AN37: =STDEV(D37:D127) -> 0.011469102
B38: 42054 | C38: 23.48 | D38: =((C38-C37)/C37) -> 0.0064294899 | E38: =IF(C38=C37, 0, LN(C38/C37)) -> 0.0064089089 | AJ38: 42054 | AK38: =1 + D38 -> 1.0064295 | AL38: =1 + E38 -> 1.0064089 | AM38: =AVERAGE(D38:D128) -> -0.00050545825 | AN38: =STDEV(D38:D128) -> 0.011430026
... B2520: 45656 | C2520: 166.51 | D2520: =((C2520-C2519)/C2519) -> -0.022140005 | E2520: =IF(C2520=C2519, 0, LN(C2520/C2519)) -> -0.022388773 | AJ2520: 45656 | AK2520: =1 + D2520 -> 0.97786 | AL2520: =1 + E2520 -> 0.97761123 | AM2520: =AVERAGE(D2520:D2610) -> -0.015123813 | AN2520: =STDEV(D2520:D2610) -> 0.0099223936
B2521: 45657 | C2521: 165.16 | D2521: =((C2521-C2520)/C2520) -> -0.0081076212 | E2521: =IF(C2521=C2520, 0, LN(C2521/C2520)) -> -0.0081406667 | AJ2521: 45657 | AK2521: =1 + D2521 -> 0.99189238 | AL2521: =1 + E2521 -> 0.99185933 | AM2521: =AVERAGE(D2521:D2611) -> -0.0081076212

Sheet Beta
B2: SPX index (x) | E2: Apollo Global Mgmt (y) | I2: Classic Beta | U2: Beta +/-
B3: Date | C3: Price | E3: Date | F3: Price | I3: Z | K3: Y | U3: Z | X3: Y | AI3: Min Beta | AJ3: Max Beta | AM3: Beta | AN3: Beta + / Beta -
B4: 42008 | C4: 2044.8 | E4: 42008 | F4: 23.87 | J4: x | K4: y | M4: Z'*Z | P4: Linest | V4: x | W4: mod x | X4: y | Z4: Z'*Z | AD4: Linest | AI4: =MIN(J6:J532) -> -0.14979602 | AJ4: =MAX(J6:J532) -> 0.12101742 | AL4: -0.15 | AM4: =$M$18*AL4+$M$20 -> -0.21345607 | AN4: =$AA$21*AL4-$Z$17 -> -0.23917787 | BH4: x | BI4: y | BK4: Dates | BL4: Beta 52w | BM4: Volat 52w
B5: 42015 | C5: 2019.4 | E5: 42015 | F5: 23.95 | I5: 1 | J5: 0 | K5: 0 | M5: {=MMULT(TRANSPOSE(I6:J525),I6:J525)} -> 520 | N5: 1.2153812 | P5: {=LINEST(K6:K525,J6:J525,TRUE,TRUE)} -> 1.4345162 | Q5: 0.001721361 | U5: 1 | V5: =C5/C4-1 -> -0.012421753 | W5: =ABS(V5) -> 0.012421753 | X5: =F5/F4-1 -> 0.0033514872 | Z5: {=MMULT(TRANSPOSE(U5:W525),U5:W525)} -> 521 | AA5: 1.2106298 | AB5: 8.577733 | AD5: {=LINEST(X5:X525,V5:W525,TRUE,TRUE)} -> 0.15862893 | AE5: 1.4419675 | AF5: -0.00091158987 | AL5: =AL4+0.5% -> -0.145 | AM5: =$M$18*AL5+$M$20 -> -0.20628349 | AN5: =$AA$21*AL5-$Z$17 -> -0.23117489 | BH5: 0 | BI5: 0 | BK5: 42008 | BL5: / | BM5: /
B6: 42022 | C6: 2051.8 | E6: 42022 | F6: 24.62 | I6: 1 | J6: =C5/C4-1 -> -0.012421753 | K6: =F5/F4-1 -> 0.0033514872 | M6: 1.2153812 | N6: 0.28542858 | P6: 0.072642094 | Q6: 0.0017019054 | U6: 1 | V6: =C6/C5-1 -> 0.01604437 | W6: =ABS(V6) -> 0.01604437 | X6: =F6/F5-1 -> 0.027974948 | Z6: 1.2106298 | AA6: 0.28545115 | AB6: 0.0067477555 | AD6: 0.10166041 | AE6: 0.072620735 | AF6: 0.0023907166 | AL6: =AL5+0.5% -> -0.14 | AM6: =$M$18*AL6+$M$20 -> -0.1991109 | AN6: =$AA$21*AL6-$Z$17 -> -0.2231719 | BH6: =C5/C4-1 -> -0.012421753 | BI6: =F5/F4-1 -> 0.0033514872 | BK6: 42015 | BL6: / | BM6: /
B7: 42029 | C7: 1995 | E7: 42029 | F7: 24.87 | I7: 1 | J7: =C6/C5-1 -> 0.01604437 | K7: =F6/F5-1 -> 0.027974948 | M7: Inverse(Z*Z') | P7: 0.42949826 | Q7: 0.038615809 | U7: 1 | V7: =C7/C6-1 -> -0.02768301 | W7: =ABS(V7) -> 0.02768301 | X7: =F7/F6-1 -> 0.010154346 | Z7: 8.577733 | AA7: 0.0067477555 | AB7: 0.28545115 | AD7: 0.43222683 | AE7: 0.03852548 | AF7: #N/A | AL7: =AL6+0.5% -> -0.135 | AM7: =$M$18*AL7+$M$20 -> -0.19193832 | AN7: =$AA$21*AL7-$Z$17 -> -0.21516892 | BH7: =C6/C5-1 -> 0.01604437 | BI7: =F6/F5-1 -> 0.027974948 | BK7: 42022 | BL7: / | BM7: /
B8: 42036 | C8: 2055.5 | E8: 42036 | F8: 24.3 | I8: 1 | J8: =C7/C6-1 -> -0.02768301 | K8: =F7/F6-1 -> 0.010154346 | M8: {=MINVERSE(M5:N6)} -> 0.0019424084 | N8: -0.0082709542 | P8: 389.97269 | Q8: 518 | U8: 1 | V8: =C8/C7-1 -> 0.030325815 | W8: =ABS(V8) -> 0.030325815 | X8: =F8/F7-1 -> -0.02291918 | Z8: Inverse(Z*Z') | AD8: 197.16809 | AE8: 518 | AF8: #N/A | AL8: =AL7+0.5% -> -0.13 | AM8: =$M$18*AL8+$M$20 -> -0.18476574 | AN8: =$AA$21*AL8-$Z$17 -> -0.20716594 | BH8: =C7/C6-1 -> -0.02768301 | BI8: =F7/F6-1 -> 0.010154346 | BK8: 42029 | BL8: / | BM8: /
B9: 42043 | C9: 2097 | E9: 42043 | F9: 23.7 | I9: 1 | J9: =C8/C7-1 -> 0.030325815 | K9: =F8/F7-1 -> -0.02291918 | M9: -0.0082709542 | N9: 3.5387219 | P9: 0.58151975 | Q9: 0.7724316 | U9: 1 | V9: =C9/C8-1 -> 0.020189735 | W9: =ABS(V9) -> 0.020189735 | X9: =F9/F8-1 -> -0.024691358 | Z9: {=MINVERSE(Z5:AB7)} -> 0.003850881 | AA9: -0.013604165 | AB9: -0.11539638 | AD9: 0.58527872 | AE9: 0.76882214 | AF9: #N/A | AL9: =AL8+0.5% -> -0.125 | AM9: =$M$18*AL9+$M$20 -> -0.17759316 | AN9: =$AA$21*AL9-$Z$17 -> -0.19916296 | BH9: =C8/C7-1 -> 0.030325815 | BI9: =F8/F7-1 -> -0.02291918 | BK9: 42036 | BL9: / | BM9: /
B10: 42050 | C10: 2110.3 | E10: 42050 | F10: 23.5 | I10: 1 | J10: =C9/C8-1 -> 0.020189735 | K10: =F9/F8-1 -> -0.024691358 | M10: Z'*Y | U10: 1 | V10: =C10/C9-1 -> 0.0063423939 | W10: =ABS(V10) -> 0.0063423939 | X10: =F10/F9-1 -> -0.0084388186 | Z10: -0.013604165 | AA10: 3.553245 | AB10: 0.32480677 | AL10: =AL9+0.5% -> -0.12 | AM10: =$M$18*AL10+$M$20 -> -0.17042058 | AN10: =$AA$21*AL10-$Z$17 -> -0.19115998 | BH10: =C9/C8-1 -> 0.020189735 | BI10: =F9/F8-1 -> -0.024691358 | BK10: 42043 | BL10: / | BM10: /
B11: 42057 | C11: 2104.5 | E11: 42057 | F11: 23.32 | I11: 1 | J11: =C10/C9-1 -> 0.0063423939 | K11: =F10/F9-1 -> -0.0084388186 | M11: {=MMULT(TRANSPOSE(I6:J525),K6:K525)} -> 2.6385918 | P11: Beta | Q11: Alpha | U11: 1 | V11: =C11/C10-1 -> -0.0027484244 | W11: =ABS(V11) -> 0.0027484244 | X11: =F11/F10-1 -> -0.0076595745 | Z11: -0.11539638 | AA11: 0.32480677 | AB11: 6.9631796 | AD11: Beta mod | AE11: Beta | AF11: Alpha | AL11: =AL10+0.5% -> -0.115 | AM11: =$M$18*AL11+$M$20 -> -0.163248 | AN11: =$AA$21*AL11-$Z$17 -> -0.183157 | BH11: =C10/C9-1 -> 0.0063423939 | BI11: =F10/F9-1 -> -0.0084388186 | BK11: 42050 | BL11: / | BM11: /
B12: 42064 | C12: 2071.3 | E12: 42064 | F12: 22.28 | I12: 1 | J12: =C11/C10-1 -> -0.0027484244 | K12: =F11/F10-1 -> -0.0076595745 | M12: 0.41154402 | P12: Std err | U12: 1 | V12: =C12/C11-1 -> -0.015775719 | W12: =ABS(V12) -> 0.015775719 | X12: =F12/F11-1 -> -0.044596913 | Z12: Z'*Y | AD12: Std err | AL12: =AL11+0.5% -> -0.11 | AM12: =$M$18*AL12+$M$20 -> -0.15607542 | AN12: =$AA$21*AL12-$Z$17 -> -0.17515401 | BH12: =C11/C10-1 -> -0.0027484244 | BI12: =F11/F10-1 -> -0.0076595745 | BK12: 42057 | BL12: / | BM12: /
B13: 42071 | C13: 2053.4 | E13: 42071 | F13: 22.53 | I13: 1 | J13: =C12/C11-1 -> -0.015775719 | K13: =F12/F11-1 -> -0.044596913 | M13: Alpha e Beta | P13: R^2 | Q13: Std err Y | U13: 1 | V13: =C13/C12-1 -> -0.0086419157 | W13: =ABS(V13) -> 0.0086419157 | X13: =F13/F12-1 -> 0.011220826 | Z13: {=MMULT(TRANSPOSE(U5:W525),X5:X525)} -> 2.6314271 | AD13: R^2 | AE13: Std err Y | AL13: =AL12+0.5% -> -0.105 | AM13: =$M$18*AL13+$M$20 -> -0.14890284 | AN13: =$AA$21*AL13-$Z$17 -> -0.16715103 | BH13: =C12/C11-1 -> -0.015775719 | BI13: =F12/F11-1 -> -0.044596913 | BK13: 42064 | BL13: / | BM13: /
B14: 42078 | C14: 2108.1 | E14: 42078 | F14: 22.24 | I14: 1 | J14: =C13/C12-1 -> -0.0086419157 | K14: =F13/F12-1 -> 0.011220826 | M14: {=MMULT(M8:N9,M11:M12)} -> 0.001721361 | P14: F | Q14: Free | U14: 1 | V14: =C14/C13-1 -> 0.026638745 | W14: =ABS(V14) -> 0.026638745 | X14: =F14/F13-1 -> -0.012871727 | Z14: 0.41157807 | AD14: F | AE14: Free | AL14: =AL13+0.5% -> -0.1 | AM14: =$M$18*AL14+$M$20 -> -0.14173026 | AN14: =$AA$21*AL14-$Z$17 -> -0.15914805 | BH14: =C13/C12-1 -> -0.0086419157 | BI14: =F13/F12-1 -> 0.011220826 | BK14: 42071 | BL14: / | BM14: /
B15: 42085 | C15: 2061 | E15: 42085 | F15: 21.07 | I15: 1 | J15: =C14/C13-1 -> 0.026638745 | K15: =F14/F13-1 -> -0.012871727 | M15: 1.4345162 | P15: SS Reg | Q15: SS Res | U15: 1 | V15: =C15/C14-1 -> -0.022342394 | W15: =ABS(V15) -> 0.022342394 | X15: =F15/F14-1 -> -0.052607914 | Z15: 0.047191482 | AD15: SS Reg | AE15: SS Res | AL15: =AL14+0.5% -> -0.095 | AM15: =$M$18*AL15+$M$20 -> -0.13455768 | AN15: =$AA$21*AL15-$Z$17 -> -0.15114507 | BH15: =C14/C13-1 -> 0.026638745 | BI15: =F14/F13-1 -> -0.012871727 | BK15: 42078 | BL15: / | BM15: /
B16: 42092 | C16: 2067 | E16: 42092 | F16: 21.49 | I16: 1 | J16: =C15/C14-1 -> -0.022342394 | K16: =F15/F14-1 -> -0.052607914 | U16: 1 | V16: =C16/C15-1 -> 0.0029112082 | W16: =ABS(V16) -> 0.0029112082 | X16: =F16/F15-1 -> 0.019933555 | Z16: Alpha, Beta1, Beta2 | AL16: =AL15+0.5% -> -0.09 | AM16: =$M$18*AL16+$M$20 -> -0.1273851 | AN16: =$AA$21*AL16-$Z$17 -> -0.14314209 | BH16: =C15/C14-1 -> -0.022342394 | BI16: =F15/F14-1 -> -0.052607914 | BK16: 42085 | BL16: / | BM16: /
B17: 42099 | C17: 2102.1 | E17: 42099 | F17: 21.25 | I17: 1 | J17: =C16/C15-1 -> 0.0029112082 | K17: =F16/F15-1 -> 0.019933555 | M17: Slope | U17: 1 | V17: =C17/C16-1 -> 0.016981132 | W17: =ABS(V17) -> 0.016981132 | X17: =F17/F16-1 -> -0.011167985 | Z17: {=MMULT(Z9:AB11,Z13:Z15)} -> -0.00091158987 | AL17: =AL16+0.5% -> -0.085 | AM17: =$M$18*AL17+$M$20 -> -0.12021251 | AN17: =$AA$21*AL17-$Z$17 -> -0.1351391 | BH17: =C16/C15-1 -> 0.0029112082 | BI17: =F16/F15-1 -> 0.019933555 | BK17: 42092 | BL17: / | BM17: /
B18: 42106 | C18: 2081.2 | E18: 42106 | F18: 22.06 | I18: 1 | J18: =C17/C16-1 -> 0.016981132 | K18: =F17/F16-1 -> -0.011167985 | M18: =SLOPE(K6:K532,J6:J532) -> 1.4345162 | U18: 1 | V18: =C18/C17-1 -> -0.0099424385 | W18: =ABS(V18) -> 0.0099424385 | X18: =F18/F17-1 -> 0.038117647 | Z18: 1.4419675 | AL18: =AL17+0.5% -> -0.08 | AM18: =$M$18*AL18+$M$20 -> -0.11303993 | AN18: =$AA$21*AL18-$Z$17 -> -0.12713612 | BH18: =C17/C16-1 -> 0.016981132 | BI18: =F17/F16-1 -> -0.011167985 | BK18: 42099 | BL18: / | BM18: /
B19: 42113 | C19: 2117.7 | E19: 42113 | F19: 22.02 | I19: 1 | J19: =C18/C17-1 -> -0.0099424385 | K19: =F18/F17-1 -> 0.038117647 | M19: Intercept | U19: 1 | V19: =C19/C18-1 -> 0.017537959 | W19: =ABS(V19) -> 0.017537959 | X19: =F19/F18-1 -> -0.0018132366 | Z19: 0.15862893 | AL19: =AL18+0.5% -> -0.075 | AM19: =$M$18*AL19+$M$20 -> -0.10586735 | AN19: =$AA$21*AL19-$Z$17 -> -0.11913314 | BH19: =C18/C17-1 -> -0.0099424385 | BI19: =F18/F17-1 -> 0.038117647 | BK19: 42106 | BL19: / | BM19: /
B20: 42120 | C20: 2108.3 | E20: 42120 | F20: 22.88 | I20: 1 | J20: =C19/C18-1 -> 0.017537959 | K20: =F19/F18-1 -> -0.0018132366 | M20: =INTERCEPT(K6:K532,J6:J532) -> 0.001721361 | U20: 1 | V20: =C20/C19-1 -> -0.0044387779 | W20: =ABS(V20) -> 0.0044387779 | X20: =F20/F19-1 -> 0.039055404 | AL20: =AL19+0.5% -> -0.07 | AM20: =$M$18*AL20+$M$20 -> -0.098694772 | AN20: =$AA$21*AL20-$Z$17 -> -0.11113016 | BH20: =C19/C18-1 -> 0.017537959 | BI20: =F19/F18-1 -> -0.0018132366 | BK20: 42113 | BL20: / | BM20: /
B21: 42127 | C21: 2116.1 | E21: 42127 | F21: 21.95 | I21: 1 | J21: =C20/C19-1 -> -0.0044387779 | K21: =F20/F19-1 -> 0.039055404 | U21: 1 | V21: =C21/C20-1 -> 0.0036996632 | W21: =ABS(V21) -> 0.0036996632 | X21: =F21/F20-1 -> -0.040646853 | Z21: Beta + | AA21: =Z18+Z19 -> 1.6005964 | AL21: =AL20+0.5% -> -0.065 | AM21: =$M$18*AL21+$M$20 -> -0.091522191 | AN21: =$AA$21*AL21-$Z$17 -> -0.10312718 | BH21: =C20/C19-1 -> -0.0044387779 | BI21: =F20/F19-1 -> 0.039055404 | BK21: 42120 | BL21: / | BM21: /
B22: 42134 | C22: 2122.7 | E22: 42134 | F22: 21.87 | I22: 1 | J22: =C21/C20-1 -> 0.0036996632 | K22: =F21/F20-1 -> -0.040646853 | M22: Jensen Alpha | U22: 1 | V22: =C22/C21-1 -> 0.0031189452 | W22: =ABS(V22) -> 0.0031189452 | X22: =F22/F21-1 -> -0.0036446469 | Z22: Beta - | AA22: =Z18-Z19 -> 1.2833385 | AL22: =AL21+0.5% -> -0.06 | AM22: =$M$18*AL22+$M$20 -> -0.08434961 | AN22: =$AA$21*AL22-$Z$17 -> -0.095124194 | BH22: =C21/C20-1 -> 0.0036996632 | BI22: =F21/F20-1 -> -0.040646853 | BK22: 42127 | BL22: / | BM22: /
B23: 42141 | C23: 2126.1 | E23: 42141 | F23: 21.75 | I23: 1 | J23: =C22/C21-1 -> 0.0031189452 | K23: =F22/F21-1 -> -0.0036446469 | M23: =M20-N25/52*(1-M18) -> 0.0020973846 | N23: n | U23: 1 | V23: =C23/C22-1 -> 0.0016017336 | W23: =ABS(V23) -> 0.0016017336 | X23: =F23/F22-1 -> -0.0054869684 | AL23: =AL22+0.5% -> -0.055 | AM23: =$M$18*AL23+$M$20 -> -0.077177029 | AN23: =$AA$21*AL23-$Z$17 -> -0.087121212 | BH23: =C22/C21-1 -> 0.0031189452 | BI23: =F22/F21-1 -> -0.0036446469 | BK23: 42134 | BL23: / | BM23: /
B24: 42148 | C24: 2107.4 | E24: 42148 | F24: 22.2 | I24: 1 | J24: =C23/C22-1 -> 0.0016017336 | K24: =F23/F22-1 -> -0.0054869684 | U24: 1 | V24: =C24/C23-1 -> -0.0087954471 | W24: =ABS(V24) -> 0.0087954471 | X24: =F24/F23-1 -> 0.020689655 | AL24: =AL23+0.5% -> -0.05 | AM24: =$M$18*AL24+$M$20 -> -0.070004448 | AN24: =$AA$21*AL24-$Z$17 -> -0.07911823 | BH24: =C23/C22-1 -> 0.0016017336 | BI24: =F23/F22-1 -> -0.0054869684 | BK24: 42141 | BL24: / | BM24: /
B25: 42155 | C25: 2092.8 | E25: 42155 | F25: 22.42 | I25: 1 | J25: =C24/C23-1 -> -0.0087954471 | K25: =F24/F23-1 -> 0.020689655 | M25: 10yr bond | N25: 0.045 | U25: 1 | V25: =C25/C24-1 -> -0.0069279681 | W25: =ABS(V25) -> 0.0069279681 | X25: =F25/F24-1 -> 0.0099099099 | AL25: =AL24+0.5% -> -0.045 | AM25: =$M$18*AL25+$M$20 -> -0.062831867 | AN25: =$AA$21*AL25-$Z$17 -> -0.071115248 | BH25: =C24/C23-1 -> -0.0087954471 | BI25: =F24/F23-1 -> 0.020689655 | BK25: 42148 | BL25: / | BM25: /
B26: 42162 | C26: 2094.1 | E26: 42162 | F26: 21.41 | I26: 1 | J26: =C25/C24-1 -> -0.0069279681 | K26: =F25/F24-1 -> 0.0099099099 | U26: 1 | V26: =C26/C25-1 -> 0.00062117737 | W26: =ABS(V26) -> 0.00062117737 | X26: =F26/F25-1 -> -0.045049063 | AL26: =AL25+0.5% -> -0.04 | AM26: =$M$18*AL26+$M$20 -> -0.055659286 | AN26: =$AA$21*AL26-$Z$17 -> -0.063112266 | BH26: =C25/C24-1 -> -0.0069279681 | BI26: =F25/F24-1 -> 0.0099099099 | BK26: 42155 | BL26: / | BM26: /
B27: 42169 | C27: 2110 | E27: 42169 | F27: 21.67 | I27: 1 | J27: =C26/C25-1 -> 0.00062117737 | K27: =F26/F25-1 -> -0.045049063 | U27: 1 | V27: =C27/C26-1 -> 0.0075927606 | W27: =ABS(V27) -> 0.0075927606 | X27: =F27/F26-1 -> 0.012143858 | AL27: =AL26+0.5% -> -0.035 | AM27: =$M$18*AL27+$M$20 -> -0.048486705 | AN27: =$AA$21*AL27-$Z$17 -> -0.055109284 | BH27: =C26/C25-1 -> 0.00062117737 | BI27: =F26/F25-1 -> -0.045049063 | BK27: 42162 | BL27: / | BM27: /
B28: 42176 | C28: 2101.5 | E28: 42176 | F28: 22.41 | I28: 1 | J28: =C27/C26-1 -> 0.0075927606 | K28: =F27/F26-1 -> 0.012143858 | U28: 1 | V28: =C28/C27-1 -> -0.004028436 | W28: =ABS(V28) -> 0.004028436 | X28: =F28/F27-1 -> 0.034148593 | AL28: =AL27+0.5% -> -0.03 | AM28: =$M$18*AL28+$M$20 -> -0.041314124 | AN28: =$AA$21*AL28-$Z$17 -> -0.047106302 | BH28: =C27/C26-1 -> 0.0075927606 | BI28: =F27/F26-1 -> 0.012143858 | BK28: 42169 | BL28: / | BM28: /
B29: 42183 | C29: 2076.8 | E29: 42183 | F29: 22.15 | I29: 1 | J29: =C28/C27-1 -> -0.004028436 | K29: =F28/F27-1 -> 0.034148593 | U29: 1 | V29: =C29/C28-1 -> -0.011753509 | W29: =ABS(V29) -> 0.011753509 | X29: =F29/F28-1 -> -0.011601963 | AL29: =AL28+0.5% -> -0.025 | AM29: =$M$18*AL29+$M$20 -> -0.034141544 | AN29: =$AA$21*AL29-$Z$17 -> -0.03910332 | BH29: =C28/C27-1 -> -0.004028436 | BI29: =F28/F27-1 -> 0.034148593 | BK29: 42176 | BL29: / | BM29: /
B30: 42190 | C30: 2076.6 | E30: 42190 | F30: 21.85 | I30: 1 | J30: =C29/C28-1 -> -0.011753509 | K30: =F29/F28-1 -> -0.011601963 | U30: 1 | V30: =C30/C29-1 -> -9.6302003e-05 | W30: =ABS(V30) -> 9.6302003e-05 | X30: =F30/F29-1 -> -0.013544018 | AL30: =AL29+0.5% -> -0.02 | AM30: =$M$18*AL30+$M$20 -> -0.026968963 | AN30: =$AA$21*AL30-$Z$17 -> -0.031100338 | BH30: =C29/C28-1 -> -0.011753509 | BI30: =F29/F28-1 -> -0.011601963 | BK30: 42183 | BL30: / | BM30: /
B31: 42197 | C31: 2126.6 | E31: 42197 | F31: 22.16 | I31: 1 | J31: =C30/C29-1 -> -9.6302003e-05 | K31: =F30/F29-1 -> -0.013544018 | U31: 1 | V31: =C31/C30-1 -> 0.02407782 | W31: =ABS(V31) -> 0.02407782 | X31: =F31/F30-1 -> 0.014187643 | AL31: =AL30+0.5% -> -0.015 | AM31: =$M$18*AL31+$M$20 -> -0.019796382 | AN31: =$AA$21*AL31-$Z$17 -> -0.023097356 | BH31: =C30/C29-1 -> -9.6302003e-05 | BI31: =F30/F29-1 -> -0.013544018 | BK31: 42190 | BL31: / | BM31: /
B32: 42204 | C32: 2079.7 | E32: 42204 | F32: 20.36 | I32: 1 | J32: =C31/C30-1 -> 0.02407782 | K32: =F31/F30-1 -> 0.014187643 | U32: 1 | V32: =C32/C31-1 -> -0.022053983 | W32: =ABS(V32) -> 0.022053983 | X32: =F32/F31-1 -> -0.081227437 | AL32: =AL31+0.5% -> -0.01 | AM32: =$M$18*AL32+$M$20 -> -0.012623801 | AN32: =$AA$21*AL32-$Z$17 -> -0.015094374 | BH32: =C31/C30-1 -> 0.02407782 | BI32: =F31/F30-1 -> 0.014187643 | BK32: 42197 | BL32: / | BM32: /
B33: 42211 | C33: 2103.8 | E33: 42211 | F33: 20.57 | I33: 1 | J33: =C32/C31-1 -> -0.022053983 | K33: =F32/F31-1 -> -0.081227437 | U33: 1 | V33: =C33/C32-1 -> 0.01158821 | W33: =ABS(V33) -> 0.01158821 | X33: =F33/F32-1 -> 0.010314342 | AL33: =AL32+0.5% -> -0.005 | AM33: =$M$18*AL33+$M$20 -> -0.0054512199 | AN33: =$AA$21*AL33-$Z$17 -> -0.0070913921 | BH33: =C32/C31-1 -> -0.022053983 | BI33: =F32/F31-1 -> -0.081227437 | BK33: 42204 | BL33: / | BM33: /
B34: 42218 | C34: 2077.6 | E34: 42218 | F34: 21.18 | I34: 1 | J34: =C33/C32-1 -> 0.01158821 | K34: =F33/F32-1 -> 0.010314342 | U34: 1 | V34: =C34/C33-1 -> -0.012453655 | W34: =ABS(V34) -> 0.012453655 | X34: =F34/F33-1 -> 0.029654837 | AL34: =AL33+0.5% -> 7.1123663e-17 | AM34: =$M$18*AL34+$M$20 -> 0.001721361 | AN34: =$AA$21*AL34-$Z$17 -> 0.00091158987 | BH34: =C33/C32-1 -> 0.01158821 | BI34: =F33/F32-1 -> 0.010314342 | BK34: 42211 | BL34: / | BM34: /
B35: 42225 | C35: 2091.5 | E35: 42225 | F35: 20.71 | I35: 1 | J35: =C34/C33-1 -> -0.012453655 | K35: =F34/F33-1 -> 0.029654837 | U35: 1 | V35: =C35/C34-1 -> 0.006690412 | W35: =ABS(V35) -> 0.006690412 | X35: =F35/F34-1 -> -0.022190746 | AL35: =AL34+0.5% -> 0.005 | AM35: =$M$18*AL35+$M$20 -> 0.0088939419 | AN35: =$AA$21*AL35-$Z$17 -> 0.0089145718 | BH35: =C34/C33-1 -> -0.012453655 | BI35: =F34/F33-1 -> 0.029654837 | BK35: 42218 | BL35: / | BM35: /
B36: 42232 | C36: 1970.9 | E36: 42232 | F36: 18.84 | I36: 1 | J36: =C35/C34-1 -> 0.006690412 | K36: =F35/F34-1 -> -0.022190746 | U36: 1 | V36: =C36/C35-1 -> -0.057661965 | W36: =ABS(V36) -> 0.057661965 | X36: =F36/F35-1 -> -0.090294544 | AL36: =AL35+0.5% -> 0.01 | AM36: =$M$18*AL36+$M$20 -> 0.016066523 | AN36: =$AA$21*AL36-$Z$17 -> 0.016917554 | BH36: =C35/C34-1 -> 0.006690412 | BI36: =F35/F34-1 -> -0.022190746 | BK36: 42225 | BL36: / | BM36: /
B37: 42239 | C37: 1988.9 | E37: 42239 | F37: 19.05 | I37: 1 | J37: =C36/C35-1 -> -0.057661965 | K37: =F36/F35-1 -> -0.090294544 | U37: 1 | V37: =C37/C36-1 -> 0.0091328835 | W37: =ABS(V37) -> 0.0091328835 | X37: =F37/F36-1 -> 0.011146497 | AL37: =AL36+0.5% -> 0.015 | AM37: =$M$18*AL37+$M$20 -> 0.023239104 | AN37: =$AA$21*AL37-$Z$17 -> 0.024920536 | BH37: =C36/C35-1 -> -0.057661965 | BI37: =F36/F35-1 -> -0.090294544 | BK37: 42232 | BL37: / | BM37: /
... B56: 42372 | C56: 1922 | E56: 42372 | F56: 14 | I56: 1 | J56: =C55/C54-1 -> -0.0082969432 | K56: =F55/F54-1 -> -0.026923077 | U56: 1 | V56: =C56/C55-1 -> -0.059640883 | W56: =ABS(V56) -> 0.059640883 | X56: =F56/F55-1 -> -0.07773386 | AL56: =AL55+0.5% -> 0.11 | AM56: =$M$18*AL56+$M$20 -> 0.15951814 | AN56: =$AA$21*AL56-$Z$17 -> 0.17697719 | BH56: =C55/C54-1 -> -0.0082969432 | BI56: =F55/F54-1 -> -0.026923077 | BK56: 42365 | BL56: / | BM56: /
B57: 42379 | C57: 1880.3 | E57: 42379 | F57: 13.38 | I57: 1 | J57: =C56/C55-1 -> -0.059640883 | K57: =F56/F55-1 -> -0.07773386 | U57: 1 | V57: =C57/C56-1 -> -0.02169615 | W57: =ABS(V57) -> 0.02169615 | X57: =F57/F56-1 -> -0.044285714 | AL57: =AL56+0.5% -> 0.115 | AM57: =$M$18*AL57+$M$20 -> 0.16669072 | AN57: =$AA$21*AL57-$Z$17 -> 0.18498017 | BH57: =C56/C55-1 -> -0.059640883 | BI57: =F56/F55-1 -> -0.07773386 | BK57: 42372 | BL57: =SLOPE(BI5:BI57,BH5:BH57) -> 0.74237049 | BM57: =STDEV(BI5:BI57) -> 0.032077309
B58: 42386 | C58: 1906.9 | E58: 42386 | F58: 13.8 | I58: 1 | J58: =C57/C56-1 -> -0.02169615 | K58: =F57/F56-1 -> -0.044285714 | U58: 1 | V58: =C58/C57-1 -> 0.014146679 | W58: =ABS(V58) -> 0.014146679 | X58: =F58/F57-1 -> 0.031390135 | AL58: =AL57+0.5% -> 0.12 | AM58: =$M$18*AL58+$M$20 -> 0.1738633 | AN58: =$AA$21*AL58-$Z$17 -> 0.19298316 | BH58: =C57/C56-1 -> -0.02169615 | BI58: =F57/F56-1 -> -0.044285714 | BK58: 42379 | BL58: =SLOPE(BI6:BI58,BH6:BH58) -> 0.75963649 | BM58: =STDEV(BI6:BI58) -> 0.032400223
B59: 42393 | C59: 1940.2 | E59: 42393 | F59: 13.58 | I59: 1 | J59: =C58/C57-1 -> 0.014146679 | K59: =F58/F57-1 -> 0.031390135 | U59: 1 | V59: =C59/C58-1 -> 0.017462898 | W59: =ABS(V59) -> 0.017462898 | X59: =F59/F58-1 -> -0.015942029 | AL59: =AL58+0.5% -> 0.125 | AM59: =$M$18*AL59+$M$20 -> 0.18103588 | AN59: =$AA$21*AL59-$Z$17 -> 0.20098614 | BH59: =C58/C57-1 -> 0.014146679 | BI59: =F58/F57-1 -> 0.031390135 | BK59: 42386 | BL59: =SLOPE(BI7:BI59,BH7:BH59) -> 0.79132828 | BM59: =STDEV(BI7:BI59) -> 0.032853758
B60: 42400 | C60: 1880 | E60: 42400 | F60: 13.6 | I60: 1 | J60: =C59/C58-1 -> 0.017462898 | K60: =F59/F58-1 -> -0.015942029 | U60: 1 | V60: =C60/C59-1 -> -0.031027729 | W60: =ABS(V60) -> 0.031027729 | X60: =F60/F59-1 -> 0.0014727541 | AL60: =AL59+0.5% -> 0.13 | AM60: =$M$18*AL60+$M$20 -> 0.18820846 | AN60: =$AA$21*AL60-$Z$17 -> 0.20898912 | BH60: =C59/C58-1 -> 0.017462898 | BI60: =F59/F58-1 -> -0.015942029 | BK60: 42393 | BL60: =SLOPE(BI8:BI60,BH8:BH60) -> 0.75588751 | BM60: =STDEV(BI8:BI60) -> 0.032433634
B61: 42407 | C61: 1864.8 | E61: 42407 | F61: 13.4 | I61: 1 | J61: =C60/C59-1 -> -0.031027729 | K61: =F60/F59-1 -> 0.0014727541 | U61: 1 | V61: =C61/C60-1 -> -0.0080851064 | W61: =ABS(V61) -> 0.0080851064 | X61: =F61/F60-1 -> -0.014705882 | BH61: =C60/C59-1 -> -0.031027729 | BI61: =F60/F59-1 -> 0.0014727541 | BK61: 42400 | BL61: =SLOPE(BI9:BI61,BH9:BH61) -> 0.75802114 | BM61: =STDEV(BI9:BI61) -> 0.032348423
B62: 42414 | C62: 1917.8 | E62: 42414 | F62: 14.91 | I62: 1 | J62: =C61/C60-1 -> -0.0080851064 | K62: =F61/F60-1 -> -0.014705882 | U62: 1 | V62: =C62/C61-1 -> 0.028421278 | W62: =ABS(V62) -> 0.028421278 | X62: =F62/F61-1 -> 0.11268657 | BH62: =C61/C60-1 -> -0.0080851064 | BI62: =F61/F60-1 -> -0.014705882 | BK62: 42407 | BL62: =SLOPE(BI10:BI62,BH10:BH62) -> 0.81069768 | BM62: =STDEV(BI10:BI62) -> 0.032308899
B63: 42421 | C63: 1948 | E63: 42421 | F63: 15.07 | I63: 1 | J63: =C62/C61-1 -> 0.028421278 | K63: =F62/F61-1 -> 0.11268657 | U63: 1 | V63: =C63/C62-1 -> 0.01574721 | W63: =ABS(V63) -> 0.01574721 | X63: =F63/F62-1 -> 0.010731053 | BH63: =C62/C61-1 -> 0.028421278 | BI63: =F62/F61-1 -> 0.11268657 | BK63: 42414 | BL63: =SLOPE(BI11:BI63,BH11:BH63) -> 0.97681198 | BM63: =STDEV(BI11:BI63) -> 0.036410676
B64: 42428 | C64: 2000 | E64: 42428 | F64: 16.85 | I64: 1 | J64: =C63/C62-1 -> 0.01574721 | K64: =F63/F62-1 -> 0.010731053 | U64: 1 | V64: =C64/C63-1 -> 0.026694045 | W64: =ABS(V64) -> 0.026694045 | X64: =F64/F63-1 -> 0.11811546 | BH64: =C63/C62-1 -> 0.01574721 | BI64: =F63/F62-1 -> 0.010731053 | BK64: 42421 | BL64: =SLOPE(BI12:BI64,BH12:BH64) -> 0.98108155 | BM64: =STDEV(BI12:BI64) -> 0.036501872
B65: 42435 | C65: 2022.2 | E65: 42435 | F65: 16.91 | I65: 1 | J65: =C64/C63-1 -> 0.026694045 | K65: =F64/F63-1 -> 0.11811546 | U65: 1 | V65: =C65/C64-1 -> 0.0111 | W65: =ABS(V65) -> 0.0111 | X65: =F65/F64-1 -> 0.0035608309 | BH65: =C64/C63-1 -> 0.026694045 | BI65: =F64/F63-1 -> 0.11811546 | BK65: 42428 | BL65: =SLOPE(BI13:BI65,BH13:BH65) -> 1.0987795 | BM65: =STDEV(BI13:BI65) -> 0.040385886
B66: 42442 | C66: 2049.6 | E66: 42442 | F66: 17.15 | I66: 1 | J66: =C65/C64-1 -> 0.0111 | K66: =F65/F64-1 -> 0.0035608309 | U66: 1 | V66: =C66/C65-1 -> 0.013549599 | W66: =ABS(V66) -> 0.013549599 | X66: =F66/F65-1 -> 0.014192785 | BH66: =C65/C64-1 -> 0.0111 | BI66: =F65/F64-1 -> 0.0035608309 | BK66: 42435 | BL66: =SLOPE(BI14:BI66,BH14:BH66) -> 1.0812503 | BM66: =STDEV(BI14:BI66) -> 0.040025308
B67: 42449 | C67: 2035.9 | E67: 42449 | F67: 16.73 | I67: 1 | J67: =C66/C65-1 -> 0.013549599 | K67: =F66/F65-1 -> 0.014192785 | U67: 1 | V67: =C67/C66-1 -> -0.0066842311 | W67: =ABS(V67) -> 0.0066842311 | X67: =F67/F66-1 -> -0.024489796 | BH67: =C66/C65-1 -> 0.013549599 | BI67: =F66/F65-1 -> 0.014192785 | BK67: 42442 | BL67: =SLOPE(BI15:BI67,BH15:BH67) -> 1.0929068 | BM67: =STDEV(BI15:BI67) -> 0.040049701
B68: 42456 | C68: 2072.8 | E68: 42456 | F68: 17.35 | I68: 1 | J68: =C67/C66-1 -> -0.0066842311 | K68: =F67/F66-1 -> -0.024489796 | U68: 1 | V68: =C68/C67-1 -> 0.018124662 | W68: =ABS(V68) -> 0.018124662 | X68: =F68/F67-1 -> 0.037059175 | BH68: =C67/C66-1 -> -0.0066842311 | BI68: =F67/F66-1 -> -0.024489796 | BK68: 42449 | BL68: =SLOPE(BI16:BI68,BH16:BH68) -> 1.1419295 | BM68: =STDEV(BI16:BI68) -> 0.040128937
B69: 42463 | C69: 2047.6 | E69: 42463 | F69: 15.83 | I69: 1 | J69: =C68/C67-1 -> 0.018124662 | K69: =F68/F67-1 -> 0.037059175 | U69: 1 | V69: =C69/C68-1 -> -0.012157468 | W69: =ABS(V69) -> 0.012157468 | X69: =F69/F68-1 -> -0.087608069 | BH69: =C68/C67-1 -> 0.018124662 | BI69: =F68/F67-1 -> 0.037059175 | BK69: 42456 | BL69: =SLOPE(BI17:BI69,BH17:BH69) -> 1.1347801 | BM69: =STDEV(BI17:BI69) -> 0.039954641
B70: 42470 | C70: 2080.7 | E70: 42470 | F70: 16.92 | I70: 1 | J70: =C69/C68-1 -> -0.012157468 | K70: =F69/F68-1 -> -0.087608069 | U70: 1 | V70: =C70/C69-1 -> 0.016165267 | W70: =ABS(V70) -> 0.016165267 | X70: =F70/F69-1 -> 0.068856601 | BH70: =C69/C68-1 -> -0.012157468 | BI70: =F69/F68-1 -> -0.087608069 | BK70: 42463 | BL70: =SLOPE(BI18:BI70,BH18:BH70) -> 1.1708558 | BM70: =STDEV(BI18:BI70) -> 0.041475515
B71: 42477 | C71: 2091.6 | E71: 42477 | F71: 17.32 | I71: 1 | J71: =C70/C69-1 -> 0.016165267 | K71: =F70/F69-1 -> 0.068856601 | U71: 1 | V71: =C71/C70-1 -> 0.0052386216 | W71: =ABS(V71) -> 0.0052386216 | X71: =F71/F70-1 -> 0.023640662 | BH71: =C70/C69-1 -> 0.016165267 | BI71: =F70/F69-1 -> 0.068856601 | BK71: 42470 | BL71: =SLOPE(BI19:BI71,BH19:BH71) -> 1.2306077 | BM71: =STDEV(BI19:BI71) -> 0.042682392
B72: 42484 | C72: 2065.3 | E72: 42484 | F72: 16.91 | I72: 1 | J72: =C71/C70-1 -> 0.0052386216 | K72: =F71/F70-1 -> 0.023640662 | U72: 1 | V72: =C72/C71-1 -> -0.012574106 | W72: =ABS(V72) -> 0.012574106 | X72: =F72/F71-1 -> -0.023672055 | BH72: =C71/C70-1 -> 0.0052386216 | BI72: =F71/F70-1 -> 0.023640662 | BK72: 42477 | BL72: =SLOPE(BI20:BI72,BH20:BH72) -> 1.260065 | BM72: =STDEV(BI20:BI72) -> 0.042457314
... B525: 45655 | C525: 5942.47 | E525: 45655 | F525: 169.06 | I525: 1 | J525: =C524/C523-1 -> 0.0067427097 | K525: =F524/F523-1 -> -0.0043851956 | U525: 1 | V525: =C525/C524-1 -> -0.0047514253 | W525: =ABS(V525) -> 0.0047514253 | X525: =F525/F524-1 -> -0.00716467 | BH525: =C524/C523-1 -> 0.0067427097 | BI525: =F524/F523-1 -> -0.0043851956 | BK525: 45648 | BL525: =SLOPE(BI473:BI525,BH473:BH525) -> 1.5788215 | BM525: =STDEV(BI473:BI525) -> 0.041275623
BH526: =C525/C524-1 -> -0.0047514253 | BI526: =F525/F524-1 -> -0.00716467 | BK526: 45655 | BL526: =SLOPE(BI474:BI526,BH474:BH526) -> 1.5824896 | BM526: =STDEV(BI474:BI526) -> 0.041358227

Sheet Pair trade
B2: Parameters | F2: Apollo Global Mgmt | H2: Blackstone | Q2: Last Price | R2: Beta | T2: Investment | V2: 100000
B3: Date | C3: 44562 | E3: Dates | F3: Price | G3: Var % | H3: Price | I3: Var % | J3: Ratio Norm | K3: RN-Std | L3: RN+Std | O3: Sell | P3: APO US | Q3: =F756 -> 165.16 | R3: =Beta!M15 -> 1.4345162 | T3: $$ Neutral | U3: APO US | V3: =ROUND(V2/Q3,0) -> 605 | AE3: Dates | AF3: ln APO US | AG3: ln BX US
C4: 45657 | E4: 44564 | F4: 71.53 | H4: 126.63 | J4: =F4/$F$4*$H$4/H4 -> 1 | K4: =AVERAGE($J$5:$J$756)-1.5*_xlfn.STDEV.S($J$5:$J$756) -> 0.94221126 | L4: =AVERAGE($J$5:$J$756)+_xlfn.STDEV.S($J$5:$J$756) -> 1.5816901 | O4: Buy | P4: BX US | Q4: =H756 -> 172.42 | R4: 1.54 | U4: BX US | V4: =ROUND(V2/Q4,0) -> 580 | AE4: 44564 | AF4: =LN(F4) -> 4.2701169 | AG4: =LN(H4) -> 4.8412694 | AI4: Slope | AJ4: =SLOPE(AG4:AG756,AF4:AF756) -> 0.5127802
B5: Indip. | C5: Blackstone | E5: 44565 | F5: 73.56 | G5: =F5/F4-1 -> 0.028379701 | H5: 124.94 | I5: =H5/H4-1 -> -0.013345969 | J5: =F5/$F$4*$H$4/H5 -> 1.0422901 | K5: =AVERAGE($J$5:$J$756)-1.5*_xlfn.STDEV.S($J$5:$J$756) -> 0.94221126 | L5: =AVERAGE($J$5:$J$756)+_xlfn.STDEV.S($J$5:$J$756) -> 1.5816901 | P5: Cur Ratio | Q5: =Q3/Q4 -> 0.95789352 | T5: Beta Neutral | U5: APO US | V5: =V3 -> 605 | AE5: 44565 | AF5: =LN(F5) -> 4.2981014 | AG5: =LN(H5) -> 4.8278336 | AI5: Intercept | AJ5: =INTERCEPT(AG4:AG2256,AF4:AF2256) -> 2.4529692
B6: Dip. | C6: Apollo Global Mgmt | E6: 44566 | F6: 69.6 | G6: =F6/F5-1 -> -0.053833605 | H6: 117.79 | I6: =H6/H5-1 -> -0.057227469 | J6: =F6/$F$4*$H$4/H6 -> 1.0460422 | K6: =AVERAGE($J$5:$J$756)-1.5*_xlfn.STDEV.S($J$5:$J$756) -> 0.94221126 | L6: =AVERAGE($J$5:$J$756)+_xlfn.STDEV.S($J$5:$J$756) -> 1.5816901 | P6: Cur Corr | Q6: =CORREL(G4:G756,I4:I756) -> 0.69515429 | U6: BX US | V6: =ROUND(V2*R3/R4/Q4,0) -> 540 | AE6: 44566 | AF6: =LN(F6) -> 4.2427646 | AG6: =LN(H6) -> 4.7689034
E7: 44567 | F7: 69.57 | G7: =F7/F6-1 -> -0.00043103448 | H7: 119.16 | I7: =H7/H6-1 -> 0.011630868 | J7: =F7/$F$4*$H$4/H7 -> 1.03357 | K7: =AVERAGE($J$5:$J$756)-1.5*_xlfn.STDEV.S($J$5:$J$756) -> 0.94221126 | L7: =AVERAGE($J$5:$J$756)+_xlfn.STDEV.S($J$5:$J$756) -> 1.5816901 | T7: Corr Neutral | U7: APO US | V7: =V5 -> 605 | AE7: 44567 | AF7: =LN(F7) -> 4.2423334 | AG7: =LN(H7) -> 4.7804671
E8: 44568 | F8: 68.96 | G8: =F8/F7-1 -> -0.0087681472 | H8: 116.65 | I8: =H8/H7-1 -> -0.021064115 | J8: =F8/$F$4*$H$4/H8 -> 1.0465522 | K8: =AVERAGE($J$5:$J$756)-1.5*_xlfn.STDEV.S($J$5:$J$756) -> 0.94221126 | L8: =AVERAGE($J$5:$J$756)+_xlfn.STDEV.S($J$5:$J$756) -> 1.5816901 | U8: BX US | V8: =ROUND(V2*Q6/Q4,0) -> 403 | AE8: 44568 | AF8: =LN(F8) -> 4.2335266 | AG8: =LN(H8) -> 4.759178
E9: 44571 | F9: 68.35 | G9: =F9/F8-1 -> -0.0088457077 | H9: 114.72 | I9: =H9/H8-1 -> -0.016545221 | J9: =F9/$F$4*$H$4/H9 -> 1.0547457 | K9: =AVERAGE($J$5:$J$756)-1.5*_xlfn.STDEV.S($J$5:$J$756) -> 0.94221126 | L9: =AVERAGE($J$5:$J$756)+_xlfn.STDEV.S($J$5:$J$756) -> 1.5816901 | AE9: 44571 | AF9: =LN(F9) -> 4.2246416 | AG9: =LN(H9) -> 4.7424944
E10: 44572 | F10: 70.58 | G10: =F10/F9-1 -> 0.032626189 | H10: 121.3 | I10: =H10/H9-1 -> 0.057357043 | J10: =F10/$F$4*$H$4/H10 -> 1.0300759 | K10: =AVERAGE($J$5:$J$756)-1.5*_xlfn.STDEV.S($J$5:$J$756) -> 0.94221126 | L10: =AVERAGE($J$5:$J$756)+_xlfn.STDEV.S($J$5:$J$756) -> 1.5816901 | AE10: 44572 | AF10: =LN(F10) -> 4.2567468 | AG10: =LN(H10) -> 4.7982668
E11: 44573 | F11: 70.76 | G11: =F11/F10-1 -> 0.0025502975 | H11: 122.34 | I11: =H11/H10-1 -> 0.008573784 | J11: =F11/$F$4*$H$4/H11 -> 1.023924 | K11: =AVERAGE($J$5:$J$756)-1.5*_xlfn.STDEV.S($J$5:$J$756) -> 0.94221126 | L11: =AVERAGE($J$5:$J$756)+_xlfn.STDEV.S($J$5:$J$756) -> 1.5816901 | AE11: 44573 | AF11: =LN(F11) -> 4.2592939 | AG11: =LN(H11) -> 4.8068041
E12: 44574 | F12: 69.55 | G12: =F12/F11-1 -> -0.017100057 | H12: 118.94 | I12: =H12/H11-1 -> -0.027791401 | J12: =F12/$F$4*$H$4/H12 -> 1.0351841 | K12: =AVERAGE($J$5:$J$756)-1.5*_xlfn.STDEV.S($J$5:$J$756) -> 0.94221126 | L12: =AVERAGE($J$5:$J$756)+_xlfn.STDEV.S($J$5:$J$756) -> 1.5816901 | AE12: 44574 | AF12: =LN(F12) -> 4.2420459 | AG12: =LN(H12) -> 4.7786192
E13: 44575 | F13: 68.83 | G13: =F13/F12-1 -> -0.010352265 | H13: 116.12 | I13: =H13/H12-1 -> -0.023709433 | J13: =F13/$F$4*$H$4/H13 -> 1.049347 | K13: =AVERAGE($J$5:$J$756)-1.5*_xlfn.STDEV.S($J$5:$J$756) -> 0.94221126 | L13: =AVERAGE($J$5:$J$756)+_xlfn.STDEV.S($J$5:$J$756) -> 1.5816901 | AE13: 44575 | AF13: =LN(F13) -> 4.2316397 | AG13: =LN(H13) -> 4.7546241
E14: 44579 | F14: 67.65 | G14: =F14/F13-1 -> -0.017143687 | H14: 113.92 | I14: =H14/H13-1 -> -0.018945918 | J14: =F14/$F$4*$H$4/H14 -> 1.0512747 | K14: =AVERAGE($J$5:$J$756)-1.5*_xlfn.STDEV.S($J$5:$J$756) -> 0.94221126 | L14: =AVERAGE($J$5:$J$756)+_xlfn.STDEV.S($J$5:$J$756) -> 1.5816901 | AE14: 44579 | AF14: =LN(F14) -> 4.2143474 | AG14: =LN(H14) -> 4.7354964
E15: 44580 | F15: 67.05 | G15: =F15/F14-1 -> -0.0088691796 | H15: 112.26 | I15: =H15/H14-1 -> -0.014571629 | J15: =F15/$F$4*$H$4/H15 -> 1.0573582 | K15: =AVERAGE($J$5:$J$756)-1.5*_xlfn.STDEV.S($J$5:$J$756) -> 0.94221126 | L15: =AVERAGE($J$5:$J$756)+_xlfn.STDEV.S($J$5:$J$756) -> 1.5816901 | AE15: 44580 | AF15: =LN(F15) -> 4.2054386 | AG15: =LN(H15) -> 4.7208176
E16: 44581 | F16: 67 | G16: =F16/F15-1 -> -0.00074571216 | H16: 111.56 | I16: =H16/H15-1 -> -0.0062355247 | J16: =F16/$F$4*$H$4/H16 -> 1.0631993 | K16: =AVERAGE($J$5:$J$756)-1.5*_xlfn.STDEV.S($J$5:$J$756) -> 0.94221126 | L16: =AVERAGE($J$5:$J$756)+_xlfn.STDEV.S($J$5:$J$756) -> 1.5816901 | AE16: 44581 | AF16: =LN(F16) -> 4.2046926 | AG16: =LN(H16) -> 4.7145626
E17: 44582 | F17: 65.9 | G17: =F17/F16-1 -> -0.01641791 | H17: 109.78 | I17: =H17/H16-1 -> -0.01595554 | J17: =F17/$F$4*$H$4/H17 -> 1.0626997 | K17: =AVERAGE($J$5:$J$756)-1.5*_xlfn.STDEV.S($J$5:$J$756) -> 0.94221126 | L17: =AVERAGE($J$5:$J$756)+_xlfn.STDEV.S($J$5:$J$756) -> 1.5816901 | AE17: 44582 | AF17: =LN(F17) -> 4.1881384 | AG17: =LN(H17) -> 4.6984784
E18: 44585 | F18: 65.35 | G18: =F18/F17-1 -> -0.0083459788 | H18: 109.39 | I18: =H18/H17-1 -> -0.0035525597 | J18: =F18/$F$4*$H$4/H18 -> 1.0575876 | K18: =AVERAGE($J$5:$J$756)-1.5*_xlfn.STDEV.S($J$5:$J$756) -> 0.94221126 | L18: =AVERAGE($J$5:$J$756)+_xlfn.STDEV.S($J$5:$J$756) -> 1.5816901 | AE18: 44585 | AF18: =LN(F18) -> 4.1797574 | AG18: =LN(H18) -> 4.6949195
E19: 44586 | F19: 64.15 | G19: =F19/F18-1 -> -0.018362663 | H19: 110.24 | I19: =H19/H18-1 -> 0.0077703629 | J19: =F19/$F$4*$H$4/H19 -> 1.0301627 | K19: =AVERAGE($J$5:$J$756)-1.5*_xlfn.STDEV.S($J$5:$J$756) -> 0.94221126 | L19: =AVERAGE($J$5:$J$756)+_xlfn.STDEV.S($J$5:$J$756) -> 1.5816901 | AE19: 44586 | AF19: =LN(F19) -> 4.1612241 | AG19: =LN(H19) -> 4.7026598
E20: 44587 | F20: 63.55 | G20: =F20/F19-1 -> -0.0093530787 | H20: 111.47 | I20: =H20/H19-1 -> 0.011157475 | J20: =F20/$F$4*$H$4/H20 -> 1.0092667 | K20: =AVERAGE($J$5:$J$756)-1.5*_xlfn.STDEV.S($J$5:$J$756) -> 0.94221126 | L20: =AVERAGE($J$5:$J$756)+_xlfn.STDEV.S($J$5:$J$756) -> 1.5816901 | AE20: 44587 | AF20: =LN(F20) -> 4.151827 | AG20: =LN(H20) -> 4.7137555
... E756: 45657 | F756: 165.16 | G756: =F756/F755-1 -> -0.0081076212 | H756: 172.42 | I756: =H756/H755-1 -> 0.0021505376 | J756: =F756/$F$4*$H$4/H756 -> 1.6957648 | K756: =AVERAGE($J$5:$J$756)-1.5*_xlfn.STDEV.S($J$5:$J$756) -> 0.94221126 | L756: =AVERAGE($J$5:$J$756)+_xlfn.STDEV.S($J$5:$J$756) -> 1.5816901 | AE756: 45657 | AF756: =LN(F756) -> 5.1069147 | AG756: =LN(H756) -> 5.1499334

Sheet Moving Avgs
AZ1: =2/(20+1) -> 0.095238095 | BA1: =2/(50+1) -> 0.039215686 | CE1: =2/(200+1) -> 0.0099502488
B2: Dates | C2: Prices | D2: MA 20d | E2: MA 50d | F2: Diff | Z2: Dates | AA2: Prices | AB2: MA 200d | AX2: Dates | AY2: Prices | AZ2: EMA 20d | BA2: EMA 50d | BC2: Diff 20d | BD2: Diff50d | BE2: Zero Lag 20d | BF2: Zero Lag 50d | CC2: Dates | CD2: Prices | CE2: EMA 200d | CG2: Diff | CH2: Zero Lag 200d
B3: 44929 | C3: 62.81 | Z3: 43102 | AA3: 33.6 | AX3: 44929 | AY3: 62.81 | CC3: 43102 | CD3: 33.6
B4: 44930 | C4: 64.36 | Z4: 43103 | AA4: 34.27 | AX4: 44930 | AY4: 64.36 | CC4: 43103 | CD4: 34.27
B5: 44931 | C5: 62.95 | Z5: 43104 | AA5: 34.31 | AX5: 44931 | AY5: 62.95 | CC5: 43104 | CD5: 34.31
B6: 44932 | C6: 64.33 | Z6: 43105 | AA6: 34.48 | AX6: 44932 | AY6: 64.33 | CC6: 43105 | CD6: 34.48
B7: 44935 | C7: 65.32 | Z7: 43108 | AA7: 34.92 | AX7: 44935 | AY7: 65.32 | CC7: 43108 | CD7: 34.92
B8: 44936 | C8: 66.52 | Z8: 43109 | AA8: 35.69 | AX8: 44936 | AY8: 66.52 | CC8: 43109 | CD8: 35.69
B9: 44937 | C9: 67.68 | Z9: 43110 | AA9: 35.56 | AX9: 44937 | AY9: 67.68 | CC9: 43110 | CD9: 35.56
B10: 44938 | C10: 68.44 | Z10: 43111 | AA10: 35.89 | AX10: 44938 | AY10: 68.44 | CC10: 43111 | CD10: 35.89
B11: 44939 | C11: 69.71 | Z11: 43112 | AA11: 36.19 | AX11: 44939 | AY11: 69.71 | CC11: 43112 | CD11: 36.19
B12: 44943 | C12: 69.09 | Z12: 43116 | AA12: 35.08 | AX12: 44943 | AY12: 69.09 | CC12: 43116 | CD12: 35.08
B13: 44944 | C13: 68.03 | Z13: 43117 | AA13: 35.42 | AX13: 44944 | AY13: 68.03 | CC13: 43117 | CD13: 35.42
B14: 44945 | C14: 65.78 | Z14: 43118 | AA14: 35.07 | AX14: 44945 | AY14: 65.78 | CC14: 43118 | CD14: 35.07
... B22: 44957 | C22: 70.78 | Z22: 43130 | AA22: 35.5 | AX22: 44957 | AY22: 70.78 | CC22: 43130 | CD22: 35.5
B23: 44958 | C23: 72.52 | D23: =AVERAGE(C3:C23) -> 67.620952 | Z23: 43131 | AA23: 35.75 | AX23: 44958 | AY23: 72.52 | AZ23: =AVERAGE(AY3:AY23) -> 67.620952 | CC23: 43131 | CD23: 35.75
B24: 44959 | C24: 72.15 | D24: =AVERAGE(C4:C24) -> 68.065714 | Z24: 43132 | AA24: 36.78 | AX24: 44959 | AY24: 72.15 | AZ24: =AY24*$AZ$1+AZ23*(1-$AZ$1) -> 68.05229 | CC24: 43132 | CD24: 36.78
B25: 44960 | C25: 73.4 | D25: =AVERAGE(C5:C25) -> 68.49619 | Z25: 43133 | AA25: 35.9 | AX25: 44960 | AY25: 73.4 | AZ25: =AY25*$AZ$1+AZ24*(1-$AZ$1) -> 68.561596 | CC25: 43133 | CD25: 35.9
B26: 44963 | C26: 72.14 | D26: =AVERAGE(C6:C26) -> 68.93381 | Z26: 43136 | AA26: 34 | AX26: 44963 | AY26: 72.14 | AZ26: =AY26*$AZ$1+AZ25*(1-$AZ$1) -> 68.902396 | CC26: 43136 | CD26: 34
B27: 44964 | C27: 73.35 | D27: =AVERAGE(C7:C27) -> 69.363333 | Z27: 43137 | AA27: 33.59 | AX27: 44964 | AY27: 73.35 | AZ27: =AY27*$AZ$1+AZ26*(1-$AZ$1) -> 69.325978 | CC27: 43137 | CD27: 33.59
B28: 44965 | C28: 73.89 | D28: =AVERAGE(C8:C28) -> 69.771429 | Z28: 43138 | AA28: 33.75 | AX28: 44965 | AY28: 73.89 | AZ28: =AY28*$AZ$1+AZ27*(1-$AZ$1) -> 69.760646 | CC28: 43138 | CD28: 33.75
B29: 44966 | C29: 68.4 | D29: =AVERAGE(C9:C29) -> 69.860952 | Z29: 43139 | AA29: 32.03 | AX29: 44966 | AY29: 68.4 | AZ29: =AY29*$AZ$1+AZ28*(1-$AZ$1) -> 69.631061 | CC29: 43139 | CD29: 32.03
B30: 44967 | C30: 70.66 | D30: =AVERAGE(C10:C30) -> 70.002857 | Z30: 43140 | AA30: 32.33 | AX30: 44967 | AY30: 70.66 | AZ30: =AY30*$AZ$1+AZ29*(1-$AZ$1) -> 69.729055 | CC30: 43140 | CD30: 32.33
B31: 44970 | C31: 71.07 | D31: =AVERAGE(C11:C31) -> 70.128095 | Z31: 43143 | AA31: 33.02 | AX31: 44970 | AY31: 71.07 | AZ31: =AY31*$AZ$1+AZ30*(1-$AZ$1) -> 69.856764 | CC31: 43143 | CD31: 33.02
B32: 44971 | C32: 71.66 | D32: =AVERAGE(C12:C32) -> 70.220952 | Z32: 43144 | AA32: 33.57 | AX32: 44971 | AY32: 71.66 | AZ32: =AY32*$AZ$1+AZ31*(1-$AZ$1) -> 70.028501 | CC32: 43144 | CD32: 33.57
B33: 44972 | C33: 72.43 | D33: =AVERAGE(C13:C33) -> 70.38 | Z33: 43145 | AA33: 34.28 | AX33: 44972 | AY33: 72.43 | AZ33: =AY33*$AZ$1+AZ32*(1-$AZ$1) -> 70.257215 | CC33: 43145 | CD33: 34.28
B34: 44973 | C34: 72.09 | D34: =AVERAGE(C14:C34) -> 70.573333 | Z34: 43146 | AA34: 34.52 | AX34: 44973 | AY34: 72.09 | AZ34: =AY34*$AZ$1+AZ33*(1-$AZ$1) -> 70.431766 | CC34: 43146 | CD34: 34.52
B35: 44974 | C35: 71.44 | D35: =AVERAGE(C15:C35) -> 70.842857 | Z35: 43147 | AA35: 34.01 | AX35: 44974 | AY35: 71.44 | AZ35: =AY35*$AZ$1+AZ34*(1-$AZ$1) -> 70.527788 | CC35: 43147 | CD35: 34.01
... B42: 44986 | C42: 71.94 | D42: =AVERAGE(C22:C42) -> 71.473333 | Z42: 43159 | AA42: 32.8 | AX42: 44986 | AY42: 71.94 | AZ42: =AY42*$AZ$1+AZ41*(1-$AZ$1) -> 70.677216 | CC42: 43159 | CD42: 32.8
B43: 44987 | C43: 72.38 | D43: =AVERAGE(C23:C43) -> 71.549524 | Z43: 43160 | AA43: 31.99 | AX43: 44987 | AY43: 72.38 | AZ43: =AY43*$AZ$1+AZ42*(1-$AZ$1) -> 70.839386 | BC43: =AZ43-AVERAGE(AZ23:AZ43) -> 0.97910792 | BE43: =AZ43+BC43 -> 71.818494 | CC43: 43160 | CD43: 31.99
B44: 44988 | C44: 73.11 | D44: =AVERAGE(C24:C44) -> 71.577619 | Z44: 43161 | AA44: 32.05 | AX44: 44988 | AY44: 73.11 | AZ44: =AY44*$AZ$1+AZ43*(1-$AZ$1) -> 71.055635 | BC44: =AZ44-AVERAGE(AZ24:AZ44) -> 1.0318006 | BE44: =AZ44+BC44 -> 72.087435 | CC44: 43161 | CD44: 32.05
B45: 44991 | C45: 72.54 | D45: =AVERAGE(C25:C45) -> 71.59619 | Z45: 43164 | AA45: 32.45 | AX45: 44991 | AY45: 72.54 | AZ45: =AY45*$AZ$1+AZ44*(1-$AZ$1) -> 71.197003 | BC45: =AZ45-AVERAGE(AZ25:AZ45) -> 1.0234205 | BE45: =AZ45+BC45 -> 72.220423 | CC45: 43164 | CD45: 32.45
B46: 44992 | C46: 71.2 | D46: =AVERAGE(C26:C46) -> 71.491429 | Z46: 43165 | AA46: 32.85 | AX46: 44992 | AY46: 71.2 | AZ46: =AY46*$AZ$1+AZ45*(1-$AZ$1) -> 71.197288 | BC46: =AZ46-AVERAGE(AZ26:AZ46) -> 0.89819677 | BE46: =AZ46+BC46 -> 72.095485 | CC46: 43165 | CD46: 32.85
B47: 44993 | C47: 71.23 | D47: =AVERAGE(C27:C47) -> 71.448095 | Z47: 43166 | AA47: 32.75 | AX47: 44993 | AY47: 71.23 | AZ47: =AY47*$AZ$1+AZ46*(1-$AZ$1) -> 71.200404 | BC47: =AZ47-AVERAGE(AZ27:AZ47) -> 0.79188325 | BE47: =AZ47+BC47 -> 71.992287 | CC47: 43166 | CD47: 32.75
B48: 44994 | C48: 67.37 | D48: =AVERAGE(C28:C48) -> 71.163333 | Z48: 43167 | AA48: 33.01 | AX48: 44994 | AY48: 67.37 | AZ48: =AY48*$AZ$1+AZ47*(1-$AZ$1) -> 70.835603 | BC48: =AZ48-AVERAGE(AZ28:AZ48) -> 0.35519595 | BE48: =AZ48+BC48 -> 71.190799 | CC48: 43167 | CD48: 33.01
B49: 44995 | C49: 60.29 | D49: =AVERAGE(C29:C49) -> 70.515714 | Z49: 43168 | AA49: 33.56 | AX49: 44995 | AY49: 60.29 | AZ49: =AY49*$AZ$1+AZ48*(1-$AZ$1) -> 69.83126 | BC49: =AZ49-AVERAGE(AZ29:AZ49) -> -0.65250978 | BE49: =AZ49+BC49 -> 69.17875 | CC49: 43168 | CD49: 33.56
B50: 44998 | C50: 58.47 | D50: =AVERAGE(C30:C50) -> 70.042857 | Z50: 43171 | AA50: 33.54 | AX50: 44998 | AY50: 58.47 | AZ50: =AY50*$AZ$1+AZ49*(1-$AZ$1) -> 68.749235 | BC50: =AZ50-AVERAGE(AZ30:AZ50) -> -1.6925429 | BE50: =AZ50+BC50 -> 67.056693 | CC50: 43171 | CD50: 33.54
B51: 44999 | C51: 59.76 | D51: =AVERAGE(C31:C51) -> 69.52381 | Z51: 43172 | AA51: 33.01 | AX51: 44999 | AY51: 59.76 | AZ51: =AY51*$AZ$1+AZ50*(1-$AZ$1) -> 67.893118 | BC51: =AZ51-AVERAGE(AZ31:AZ51) -> -2.4612349 | BE51: =AZ51+BC51 -> 65.431883 | CC51: 43172 | CD51: 33.01
B52: 45000 | C52: 57.61 | D52: =AVERAGE(C32:C52) -> 68.882857 | Z52: 43173 | AA52: 32.83 | AX52: 45000 | AY52: 57.61 | AZ52: =AY52*$AZ$1+AZ51*(1-$AZ$1) -> 66.913773 | BC52: =AZ52-AVERAGE(AZ32:AZ52) -> -3.300437 | BE52: =AZ52+BC52 -> 63.613336 | CC52: 43173 | CD52: 32.83
B53: 45001 | C53: 58.75 | D53: =AVERAGE(C33:C53) -> 68.268095 | E53: =AVERAGE(C3:C53) -> 68.635098 | F53: =D53-E53 -> -0.3670028 | Z53: 43174 | AA53: 32.37 | AX53: 45001 | AY53: 58.75 | AZ53: =AY53*$AZ$1+AZ52*(1-$AZ$1) -> 66.136271 | BA53: =AVERAGE(AY3:AY53) -> 68.635098 | BC53: =AZ53-AVERAGE(AZ33:AZ53) -> -3.892595 | BE53: =AZ53+BC53 -> 62.243676 | CC53: 43174 | CD53: 32.37
B54: 45002 | C54: 56.53 | D54: =AVERAGE(C34:C54) -> 67.510952 | E54: =AVERAGE(C4:C54) -> 68.511961 | F54: =D54-E54 -> -1.0010084 | Z54: 43175 | AA54: 32.05 | AX54: 45002 | AY54: 56.53 | AZ54: =AY54*$AZ$1+AZ53*(1-$AZ$1) -> 65.221388 | BA54: =AY54*$BA$1+BA53*(1-$BA$1) -> 68.160388 | BC54: =AZ54-AVERAGE(AZ34:AZ54) -> -4.5676766 | BE54: =AZ54+BC54 -> 60.653711 | CC54: 43175 | CD54: 32.05
B55: 45005 | C55: 56.81 | D55: =AVERAGE(C35:C55) -> 66.783333 | E55: =AVERAGE(C5:C55) -> 68.363922 | F55: =D55-E55 -> -1.5805882 | Z55: 43178 | AA55: 31.27 | AX55: 45005 | AY55: 56.81 | AZ55: =AY55*$AZ$1+AZ54*(1-$AZ$1) -> 64.420303 | BA55: =AY55*$BA$1+BA54*(1-$BA$1) -> 67.715275 | BC55: =AZ55-AVERAGE(AZ35:AZ55) -> -5.0825011 | BE55: =AZ55+BC55 -> 59.337802 | CC55: 43178 | CD55: 31.27
B56: 45006 | C56: 60.71 | D56: =AVERAGE(C36:C56) -> 66.272381 | E56: =AVERAGE(C6:C56) -> 68.32 | F56: =D56-E56 -> -2.047619 | Z56: 43179 | AA56: 31.76 | AX56: 45006 | AY56: 60.71 | AZ56: =AY56*$AZ$1+AZ55*(1-$AZ$1) -> 64.066941 | BA56: =AY56*$BA$1+BA55*(1-$BA$1) -> 67.440558 | BC56: =AZ56-AVERAGE(AZ36:AZ56) -> -5.1282039 | BE56: =AZ56+BC56 -> 58.938737 | CC56: 43179 | CD56: 31.76
B57: 45007 | C57: 58.93 | D57: =AVERAGE(C37:C57) -> 65.77619 | E57: =AVERAGE(C7:C57) -> 68.214118 | F57: =D57-E57 -> -2.4379272 | Z57: 43180 | AA57: 31.99 | AX57: 45007 | AY57: 58.93 | AZ57: =AY57*$AZ$1+AZ56*(1-$AZ$1) -> 63.577709 | BA57: =AY57*$BA$1+BA56*(1-$BA$1) -> 67.106811 | BC57: =AZ57-AVERAGE(AZ37:AZ57) -> -5.2918217 | BE57: =AZ57+BC57 -> 58.285887 | CC57: 43180 | CD57: 31.99
B58: 45008 | C58: 57.7 | D58: =AVERAGE(C38:C58) -> 65.177619 | E58: =AVERAGE(C8:C58) -> 68.064706 | F58: =D58-E58 -> -2.8870868 | Z58: 43181 | AA58: 30.52 | AX58: 45008 | AY58: 57.7 | AZ58: =AY58*$AZ$1+AZ57*(1-$AZ$1) -> 63.017927 | BA58: =AY58*$BA$1+BA57*(1-$BA$1) -> 66.737916 | BC58: =AZ58-AVERAGE(AZ38:AZ58) -> -5.4999929 | BE58: =AZ58+BC58 -> 57.517934 | CC58: 43181 | CD58: 30.52
B59: 45009 | C59: 57.54 | D59: =AVERAGE(C39:C59) -> 64.526667 | E59: =AVERAGE(C9:C59) -> 67.888627 | F59: =D59-E59 -> -3.3619608 | Z59: 43182 | AA59: 30.16 | AX59: 45009 | AY59: 57.54 | AZ59: =AY59*$AZ$1+AZ58*(1-$AZ$1) -> 62.49622 | BA59: =AY59*$BA$1+BA58*(1-$BA$1) -> 66.377214 | BC59: =AZ59-AVERAGE(AZ39:AZ59) -> -5.6415808 | BE59: =AZ59+BC59 -> 56.854639 | CC59: 43182 | CD59: 30.16
B60: 45012 | C60: 58.95 | D60: =AVERAGE(C40:C60) -> 63.959048 | E60: =AVERAGE(C10:C60) -> 67.717451 | F60: =D60-E60 -> -3.7584034 | Z60: 43185 | AA60: 30.51 | AX60: 45012 | AY60: 58.95 | AZ60: =AY60*$AZ$1+AZ59*(1-$AZ$1) -> 62.158484 | BA60: =AY60*$BA$1+BA59*(1-$BA$1) -> 66.085951 | BC60: =AZ60-AVERAGE(AZ40:AZ60) -> -5.5813396 | BE60: =AZ60+BC60 -> 56.577145 | CC60: 43185 | CD60: 30.51
B61: 45013 | C61: 59.1 | D61: =AVERAGE(C41:C61) -> 63.42 | E61: =AVERAGE(C11:C61) -> 67.534314 | F61: =D61-E61 -> -4.1143137 | Z61: 43186 | AA61: 30.23 | AX61: 45013 | AY61: 59.1 | AZ61: =AY61*$AZ$1+AZ60*(1-$AZ$1) -> 61.8672 | BA61: =AY61*$BA$1+BA60*(1-$BA$1) -> 65.811992 | BC61: =AZ61-AVERAGE(AZ41:AZ61) -> -5.461212 | BE61: =AZ61+BC61 -> 56.405988 | CC61: 43186 | CD61: 30.23
B62: 45014 | C62: 60.66 | D62: =AVERAGE(C42:C62) -> 62.932381 | E62: =AVERAGE(C12:C62) -> 67.356863 | F62: =D62-E62 -> -4.4244818 | Z62: 43187 | AA62: 29.62 | AX62: 45014 | AY62: 60.66 | AZ62: =AY62*$AZ$1+AZ61*(1-$AZ$1) -> 61.752229 | BA62: =AY62*$BA$1+BA61*(1-$BA$1) -> 65.609953 | BC62: =AZ62-AVERAGE(AZ42:AZ62) -> -5.1575138 | BE62: =AZ62+BC62 -> 56.594715 | CC62: 43187 | CD62: 29.62
B63: 45015 | C63: 61.45 | D63: =AVERAGE(C43:C63) -> 62.432857 | E63: =AVERAGE(C13:C63) -> 67.207059 | F63: =D63-E63 -> -4.7742017 | Z63: 43188 | AA63: 29.62 | AX63: 45015 | AY63: 61.45 | AZ63: =AY63*$AZ$1+AZ62*(1-$AZ$1) -> 61.723445 | BA63: =AY63*$BA$1+BA62*(1-$BA$1) -> 65.446817 | BC63: =AZ63-AVERAGE(AZ43:AZ63) -> -4.7599275 | BE63: =AZ63+BC63 -> 56.963518 | CC63: 43188 | CD63: 29.62
B64: 45016 | C64: 63.16 | D64: =AVERAGE(C44:C64) -> 61.99381 | E64: =AVERAGE(C14:C64) -> 67.111569 | F64: =D64-E64 -> -5.1177591 | Z64: 43192 | AA64: 29.78 | AX64: 45016 | AY64: 63.16 | AZ64: =AY64*$AZ$1+AZ63*(1-$AZ$1) -> 61.86026 | BA64: =AY64*$BA$1+BA63*(1-$BA$1) -> 65.357138 | BC64: =AZ64-AVERAGE(AZ44:AZ64) -> -4.1955353 | BE64: =AZ64+BC64 -> 57.664725 | CC64: 43192 | CD64: 29.78
B65: 45019 | C65: 62.4 | D65: =AVERAGE(C45:C65) -> 61.48381 | E65: =AVERAGE(C15:C65) -> 67.045294 | F65: =D65-E65 -> -5.5614846 | Z65: 43193 | AA65: 30.14 | AX65: 45019 | AY65: 62.4 | AZ65: =AY65*$AZ$1+AZ64*(1-$AZ$1) -> 61.911664 | BA65: =AY65*$BA$1+BA64*(1-$BA$1) -> 65.241172 | BC65: =AZ65-AVERAGE(AZ45:AZ65) -> -3.7087043 | BE65: =AZ65+BC65 -> 58.202959 | CC65: 43193 | CD65: 30.14
... B102: 45071 | C102: 64.23 | D102: =AVERAGE(C82:C102) -> 62.774762 | E102: =AVERAGE(C52:C102) -> 61.978039 | F102: =D102-E102 -> 0.79672269 | Z102: 43244 | AA102: 31.27 | AX102: 45071 | AY102: 64.23 | AZ102: =AY102*$AZ$1+AZ101*(1-$AZ$1) -> 63.270273 | BA102: =AY102*$BA$1+BA101*(1-$BA$1) -> 63.569673 | BC102: =AZ102-AVERAGE(AZ82:AZ102) -> 0.59816631 | BE102: =AZ102+BC102 -> 63.868439 | CC102: 43244 | CD102: 31.27
B103: 45072 | C103: 65.42 | D103: =AVERAGE(C83:C103) -> 62.904762 | E103: =AVERAGE(C53:C103) -> 62.131176 | F103: =D103-E103 -> 0.77358543 | Z103: 43245 | AA103: 31.62 | AX103: 45072 | AY103: 65.42 | AZ103: =AY103*$AZ$1+AZ102*(1-$AZ$1) -> 63.475009 | BA103: =AY103*$BA$1+BA102*(1-$BA$1) -> 63.642235 | BC103: =AZ103-AVERAGE(AZ83:AZ103) -> 0.78074458 | BD103: =BA103-AVERAGE(BA53:BA103) -> -1.0812991 | BE103: =AZ103+BC103 -> 64.255753 | BF103: =BA103+BD103 -> 62.560936 | CC103: 43245 | CD103: 31.62
B104: 45076 | C104: 66.78 | D104: =AVERAGE(C84:C104) -> 63.06619 | E104: =AVERAGE(C54:C104) -> 62.288627 | F104: =D104-E104 -> 0.77756303 | Z104: 43249 | AA104: 31.4 | AX104: 45076 | AY104: 66.78 | AZ104: =AY104*$AZ$1+AZ103*(1-$AZ$1) -> 63.78977 | BA104: =AY104*$BA$1+BA103*(1-$BA$1) -> 63.765285 | BC104: =AZ104-AVERAGE(AZ84:AZ104) -> 1.0600841 | BD104: =BA104-AVERAGE(BA54:BA104) -> -0.86276298 | BE104: =AZ104+BC104 -> 64.849854 | BF104: =BA104+BD104 -> 62.902522 | CC104: 43249 | CD104: 31.4
B105: 45077 | C105: 66.85 | D105: =AVERAGE(C85:C105) -> 63.215238 | E105: =AVERAGE(C55:C105) -> 62.49098 | F105: =D105-E105 -> 0.7242577 | Z105: 43250 | AA105: 31.48 | AX105: 45077 | AY105: 66.85 | AZ105: =AY105*$AZ$1+AZ104*(1-$AZ$1) -> 64.08122 | BA105: =AY105*$BA$1+BA104*(1-$BA$1) -> 63.886254 | BC105: =AZ105-AVERAGE(AZ85:AZ105) -> 1.3052915 | BD105: =BA105-AVERAGE(BA55:BA105) -> -0.6579872 | BE105: =AZ105+BC105 -> 65.386512 | BF105: =BA105+BD105 -> 63.228267 | CC105: 43250 | CD105: 31.48
B106: 45078 | C106: 68 | D106: =AVERAGE(C86:C106) -> 63.53619 | E106: =AVERAGE(C56:C106) -> 62.710392 | F106: =D106-E106 -> 0.82579832 | Z106: 43251 | AA106: 31.32 | AX106: 45078 | AY106: 68 | AZ106: =AY106*$AZ$1+AZ105*(1-$AZ$1) -> 64.454437 | BA106: =AY106*$BA$1+BA105*(1-$BA$1) -> 64.047577 | BC106: =AZ106-AVERAGE(AZ86:AZ106) -> 1.6061027 | BD106: =BA106-AVERAGE(BA56:BA106) -> -0.42474818 | BE106: =AZ106+BC106 -> 66.06054 | BF106: =BA106+BD106 -> 63.622829 | CC106: 43251 | CD106: 31.32
B107: 45079 | C107: 69.7 | D107: =AVERAGE(C87:C107) -> 63.95381 | E107: =AVERAGE(C57:C107) -> 62.886667 | F107: =D107-E107 -> 1.0671429 | Z107: 43252 | AA107: 32.33 | AX107: 45079 | AY107: 69.7 | AZ107: =AY107*$AZ$1+AZ106*(1-$AZ$1) -> 64.954015 | BA107: =AY107*$BA$1+BA106*(1-$BA$1) -> 64.269241 | BC107: =AZ107-AVERAGE(AZ87:AZ107) -> 2.0003968 | BD107: =BA107-AVERAGE(BA57:BA107) -> -0.14090184 | BE107: =AZ107+BC107 -> 66.954412 | BF107: =BA107+BD107 -> 64.128339 | CC107: 43252 | CD107: 32.33
B108: 45082 | C108: 70.5 | D108: =AVERAGE(C88:C108) -> 64.547143 | E108: =AVERAGE(C58:C108) -> 63.113529 | F108: =D108-E108 -> 1.4336134 | Z108: 43255 | AA108: 32.18 | AX108: 45082 | AY108: 70.5 | AZ108: =AY108*$AZ$1+AZ107*(1-$AZ$1) -> 65.482204 | BA108: =AY108*$BA$1+BA107*(1-$BA$1) -> 64.513584 | BC108: =AZ108-AVERAGE(AZ88:AZ108) -> 2.3768216 | BD108: =BA108-AVERAGE(BA58:BA108) -> 0.15428923 | BE108: =AZ108+BC108 -> 67.859025 | BF108: =BA108+BD108 -> 64.667874 | CC108: 43255 | CD108: 32.18
B109: 45083 | C109: 70.93 | D109: =AVERAGE(C89:C109) -> 65.042381 | E109: =AVERAGE(C59:C109) -> 63.372941 | F109: =D109-E109 -> 1.6694398 | Z109: 43256 | AA109: 32.29 | AX109: 45083 | AY109: 70.93 | AZ109: =AY109*$AZ$1+AZ108*(1-$AZ$1) -> 66.001042 | BA109: =AY109*$BA$1+BA108*(1-$BA$1) -> 64.765209 | BC109: =AZ109-AVERAGE(AZ89:AZ109) -> 2.7111833 | BD109: =BA109-AVERAGE(BA59:BA109) -> 0.44459392 | BE109: =AZ109+BC109 -> 68.712225 | BF109: =BA109+BD109 -> 65.209802 | CC109: 43256 | CD109: 32.29
B110: 45084 | C110: 71.58 | D110: =AVERAGE(C90:C110) -> 65.506667 | E110: =AVERAGE(C60:C110) -> 63.648235 | F110: =D110-E110 -> 1.8584314 | Z110: 43257 | AA110: 32.23 | AX110: 45084 | AY110: 71.58 | AZ110: =AY110*$AZ$1+AZ109*(1-$AZ$1) -> 66.532371 | BA110: =AY110*$BA$1+BA109*(1-$BA$1) -> 65.032455 | BC110: =AZ110-AVERAGE(AZ90:AZ110) -> 3.031388 | BD110: =BA110-AVERAGE(BA60:BA110) -> 0.73820846 | BE110: =AZ110+BC110 -> 69.563759 | BF110: =BA110+BD110 -> 65.770664 | CC110: 43257 | CD110: 32.23
B111: 45085 | C111: 72.75 | D111: =AVERAGE(C91:C111) -> 66.00619 | E111: =AVERAGE(C61:C111) -> 63.918824 | F111: =D111-E111 -> 2.0873669 | Z111: 43258 | AA111: 32.19 | AX111: 45085 | AY111: 72.75 | AZ111: =AY111*$AZ$1+AZ110*(1-$AZ$1) -> 67.124526 | BA111: =AY111*$BA$1+BA110*(1-$BA$1) -> 65.335104 | BC111: =AZ111-AVERAGE(AZ91:AZ111) -> 3.384952 | BD111: =BA111-AVERAGE(BA61:BA111) -> 1.0555798 | BE111: =AZ111+BC111 -> 70.509478 | BF111: =BA111+BD111 -> 66.390684 | CC111: 43258 | CD111: 32.19
B112: 45086 | C112: 72.98 | D112: =AVERAGE(C92:C112) -> 66.450952 | E112: =AVERAGE(C62:C112) -> 64.19098 | F112: =D112-E112 -> 2.259972 | Z112: 43259 | AA112: 32.24 | AX112: 45086 | AY112: 72.98 | AZ112: =AY112*$AZ$1+AZ111*(1-$AZ$1) -> 67.68219 | BA112: =AY112*$BA$1+BA111*(1-$BA$1) -> 65.634904 | BC112: =AZ112-AVERAGE(AZ92:AZ112) -> 3.6843897 | BD112: =BA112-AVERAGE(BA62:BA112) -> 1.3588519 | BE112: =AZ112+BC112 -> 71.36658 | BF112: =BA112+BD112 -> 66.993756 | CC112: 43259 | CD112: 32.24
B113: 45089 | C113: 73.64 | D113: =AVERAGE(C93:C113) -> 66.923333 | E113: =AVERAGE(C63:C113) -> 64.44549 | F113: =D113-E113 -> 2.4778431 | Z113: 43262 | AA113: 32.33 | AX113: 45089 | AY113: 73.64 | AZ113: =AY113*$AZ$1+AZ112*(1-$AZ$1) -> 68.249601 | BA113: =AY113*$BA$1+BA112*(1-$BA$1) -> 65.948829 | BC113: =AZ113-AVERAGE(AZ93:AZ113) -> 3.973178 | BD113: =BA113-AVERAGE(BA63:BA113) -> 1.6661326 | BE113: =AZ113+BC113 -> 72.222779 | BF113: =BA113+BD113 -> 67.614962 | CC113: 43262 | CD113: 32.33
B114: 45090 | C114: 76.01 | D114: =AVERAGE(C94:C114) -> 67.56619 | E114: =AVERAGE(C64:C114) -> 64.73098 | F114: =D114-E114 -> 2.8352101 | Z114: 43263 | AA114: 32 | AX114: 45090 | AY114: 76.01 | AZ114: =AY114*$AZ$1+AZ113*(1-$AZ$1) -> 68.988686 | BA114: =AY114*$BA$1+BA113*(1-$BA$1) -> 66.343385 | BC114: =AZ114-AVERAGE(AZ94:AZ114) -> 4.3989524 | BD114: =BA114-AVERAGE(BA64:BA114) -> 2.0431086 | BE114: =AZ114+BC114 -> 73.387639 | BF114: =BA114+BD114 -> 68.386494 | CC114: 43263 | CD114: 32
... B202: 45217 | C202: 87.25 | D202: =AVERAGE(C182:C202) -> 89.317619 | E202: =AVERAGE(C152:C202) -> 86.903725 | F202: =D202-E202 -> 2.4138936 | Z202: 43389 | AA202: 31.74 | AX202: 45217 | AY202: 87.25 | AZ202: =AY202*$AZ$1+AZ201*(1-$AZ$1) -> 88.584656 | BA202: =AY202*$BA$1+BA201*(1-$BA$1) -> 86.724506 | BC202: =AZ202-AVERAGE(AZ182:AZ202) -> -0.42642453 | BD202: =BA202-AVERAGE(BA152:BA202) -> 4.4530325 | BE202: =AZ202+BC202 -> 88.158232 | BF202: =BA202+BD202 -> 91.177539 | CC202: 43389 | CD202: 31.74
B203: 45218 | C203: 83.38 | D203: =AVERAGE(C183:C203) -> 88.90619 | E203: =AVERAGE(C153:C203) -> 86.921373 | F203: =D203-E203 -> 1.9848179 | Z203: 43390 | AA203: 31.68 | AB203: =AVERAGE(AA3:AA203) -> 33.005274 | AX203: 45218 | AY203: 83.38 | AZ203: =AY203*$AZ$1+AZ202*(1-$AZ$1) -> 88.088975 | BA203: =AY203*$BA$1+BA202*(1-$BA$1) -> 86.593349 | BC203: =AZ203-AVERAGE(AZ183:AZ203) -> -0.91211652 | BD203: =BA203-AVERAGE(BA153:BA203) -> 4.1395264 | BE203: =AZ203+BC203 -> 87.176858 | BF203: =BA203+BD203 -> 90.732875 | CC203: 43390 | CD203: 31.68 | CE203: =AVERAGE(CD3:CD203) -> 33.005274
B204: 45219 | C204: 82.36 | D204: =AVERAGE(C184:C204) -> 88.522857 | E204: =AVERAGE(C154:C204) -> 86.934314 | F204: =D204-E204 -> 1.5885434 | Z204: 43391 | AA204: 30.37 | AB204: =AVERAGE(AA4:AA204) -> 32.989204 | AX204: 45219 | AY204: 82.36 | AZ204: =AY204*$AZ$1+AZ203*(1-$AZ$1) -> 87.543358 | BA204: =AY204*$BA$1+BA203*(1-$BA$1) -> 86.427335 | BC204: =AZ204-AVERAGE(AZ184:AZ204) -> -1.4121871 | BD204: =BA204-AVERAGE(BA154:BA204) -> 3.7978072 | BE204: =AZ204+BC204 -> 86.131171 | BF204: =BA204+BD204 -> 90.225142 | CC204: 43391 | CD204: 30.37 | CE204: =CD204*$CE$1+CE203*(1-$CE$1) -> 32.979052
B205: 45222 | C205: 82.82 | D205: =AVERAGE(C185:C205) -> 88.142381 | E205: =AVERAGE(C155:C205) -> 86.958235 | F205: =D205-E205 -> 1.1841457 | Z205: 43392 | AA205: 29.49 | AB205: =AVERAGE(AA5:AA205) -> 32.965423 | AX205: 45222 | AY205: 82.82 | AZ205: =AY205*$AZ$1+AZ204*(1-$AZ$1) -> 87.093515 | BA205: =AY205*$BA$1+BA204*(1-$BA$1) -> 86.285871 | BC205: =AZ205-AVERAGE(AZ185:AZ205) -> -1.7845865 | BD205: =BA205-AVERAGE(BA155:BA205) -> 3.4865899 | BE205: =AZ205+BC205 -> 85.308928 | BF205: =BA205+BD205 -> 89.772461 | CC205: 43392 | CD205: 29.49 | CE205: =CD205*$CE$1+CE204*(1-$CE$1) -> 32.944335
B206: 45223 | C206: 84 | D206: =AVERAGE(C186:C206) -> 87.738571 | E206: =AVERAGE(C156:C206) -> 87.00902 | F206: =D206-E206 -> 0.72955182 | Z206: 43395 | AA206: 29.49 | AB206: =AVERAGE(AA6:AA206) -> 32.941443 | AX206: 45223 | AY206: 84 | AZ206: =AY206*$AZ$1+AZ205*(1-$AZ$1) -> 86.798894 | BA206: =AY206*$BA$1+BA205*(1-$BA$1) -> 86.196229 | BC206: =AZ206-AVERAGE(AZ186:AZ206) -> -1.9706803 | BD206: =BA206-AVERAGE(BA156:BA206) -> 3.2318601 | BE206: =AZ206+BC206 -> 84.828214 | BF206: =BA206+BD206 -> 89.428089 | CC206: 43395 | CD206: 29.49 | CE206: =CD206*$CE$1+CE205*(1-$CE$1) -> 32.909964
B207: 45224 | C207: 81.4 | D207: =AVERAGE(C187:C207) -> 87.334762 | E207: =AVERAGE(C157:C207) -> 86.998039 | F207: =D207-E207 -> 0.33672269 | Z207: 43396 | AA207: 29.47 | AB207: =AVERAGE(AA7:AA207) -> 32.916517 | AX207: 45224 | AY207: 81.4 | AZ207: =AY207*$AZ$1+AZ206*(1-$AZ$1) -> 86.284714 | BA207: =AY207*$BA$1+BA206*(1-$BA$1) -> 86.008142 | BC207: =AZ207-AVERAGE(AZ187:AZ207) -> -2.3482119 | BD207: =BA207-AVERAGE(BA157:BA207) -> 2.8855895 | BE207: =AZ207+BC207 -> 83.936502 | BF207: =BA207+BD207 -> 88.893731 | CC207: 43396 | CD207: 29.47 | CE207: =CD207*$CE$1+CE206*(1-$CE$1) -> 32.875735
B208: 45225 | C208: 81.02 | D208: =AVERAGE(C188:C208) -> 86.928571 | E208: =AVERAGE(C158:C208) -> 87.007843 | F208: =D208-E208 -> -0.079271709 | Z208: 43397 | AA208: 28.35 | AB208: =AVERAGE(AA8:AA208) -> 32.883831 | AX208: 45225 | AY208: 81.02 | AZ208: =AY208*$AZ$1+AZ207*(1-$AZ$1) -> 85.783312 | BA208: =AY208*$BA$1+BA207*(1-$BA$1) -> 85.812528 | BC208: =AZ208-AVERAGE(AZ188:AZ208) -> -2.6872937 | BD208: =BA208-AVERAGE(BA158:BA208) -> 2.5376118 | BE208: =AZ208+BC208 -> 83.096019 | BF208: =BA208+BD208 -> 88.35014 | CC208: 43397 | CD208: 28.35 | CE208: =CD208*$CE$1+CE207*(1-$CE$1) -> 32.830703
B209: 45226 | C209: 80.35 | D209: =AVERAGE(C189:C209) -> 86.416667 | E209: =AVERAGE(C159:C209) -> 87.009608 | F209: =D209-E209 -> -0.59294118 | Z209: 43398 | AA209: 29.86 | AB209: =AVERAGE(AA9:AA209) -> 32.854826 | AX209: 45226 | AY209: 80.35 | AZ209: =AY209*$AZ$1+AZ208*(1-$AZ$1) -> 85.265854 | BA209: =AY209*$BA$1+BA208*(1-$BA$1) -> 85.598311 | BC209: =AZ209-AVERAGE(AZ189:AZ209) -> -3.0091388 | BD209: =BA209-AVERAGE(BA159:BA209) -> 2.1769365 | BE209: =AZ209+BC209 -> 82.256715 | BF209: =BA209+BD209 -> 87.775248 | CC209: 43398 | CD209: 29.86 | CE209: =CD209*$CE$1+CE208*(1-$CE$1) -> 32.801144
B210: 45229 | C210: 80.16 | D210: =AVERAGE(C190:C210) -> 85.959524 | E210: =AVERAGE(C160:C210) -> 87.028431 | F210: =D210-E210 -> -1.0689076 | Z210: 43399 | AA210: 30.31 | AB210: =AVERAGE(AA10:AA210) -> 32.828706 | AX210: 45229 | AY210: 80.16 | AZ210: =AY210*$AZ$1+AZ209*(1-$AZ$1) -> 84.779582 | BA210: =AY210*$BA$1+BA209*(1-$BA$1) -> 85.385044 | BC210: =AZ210-AVERAGE(AZ190:AZ210) -> -3.2748897 | BD210: =BA210-AVERAGE(BA160:BA210) -> 1.8222162 | BE210: =AZ210+BC210 -> 81.504693 | BF210: =BA210+BD210 -> 87.207261 | CC210: 43399 | CD210: 30.31 | CE210: =CD210*$CE$1+CE209*(1-$CE$1) -> 32.776356
B211: 45230 | C211: 77.44 | D211: =AVERAGE(C191:C211) -> 85.380476 | E211: =AVERAGE(C161:C211) -> 86.95549 | F211: =D211-E211 -> -1.575014 | Z211: 43402 | AA211: 29.53 | AB211: =AVERAGE(AA11:AA211) -> 32.797065 | AX211: 45230 | AY211: 77.44 | AZ211: =AY211*$AZ$1+AZ210*(1-$AZ$1) -> 84.080574 | BA211: =AY211*$BA$1+BA210*(1-$BA$1) -> 85.073474 | BC211: =AZ211-AVERAGE(AZ191:AZ211) -> -3.7192313 | BD211: =BA211-AVERAGE(BA161:BA211) -> 1.3776002 | BE211: =AZ211+BC211 -> 80.361343 | BF211: =BA211+BD211 -> 86.451074 | CC211: 43402 | CD211: 29.53 | CE211: =CD211*$CE$1+CE210*(1-$CE$1) -> 32.744054
B212: 45231 | C212: 83.65 | D212: =AVERAGE(C192:C212) -> 85.241905 | E212: =AVERAGE(C162:C212) -> 86.996667 | F212: =D212-E212 -> -1.7547619 | Z212: 43403 | AA212: 29.92 | AB212: =AVERAGE(AA12:AA212) -> 32.765871 | AX212: 45231 | AY212: 83.65 | AZ212: =AY212*$AZ$1+AZ211*(1-$AZ$1) -> 84.039567 | BA212: =AY212*$BA$1+BA211*(1-$BA$1) -> 85.017651 | BC212: =AZ212-AVERAGE(AZ192:AZ212) -> -3.5166288 | BD212: =BA212-AVERAGE(BA162:BA212) -> 1.1923349 | BE212: =AZ212+BC212 -> 80.522939 | BF212: =BA212+BD212 -> 86.209986 | CC212: 43403 | CD212: 29.92 | CE212: =CD212*$CE$1+CE211*(1-$CE$1) -> 32.715954
B213: 45232 | C213: 84.12 | D213: =AVERAGE(C193:C213) -> 85.058571 | E213: =AVERAGE(C163:C213) -> 87.047451 | F213: =D213-E213 -> -1.9888796 | Z213: 43404 | AA213: 29.42 | AB213: =AVERAGE(AA13:AA213) -> 32.737711 | AX213: 45232 | AY213: 84.12 | AZ213: =AY213*$AZ$1+AZ212*(1-$AZ$1) -> 84.047228 | BA213: =AY213*$BA$1+BA212*(1-$BA$1) -> 84.982449 | BC213: =AZ213-AVERAGE(AZ193:AZ213) -> -3.2710995 | BD213: =BA213-AVERAGE(BA163:BA213) -> 1.0307746 | BE213: =AZ213+BC213 -> 80.776128 | BF213: =BA213+BD213 -> 86.013224 | CC213: 43404 | CD213: 29.42 | CE213: =CD213*$CE$1+CE212*(1-$CE$1) -> 32.683159
B214: 45233 | C214: 85.03 | D214: =AVERAGE(C194:C214) -> 84.889524 | E214: =AVERAGE(C164:C214) -> 87.086078 | F214: =D214-E214 -> -2.1965546 | Z214: 43405 | AA214: 30.59 | AB214: =AVERAGE(AA14:AA214) -> 32.713682 | AX214: 45233 | AY214: 85.03 | AZ214: =AY214*$AZ$1+AZ213*(1-$AZ$1) -> 84.140825 | BA214: =AY214*$BA$1+BA213*(1-$BA$1) -> 84.984314 | BC214: =AZ214-AVERAGE(AZ194:AZ214) -> -2.9461875 | BD214: =BA214-AVERAGE(BA164:BA214) -> 0.90972159 | BE214: =AZ214+BC214 -> 81.194637 | BF214: =BA214+BD214 -> 85.894036 | CC214: 43405 | CD214: 30.59 | CE214: =CD214*$CE$1+CE213*(1-$CE$1) -> 32.662331
B215: 45236 | C215: 83.15 | D215: =AVERAGE(C195:C215) -> 84.53619 | E215: =AVERAGE(C165:C215) -> 87.098431 | F215: =D215-E215 -> -2.5622409 | Z215: 43406 | AA215: 29.56 | AB215: =AVERAGE(AA15:AA215) -> 32.686269 | AX215: 45236 | AY215: 83.15 | AZ215: =AY215*$AZ$1+AZ214*(1-$AZ$1) -> 84.046461 | BA215: =AY215*$BA$1+BA214*(1-$BA$1) -> 84.91238 | BC215: =AZ215-AVERAGE(AZ195:AZ215) -> -2.7976164 | BD215: =BA215-AVERAGE(BA165:BA215) -> 0.71920579 | BE215: =AZ215+BC215 -> 81.248844 | BF215: =BA215+BD215 -> 85.631586 | CC215: 43406 | CD215: 29.56 | CE215: =CD215*$CE$1+CE214*(1-$CE$1) -> 32.631462
... B402: 45510 | C402: 103.46 | D402: =AVERAGE(C382:C402) -> 118.69286 | E402: =AVERAGE(C352:C402) -> 117.54196 | F402: =D402-E402 -> 1.1508964 | Z402: 43682 | AA402: 31.43 | AB402: =AVERAGE(AA202:AA402) -> 30.100348 | AX402: 45510 | AY402: 103.46 | AZ402: =AY402*$AZ$1+AZ401*(1-$AZ$1) -> 116.04201 | BA402: =AY402*$BA$1+BA401*(1-$BA$1) -> 116.65652 | BC402: =AZ402-AVERAGE(AZ382:AZ402) -> -3.2957292 | BD402: =BA402-AVERAGE(BA352:BA402) -> 1.8866226 | BE402: =AZ402+BC402 -> 112.74628 | BF402: =BA402+BD402 -> 118.54314 | CC402: 43682 | CD402: 31.43 | CE402: =CD402*$CE$1+CE401*(1-$CE$1) -> 31.684863
B403: 45511 | C403: 103.12 | D403: =AVERAGE(C383:C403) -> 118.04714 | E403: =AVERAGE(C353:C403) -> 117.35059 | F403: =D403-E403 -> 0.69655462 | Z403: 43683 | AA403: 33.26 | AB403: =AVERAGE(AA203:AA403) -> 30.10791 | AX403: 45511 | AY403: 103.12 | AZ403: =AY403*$AZ$1+AZ402*(1-$AZ$1) -> 114.81134 | BA403: =AY403*$BA$1+BA402*(1-$BA$1) -> 116.12568 | BC403: =AZ403-AVERAGE(AZ383:AZ403) -> -4.4034829 | BD403: =BA403-AVERAGE(BA353:BA403) -> 1.2545752 | BE403: =AZ403+BC403 -> 110.40786 | BF403: =BA403+BD403 -> 117.38025 | CC403: 43683 | CD403: 33.26 | CE403: =CD403*$CE$1+CE402*(1-$CE$1) -> 31.700536 | CG403: =CE403-AVERAGE(CE203:CE403) -> 0.94015431 | CH403: =CE403+CG403 -> 32.64069
B404: 45512 | C404: 103.19 | D404: =AVERAGE(C384:C404) -> 117.28429 | E404: =AVERAGE(C354:C404) -> 117.10882 | F404: =D404-E404 -> 0.17546218 | Z404: 43684 | AA404: 33.88 | AB404: =AVERAGE(AA204:AA404) -> 30.118856 | AX404: 45512 | AY404: 103.19 | AZ404: =AY404*$AZ$1+AZ403*(1-$AZ$1) -> 113.70455 | BA404: =AY404*$BA$1+BA403*(1-$BA$1) -> 115.61839 | BC404: =AZ404-AVERAGE(AZ384:AZ404) -> -5.3264165 | BD404: =BA404-AVERAGE(BA354:BA404) -> 0.65953991 | BE404: =AZ404+BC404 -> 108.37813 | BF404: =BA404+BD404 -> 116.27793 | CC404: 43684 | CD404: 33.88 | CE404: =CD404*$CE$1+CE403*(1-$CE$1) -> 31.722222 | CG404: =CE404-AVERAGE(CE204:CE404) -> 0.96822386 | CH404: =CE404+CG404 -> 32.690446
B405: 45513 | C405: 104.7 | D405: =AVERAGE(C385:C405) -> 116.50333 | E405: =AVERAGE(C355:C405) -> 116.8951 | F405: =D405-E405 -> -0.39176471 | Z405: 43685 | AA405: 34 | AB405: =AVERAGE(AA205:AA405) -> 30.136915 | AX405: 45513 | AY405: 104.7 | AZ405: =AY405*$AZ$1+AZ404*(1-$AZ$1) -> 112.84697 | BA405: =AY405*$BA$1+BA404*(1-$BA$1) -> 115.19022 | BC405: =AZ405-AVERAGE(AZ385:AZ405) -> -5.9432657 | BD405: =BA405-AVERAGE(BA355:BA405) -> 0.15543647 | BE405: =AZ405+BC405 -> 106.90371 | BF405: =BA405+BD405 -> 115.34566 | CC405: 43685 | CD405: 34 | CE405: =CD405*$CE$1+CE404*(1-$CE$1) -> 31.744886 | CG405: =CE405-AVERAGE(CE205:CE405) -> 0.99702845 | CH405: =CE405+CG405 -> 32.741915
B406: 45516 | C406: 103.03 | D406: =AVERAGE(C386:C406) -> 115.66952 | E406: =AVERAGE(C356:C406) -> 116.69627 | F406: =D406-E406 -> -1.0267507 | Z406: 43686 | AA406: 32.84 | AB406: =AVERAGE(AA206:AA406) -> 30.153582 | AX406: 45516 | AY406: 103.03 | AZ406: =AY406*$AZ$1+AZ405*(1-$AZ$1) -> 111.91202 | BA406: =AY406*$BA$1+BA405*(1-$BA$1) -> 114.71335 | BC406: =AZ406-AVERAGE(AZ386:AZ406) -> -6.5810046 | BD406: =BA406-AVERAGE(BA356:BA406) -> -0.38659142 | BE406: =AZ406+BC406 -> 105.33102 | BF406: =BA406+BD406 -> 114.32676 | CC406: 43686 | CD406: 32.84 | CE406: =CD406*$CE$1+CE405*(1-$CE$1) -> 31.755783 | CG406: =CE406-AVERAGE(CE206:CE406) -> 1.0138383 | CH406: =CE406+CG406 -> 32.769621
B407: 45517 | C407: 104.61 | D407: =AVERAGE(C387:C407) -> 114.81762 | E407: =AVERAGE(C357:C407) -> 116.45784 | F407: =D407-E407 -> -1.6402241 | Z407: 43689 | AA407: 33.07 | AB407: =AVERAGE(AA207:AA407) -> 30.171393 | AX407: 45517 | AY407: 104.61 | AZ407: =AY407*$AZ$1+AZ406*(1-$AZ$1) -> 111.21659 | BA407: =AY407*$BA$1+BA406*(1-$BA$1) -> 114.31714 | BC407: =AZ407-AVERAGE(AZ387:AZ407) -> -6.9263964 | BD407: =BA407-AVERAGE(BA357:BA407) -> -0.83605227 | BE407: =AZ407+BC407 -> 104.2902 | BF407: =BA407+BD407 -> 113.48109 | CC407: 43689 | CD407: 33.07 | CE407: =CD407*$CE$1+CE406*(1-$CE$1) -> 31.76886 | CG407: =CE407-AVERAGE(CE207:CE407) -> 1.0325922 | CH407: =CE407+CG407 -> 32.801452
B408: 45518 | C408: 105.98 | D408: =AVERAGE(C388:C408) -> 113.95952 | E408: =AVERAGE(C358:C408) -> 116.25824 | F408: =D408-E408 -> -2.2987115 | Z408: 43690 | AA408: 33.59 | AB408: =AVERAGE(AA208:AA408) -> 30.191891 | AX408: 45518 | AY408: 105.98 | AZ408: =AY408*$AZ$1+AZ407*(1-$AZ$1) -> 110.71787 | BA408: =AY408*$BA$1+BA407*(1-$BA$1) -> 113.99019 | BC408: =AZ408-AVERAGE(AZ388:AZ408) -> -7.0266943 | BD408: =BA408-AVERAGE(BA358:BA408) -> -1.206334 | BE408: =AZ408+BC408 -> 103.69117 | BF408: =BA408+BD408 -> 112.78386 | CC408: 43690 | CD408: 33.59 | CE408: =CD408*$CE$1+CE407*(1-$CE$1) -> 31.786981 | CG408: =CE408-AVERAGE(CE208:CE408) -> 1.0561297 | CH408: =CE408+CG408 -> 32.84311
B409: 45519 | C409: 110.83 | D409: =AVERAGE(C389:C409) -> 113.46667 | E409: =AVERAGE(C359:C409) -> 116.14608 | F409: =D409-E409 -> -2.6794118 | Z409: 43691 | AA409: 32.12 | AB409: =AVERAGE(AA209:AA409) -> 30.210647 | AX409: 45519 | AY409: 110.83 | AZ409: =AY409*$AZ$1+AZ408*(1-$AZ$1) -> 110.72855 | BA409: =AY409*$BA$1+BA408*(1-$BA$1) -> 113.86627 | BC409: =AZ409-AVERAGE(AZ389:AZ409) -> -6.6085964 | BD409: =BA409-AVERAGE(BA359:BA409) -> -1.3675004 | BE409: =AZ409+BC409 -> 104.11995 | BF409: =BA409+BD409 -> 112.49876 | CC409: 43691 | CD409: 32.12 | CE409: =CD409*$CE$1+CE408*(1-$CE$1) -> 31.790294 | CG409: =CE409-AVERAGE(CE209:CE409) -> 1.0646195 | CH409: =CE409+CG409 -> 32.854914
B410: 45520 | C410: 111 | D410: =AVERAGE(C390:C410) -> 113.02238 | E410: =AVERAGE(C360:C410) -> 116.08961 | F410: =D410-E410 -> -3.0672269 | Z410: 43692 | AA410: 31.11 | AB410: =AVERAGE(AA210:AA410) -> 30.216866 | AX410: 45520 | AY410: 111 | AZ410: =AY410*$AZ$1+AZ409*(1-$AZ$1) -> 110.7544 | BA410: =AY410*$BA$1+BA409*(1-$BA$1) -> 113.75386 | BC410: =AZ410-AVERAGE(AZ390:AZ410) -> -6.171814 | BD410: =BA410-AVERAGE(BA360:BA410) -> -1.5134654 | BE410: =AZ410+BC410 -> 104.58259 | BF410: =BA410+BD410 -> 112.2404 | CC410: 43692 | CD410: 31.11 | CE410: =CD410*$CE$1+CE409*(1-$CE$1) -> 31.783525 | CG410: =CE410-AVERAGE(CE210:CE410) -> 1.0629132 | CH410: =CE410+CG410 -> 32.846438
B411: 45523 | C411: 111.61 | D411: =AVERAGE(C391:C411) -> 112.59857 | E411: =AVERAGE(C361:C411) -> 115.99804 | F411: =D411-E411 -> -3.3994678 | Z411: 43693 | AA411: 32 | AB411: =AVERAGE(AA211:AA411) -> 30.225274 | AX411: 45523 | AY411: 111.61 | AZ411: =AY411*$AZ$1+AZ410*(1-$AZ$1) -> 110.83589 | BA411: =AY411*$BA$1+BA410*(1-$BA$1) -> 113.66979 | BC411: =AZ411-AVERAGE(AZ391:AZ411) -> -5.6781718 | BD411: =BA411-AVERAGE(BA361:BA411) -> -1.6261938 | BE411: =AZ411+BC411 -> 105.15771 | BF411: =BA411+BD411 -> 112.0436 | CC411: 43693 | CD411: 32 | CE411: =CD411*$CE$1+CE410*(1-$CE$1) -> 31.785679 | CG411: =CE411-AVERAGE(CE211:CE411) -> 1.0699959 | CH411: =CE411+CG411 -> 32.855675
B412: 45524 | C412: 109.85 | D412: =AVERAGE(C392:C412) -> 111.92524 | E412: =AVERAGE(C362:C412) -> 115.93686 | F412: =D412-E412 -> -4.0116246 | Z412: 43696 | AA412: 33.66 | AB412: =AVERAGE(AA212:AA412) -> 30.245821 | AX412: 45524 | AY412: 109.85 | AZ412: =AY412*$AZ$1+AZ411*(1-$AZ$1) -> 110.74199 | BA412: =AY412*$BA$1+BA411*(1-$BA$1) -> 113.51999 | BC412: =AZ412-AVERAGE(AZ392:AZ412) -> -5.3350353 | BD412: =BA412-AVERAGE(BA362:BA412) -> -1.801122 | BE412: =AZ412+BC412 -> 105.40696 | BF412: =BA412+BD412 -> 111.71887 | CC412: 43696 | CD412: 33.66 | CE412: =CD412*$CE$1+CE411*(1-$CE$1) -> 31.804329 | CG412: =CE412-AVERAGE(CE212:CE412) -> 1.0933211 | CH412: =CE412+CG412 -> 32.89765
B413: 45525 | C413: 109.28 | D413: =AVERAGE(C393:C413) -> 111.18429 | E413: =AVERAGE(C363:C413) -> 115.87647 | F413: =D413-E413 -> -4.6921849 | Z413: 43697 | AA413: 34.8 | AB413: =AVERAGE(AA213:AA413) -> 30.2701 | AX413: 45525 | AY413: 109.28 | AZ413: =AY413*$AZ$1+AZ412*(1-$AZ$1) -> 110.60275 | BA413: =AY413*$BA$1+BA412*(1-$BA$1) -> 113.35372 | BC413: =AZ413-AVERAGE(AZ393:AZ413) -> -5.0082972 | BD413: =BA413-AVERAGE(BA363:BA413) -> -1.9891749 | BE413: =AZ413+BC413 -> 105.59446 | BF413: =BA413+BD413 -> 111.36454 | CC413: 43697 | CD413: 34.8 | CE413: =CD413*$CE$1+CE412*(1-$CE$1) -> 31.834137 | CG413: =CE413-AVERAGE(CE213:CE413) -> 1.1275159 | CH413: =CE413+CG413 -> 32.961653
B414: 45526 | C414: 108.47 | D414: =AVERAGE(C394:C414) -> 110.55333 | E414: =AVERAGE(C364:C414) -> 115.67451 | F414: =D414-E414 -> -5.1211765 | Z414: 43698 | AA414: 35.55 | AB414: =AVERAGE(AA214:AA414) -> 30.300597 | AX414: 45526 | AY414: 108.47 | AZ414: =AY414*$AZ$1+AZ413*(1-$AZ$1) -> 110.39964 | BA414: =AY414*$BA$1+BA413*(1-$BA$1) -> 113.1622 | BC414: =AZ414-AVERAGE(AZ394:AZ414) -> -4.7297292 | BD414: =BA414-AVERAGE(BA364:BA414) -> -2.1936978 | BE414: =AZ414+BC414 -> 105.66991 | BF414: =BA414+BD414 -> 110.9685 | CC414: 43698 | CD414: 35.55 | CE414: =CD414*$CE$1+CE413*(1-$CE$1) -> 31.871111 | CG414: =CE414-AVERAGE(CE214:CE414) -> 1.1685297 | CH414: =CE414+CG414 -> 33.03964
... B504: 45657 | C504: 165.16 | D504: =AVERAGE(C484:C504) -> 173.22143 | E504: =AVERAGE(C454:C504) -> 163.71529 | F504: =D504-E504 -> 9.5061345 | Z504: 43829 | AA504: 47.7 | AB504: =AVERAGE(AA304:AA504) -> 36.465473 | AX504: 45657 | AY504: 165.16 | AZ504: =AY504*$AZ$1+AZ503*(1-$AZ$1) -> 170.84285 | BA504: =AY504*$BA$1+BA503*(1-$BA$1) -> 162.89395 | BC504: =AZ504-AVERAGE(AZ484:AZ504) -> 0.80330316 | BD504: =BA504-AVERAGE(BA454:BA504) -> 17.362851 | BE504: =AZ504+BC504 -> 171.64615 | BF504: =BA504+BD504 -> 180.2568 | CC504: 43829 | CD504: 47.7 | CE504: =CD504*$CE$1+CE503*(1-$CE$1) -> 38.054703 | CG504: =CE504-AVERAGE(CE304:CE504) -> 5.6413098 | CH504: =CE504+CG504 -> 43.696013
Z505: 43830 | AA505: 47.71 | AB505: =AVERAGE(AA305:AA505) -> 36.55801 | CC505: 43830 | CD505: 47.71 | CE505: =CD505*$CE$1+CE504*(1-$CE$1) -> 38.150775 | CG505: =CE505-AVERAGE(CE305:CE505) -> 5.6961424 | CH505: =CE505+CG505 -> 43.846918
Z506: 43832 | AA506: 47.66 | AB506: =AVERAGE(AA306:AA506) -> 36.646965 | CC506: 43832 | CD506: 47.66 | CE506: =CD506*$CE$1+CE505*(1-$CE$1) -> 38.245394 | CG506: =CE506-AVERAGE(CE306:CE506) -> 5.7490468 | CH506: =CE506+CG506 -> 43.994441
Z507: 43833 | AA507: 47.31 | AB507: =AVERAGE(AA307:AA507) -> 36.736766 | CC507: 43833 | CD507: 47.31 | CE507: =CD507*$CE$1+CE506*(1-$CE$1) -> 38.33559 | CG507: =CE507-AVERAGE(CE307:CE507) -> 5.7970487 | CH507: =CE507+CG507 -> 44.132638
Z508: 43836 | AA508: 47.58 | AB508: =AVERAGE(AA308:AA508) -> 36.830149 | CC508: 43836 | CD508: 47.58 | CE508: =CD508*$CE$1+CE507*(1-$CE$1) -> 38.427574 | CG508: =CE508-AVERAGE(CE308:CE508) -> 5.8463303 | CH508: =CE508+CG508 -> 44.273904
Z509: 43837 | AA509: 47.63 | AB509: =AVERAGE(AA309:AA509) -> 36.9199 | CC509: 43837 | CD509: 47.63 | CE509: =CD509*$CE$1+CE508*(1-$CE$1) -> 38.51914 | CG509: =CE509-AVERAGE(CE309:CE509) -> 5.894726 | CH509: =CE509+CG509 -> 44.413866
Z510: 43838 | AA510: 48.65 | AB510: =AVERAGE(AA310:AA510) -> 37.022637 | CC510: 43838 | CD510: 48.65 | CE510: =CD510*$CE$1+CE509*(1-$CE$1) -> 38.619945 | CG510: =CE510-AVERAGE(CE310:CE510) -> 5.9517672 | CH510: =CE510+CG510 -> 44.571712
Z511: 43839 | AA511: 49.81 | AB511: =AVERAGE(AA311:AA511) -> 37.131493 | CC511: 43839 | CD511: 49.81 | CE511: =CD511*$CE$1+CE510*(1-$CE$1) -> 38.731289 | CG511: =CE511-AVERAGE(CE311:CE511) -> 6.0186999 | CH511: =CE511+CG511 -> 44.749989
...

Sheet Bollinger Bands
F1: 1.8 | G1: 1.8
B2: Dates | C2: Prices | D2: MA 20d | E2: Std dev | F2: UP Band | G2: DOWN Band | I2: %b | J2: Band amplitude
B3: 44929 | C3: 62.81
B4: 44930 | C4: 64.36
B5: 44931 | C5: 62.95
B6: 44932 | C6: 64.33
B7: 44935 | C7: 65.32
B8: 44936 | C8: 66.52
B9: 44937 | C9: 67.68
B10: 44938 | C10: 68.44
B11: 44939 | C11: 69.71
B12: 44943 | C12: 69.09
B13: 44944 | C13: 68.03
B14: 44945 | C14: 65.78
... B22: 44957 | C22: 70.78
B23: 44958 | C23: 72.52 | D23: =AVERAGE(C3:C23) -> 67.620952 | E23: =STDEV(C3:C23) -> 2.6483427 | F23: =D23+$F$1*E23 -> 72.387969 | G23: =D23-$G$1*E23 -> 62.853936 | I23: =(C23-G23)/(F23-G23) -> 1.0138484 | J23: =(F23-G23)/D23 -> 0.1409923
B24: 44959 | C24: 72.15 | D24: =AVERAGE(C4:C24) -> 68.065714 | E24: =STDEV(C4:C24) -> 2.5834794 | F24: =D24+$F$1*E24 -> 72.715977 | G24: =D24-$G$1*E24 -> 63.415451 | I24: =(C24-G24)/(F24-G24) -> 0.93914568 | J24: =(F24-G24)/D24 -> 0.13664039
B25: 44960 | C25: 73.4 | D25: =AVERAGE(C5:C25) -> 68.49619 | E25: =STDEV(C5:C25) -> 2.6862436 | F25: =D25+$F$1*E25 -> 73.331429 | G25: =D25-$G$1*E25 -> 63.660952 | I25: =(C25-G25)/(F25-G25) -> 1.0070908 | J25: =(F25-G25)/D25 -> 0.1411827
B26: 44963 | C26: 72.14 | D26: =AVERAGE(C6:C26) -> 68.93381 | E26: =STDEV(C6:C26) -> 2.4780385 | F26: =D26+$F$1*E26 -> 73.394279 | G26: =D26-$G$1*E26 -> 64.47334 | I26: =(C26-G26)/(F26-G26) -> 0.85940058 | J26: =(F26-G26)/D26 -> 0.12941311
B27: 44964 | C27: 73.35 | D27: =AVERAGE(C7:C27) -> 69.363333 | E27: =STDEV(C7:C27) -> 2.4212277 | F27: =D27+$F$1*E27 -> 73.721543 | G27: =D27-$G$1*E27 -> 65.005124 | I27: =(C27-G27)/(F27-G27) -> 0.95737434 | J27: =(F27-G27)/D27 -> 0.12566322
B28: 44965 | C28: 73.89 | D28: =AVERAGE(C8:C28) -> 69.771429 | E28: =STDEV(C8:C28) -> 2.4278762 | F28: =D28+$F$1*E28 -> 74.141606 | G28: =D28-$G$1*E28 -> 65.401251 | I28: =(C28-G28)/(F28-G28) -> 0.97121333 | J28: =(F28-G28)/D28 -> 0.12527125
B29: 44966 | C29: 68.4 | D29: =AVERAGE(C9:C29) -> 69.860952 | E29: =STDEV(C9:C29) -> 2.3348702 | F29: =D29+$F$1*E29 -> 74.063719 | G29: =D29-$G$1*E29 -> 65.658186 | I29: =(C29-G29)/(F29-G29) -> 0.32619158 | J29: =(F29-G29)/D29 -> 0.12031804
B30: 44967 | C30: 70.66 | D30: =AVERAGE(C10:C30) -> 70.002857 | E30: =STDEV(C10:C30) -> 2.2857321 | F30: =D30+$F$1*E30 -> 74.117175 | G30: =D30-$G$1*E30 -> 65.888539 | I30: =(C30-G30)/(F30-G30) -> 0.57986049 | J30: =(F30-G30)/D30 -> 0.11754714
B31: 44970 | C31: 71.07 | D31: =AVERAGE(C11:C31) -> 70.128095 | E31: =STDEV(C11:C31) -> 2.2677999 | F31: =D31+$F$1*E31 -> 74.210135 | G31: =D31-$G$1*E31 -> 66.046055 | I31: =(C31-G31)/(F31-G31) -> 0.61537183 | J31: =(F31-G31)/D31 -> 0.11641667
B32: 44971 | C32: 71.66 | D32: =AVERAGE(C12:C32) -> 70.220952 | E32: =STDEV(C12:C32) -> 2.2896417 | F32: =D32+$F$1*E32 -> 74.342307 | G32: =D32-$G$1*E32 -> 66.099597 | I32: =(C32-G32)/(F32-G32) -> 0.67458428 | J32: =(F32-G32)/D32 -> 0.11738249
B33: 44972 | C33: 72.43 | D33: =AVERAGE(C13:C33) -> 70.38 | E33: =STDEV(C13:C33) -> 2.3229163 | F33: =D33+$F$1*E33 -> 74.561249 | G33: =D33-$G$1*E33 -> 66.198751 | I33: =(C33-G33)/(F33-G33) -> 0.74514204 | J33: =(F33-G33)/D33 -> 0.11881925 | L33: A greater width of the bands corresponds to high volatility. A lower amplitude corresponds vice versa to a low volatility. If the bands are converging, the volatility is decreasing. Diverging bands mean an increasing volatility.
B34: 44973 | C34: 72.09 | D34: =AVERAGE(C14:C34) -> 70.573333 | E34: =STDEV(C14:C34) -> 2.2862138 | F34: =D34+$F$1*E34 -> 74.688518 | G34: =D34-$G$1*E34 -> 66.458149 | I34: =(C34-G34)/(F34-G34) -> 0.68427686 | J34: =(F34-G34)/D34 -> 0.11662152
B35: 44974 | C35: 71.44 | D35: =AVERAGE(C15:C35) -> 70.842857 | E35: =STDEV(C15:C35) -> 2.0097889 | F35: =D35+$F$1*E35 -> 74.460477 | G35: =D35-$G$1*E35 -> 67.225237 | I35: =(C35-G35)/(F35-G35) -> 0.58253256 | J35: =(F35-G35)/D35 -> 0.10213083 | L35: According to popular opinions, the Bollinger bands are suggesting to buy or sell when the following conditions occur:
B36: 44978 | C36: 69.35 | D36: =AVERAGE(C16:C36) -> 70.951429 | E36: =STDEV(C16:C36) -> 1.8511031 | F36: =D36+$F$1*E36 -> 74.283414 | G36: =D36-$G$1*E36 -> 67.619443 | I36: =(C36-G36)/(F36-G36) -> 0.25968856 | J36: =(F36-G36)/D36 -> 0.093923004 | L36: • when the price line exits the upper limit of the band and then falls in again, this is a short signal;
B37: 44979 | C37: 70.27 | D37: =AVERAGE(C17:C37) -> 71.019524 | E37: =STDEV(C17:C37) -> 1.7949999 | F37: =D37+$F$1*E37 -> 74.250524 | G37: =D37-$G$1*E37 -> 67.788524 | I37: =(C37-G37)/(F37-G37) -> 0.38401055 | J37: =(F37-G37)/D37 -> 0.090989061 | L37: • when the price line exits the lower limit of the band and then re-enters in it again, this is a long signal
B38: 44980 | C38: 71.21 | D38: =AVERAGE(C18:C38) -> 71.186667 | E38: =STDEV(C18:C38) -> 1.6258977 | F38: =D38+$F$1*E38 -> 74.113283 | G38: =D38-$G$1*E38 -> 68.260051 | I38: =(C38-G38)/(F38-G38) -> 0.5039864 | J38: =(F38-G38)/D38 -> 0.082223708
B39: 44981 | C39: 70.87 | D39: =AVERAGE(C19:C39) -> 71.342381 | E39: =STDEV(C19:C39) -> 1.4070853 | F39: =D39+$F$1*E39 -> 73.875134 | G39: =D39-$G$1*E39 -> 68.809627 | I39: =(C39-G39)/(F39-G39) -> 0.40674557 | J39: =(F39-G39)/D39 -> 0.071002776
B40: 44984 | C40: 70.42 | D40: =AVERAGE(C20:C40) -> 71.341905 | E40: =STDEV(C20:C40) -> 1.4074112 | F40: =D40+$F$1*E40 -> 73.875245 | G40: =D40-$G$1*E40 -> 68.808565 | I40: =(C40-G40)/(F40-G40) -> 0.3180456 | J40: =(F40-G40)/D40 -> 0.071019693
B41: 44985 | C41: 70.9 | D41: =AVERAGE(C21:C41) -> 71.345714 | E41: =STDEV(C21:C41) -> 1.4060355 | F41: =D41+$F$1*E41 -> 73.876578 | G41: =D41-$G$1*E41 -> 68.81485 | I41: =(C41-G41)/(F41-G41) -> 0.41194424 | J41: =(F41-G41)/D41 -> 0.070946485
B42: 44986 | C42: 71.94 | D42: =AVERAGE(C22:C42) -> 71.473333 | E42: =STDEV(C22:C42) -> 1.3266436 | F42: =D42+$F$1*E42 -> 73.861292 | G42: =D42-$G$1*E42 -> 69.085375 | I42: =(C42-G42)/(F42-G42) -> 0.59771247 | J42: =(F42-G42)/D42 -> 0.066820965
B43: 44987 | C43: 72.38 | D43: =AVERAGE(C23:C43) -> 71.549524 | E43: =STDEV(C23:C43) -> 1.3307722 | F43: =D43+$F$1*E43 -> 73.944914 | G43: =D43-$G$1*E43 -> 69.154134 | I43: =(C43-G43)/(F43-G43) -> 0.67334884 | J43: =(F43-G43)/D43 -> 0.06695754
B44: 44988 | C44: 73.11 | D44: =AVERAGE(C24:C44) -> 71.577619 | E44: =STDEV(C24:C44) -> 1.3582301 | F44: =D44+$F$1*E44 -> 74.022433 | G44: =D44-$G$1*E44 -> 69.132805 | I44: =(C44-G44)/(F44-G44) -> 0.81339415 | J44: =(F44-G44)/D44 -> 0.068312253
B45: 44991 | C45: 72.54 | D45: =AVERAGE(C25:C45) -> 71.59619 | E45: =STDEV(C25:C45) -> 1.3690708 | F45: =D45+$F$1*E45 -> 74.060518 | G45: =D45-$G$1*E45 -> 69.131863 | I45: =(C45-G45)/(F45-G45) -> 0.69149435 | J45: =(F45-G45)/D45 -> 0.068839623
B46: 44992 | C46: 71.2 | D46: =AVERAGE(C26:C46) -> 71.491429 | E46: =STDEV(C26:C46) -> 1.306902 | F46: =D46+$F$1*E46 -> 73.843852 | G46: =D46-$G$1*E46 -> 69.139005 | I46: =(C46-G46)/(F46-G46) -> 0.4380578 | J46: =(F46-G46)/D46 -> 0.065809948
B47: 44993 | C47: 71.23 | D47: =AVERAGE(C27:C47) -> 71.448095 | E47: =STDEV(C27:C47) -> 1.2993869 | F47: =D47+$F$1*E47 -> 73.786992 | G47: =D47-$G$1*E47 -> 69.109199 | I47: =(C47-G47)/(F47-G47) -> 0.45337646 | J47: =(F47-G47)/D47 -> 0.065471202
B48: 44994 | C48: 67.37 | D48: =AVERAGE(C28:C48) -> 71.163333 | E48: =STDEV(C28:C48) -> 1.5013139 | F48: =D48+$F$1*E48 -> 73.865698 | G48: =D48-$G$1*E48 -> 68.460968 | I48: =(C48-G48)/(F48-G48) -> -0.20185437 | J48: =(F48-G48)/D48 -> 0.07594824
B49: 44995 | C49: 60.29 | D49: =AVERAGE(C29:C49) -> 70.515714 | E49: =STDEV(C29:C49) -> 2.7116961 | F49: =D49+$F$1*E49 -> 75.396767 | G49: =D49-$G$1*E49 -> 65.634661 | I49: =(C49-G49)/(F49-G49) -> -0.54749061 | J49: =(F49-G49)/D49 -> 0.13843873
... B504: 45657 | C504: 165.16 | D504: =AVERAGE(C484:C504) -> 173.22143 | E504: =STDEV(C484:C504) -> 3.8294977 | F504: =D504+$F$1*E504 -> 180.11452 | G504: =D504-$G$1*E504 -> 166.32833 | I504: =(C504-G504)/(F504-G504) -> -0.084746584 | J504: =(F504-G504)/D504 -> 0.079587104

Sheet Momentum + ROC
B2: Dates | C2: Prices | D2: Momentum | E2: Momentum Norm | G2: ROC | H2: ROC Norm
B3: 44929 | C3: 62.81
B4: 44930 | C4: 64.36 | AN4: ROC measures percentage change, while Momentum measures absolute change
B5: 44931 | C5: 62.95
B6: 44932 | C6: 64.33
B7: 44935 | C7: 65.32
B8: 44936 | C8: 66.52
B9: 44937 | C9: 67.68
B10: 44938 | C10: 68.44
B11: 44939 | C11: 69.71
B12: 44943 | C12: 69.09
B13: 44944 | C13: 68.03 | D13: =100*C13/C3 -> 108.31078 | G13: =((C13-C3)/C3)*100 -> 8.3107785
B14: 44945 | C14: 65.78 | D14: =100*C14/C4 -> 102.20634 | G14: =((C14-C4)/C4)*100 -> 2.2063393
B15: 44946 | C15: 67.07 | D15: =100*C15/C5 -> 106.54488 | G15: =((C15-C5)/C5)*100 -> 6.5448769
B16: 44949 | C16: 68.84 | D16: =100*C16/C6 -> 107.01073 | G16: =((C16-C6)/C6)*100 -> 7.0107259
B17: 44950 | C17: 67.7 | D17: =100*C17/C7 -> 103.6436 | G17: =((C17-C7)/C7)*100 -> 3.6436007
B18: 44951 | C18: 67.6 | D18: =100*C18/C8 -> 101.62357 | G18: =((C18-C8)/C8)*100 -> 1.6235719
B19: 44952 | C19: 70.43 | D19: =100*C19/C9 -> 104.06324 | G19: =((C19-C9)/C9)*100 -> 4.0632388
B20: 44953 | C20: 70.82 | D20: =100*C20/C10 -> 103.4775 | G20: =((C20-C10)/C10)*100 -> 3.4774985
B21: 44956 | C21: 69.26 | D21: =100*C21/C11 -> 99.354469 | G21: =((C21-C11)/C11)*100 -> -0.64553149
B22: 44957 | C22: 70.78 | D22: =100*C22/C12 -> 102.44608 | G22: =((C22-C12)/C12)*100 -> 2.4460848
B23: 44958 | C23: 72.52 | D23: =100*C23/C13 -> 106.60003 | G23: =((C23-C13)/C13)*100 -> 6.6000294
B24: 44959 | C24: 72.15 | D24: =100*C24/C14 -> 109.68379 | G24: =((C24-C14)/C14)*100 -> 9.6837945
... B41: 44985 | C41: 70.9 | D41: =100*C41/C31 -> 99.760799 | G41: =((C41-C31)/C31)*100 -> -0.23920079
B42: 44986 | C42: 71.94 | D42: =100*C42/C32 -> 100.39073 | E42: =(D42-AVERAGE(D13:D41))/_xlfn.STDEV.S(D13:D41) -> -0.52511275 | G42: =((C42-C32)/C32)*100 -> 0.39073402 | H42: =(G42-AVERAGE(G13:G41))/_xlfn.STDEV.S(G13:G41) -> -0.52511275
B43: 44987 | C43: 72.38 | D43: =100*C43/C33 -> 99.930968 | E43: =(D43-AVERAGE(D14:D42))/_xlfn.STDEV.S(D14:D42) -> -0.58640785 | G43: =((C43-C33)/C33)*100 -> -0.069032169 | H43: =(G43-AVERAGE(G14:G42))/_xlfn.STDEV.S(G14:G42) -> -0.58640785
B44: 44988 | C44: 73.11 | D44: =100*C44/C34 -> 101.4149 | E44: =(D44-AVERAGE(D15:D43))/_xlfn.STDEV.S(D15:D43) -> -0.2063687 | G44: =((C44-C34)/C34)*100 -> 1.414898 | H44: =(G44-AVERAGE(G15:G43))/_xlfn.STDEV.S(G15:G43) -> -0.2063687
B45: 44991 | C45: 72.54 | D45: =100*C45/C35 -> 101.53975 | E45: =(D45-AVERAGE(D16:D44))/_xlfn.STDEV.S(D16:D44) -> -0.13626829 | G45: =((C45-C35)/C35)*100 -> 1.5397536 | H45: =(G45-AVERAGE(G16:G44))/_xlfn.STDEV.S(G16:G44) -> -0.13626829
B46: 44992 | C46: 71.2 | D46: =100*C46/C36 -> 102.66763 | E46: =(D46-AVERAGE(D17:D45))/_xlfn.STDEV.S(D17:D45) -> 0.19255514 | G46: =((C46-C36)/C36)*100 -> 2.667628 | H46: =(G46-AVERAGE(G17:G45))/_xlfn.STDEV.S(G17:G45) -> 0.19255514
B47: 44993 | C47: 71.23 | D47: =100*C47/C37 -> 101.36616 | E47: =(D47-AVERAGE(D18:D46))/_xlfn.STDEV.S(D18:D46) -> -0.12813604 | G47: =((C47-C37)/C37)*100 -> 1.3661591 | H47: =(G47-AVERAGE(G18:G46))/_xlfn.STDEV.S(G18:G46) -> -0.12813604
B48: 44994 | C48: 67.37 | D48: =100*C48/C38 -> 94.607499 | E48: =(D48-AVERAGE(D19:D47))/_xlfn.STDEV.S(D19:D47) -> -1.8379786 | G48: =((C48-C38)/C38)*100 -> -5.3925011 | H48: =(G48-AVERAGE(G19:G47))/_xlfn.STDEV.S(G19:G47) -> -1.8379786
B49: 44995 | C49: 60.29 | D49: =100*C49/C39 -> 85.071257 | E49: =(D49-AVERAGE(D20:D48))/_xlfn.STDEV.S(D20:D48) -> -3.9725205 | G49: =((C49-C39)/C39)*100 -> -14.928743 | H49: =(G49-AVERAGE(G20:G48))/_xlfn.STDEV.S(G20:G48) -> -3.9725205
B50: 44998 | C50: 58.47 | D50: =100*C50/C40 -> 83.030389 | E50: =(D50-AVERAGE(D21:D49))/_xlfn.STDEV.S(D21:D49) -> -3.4841662 | G50: =((C50-C40)/C40)*100 -> -16.969611 | H50: =(G50-AVERAGE(G21:G49))/_xlfn.STDEV.S(G21:G49) -> -3.4841662
B51: 44999 | C51: 59.76 | D51: =100*C51/C41 -> 84.287729 | E51: =(D51-AVERAGE(D22:D50))/_xlfn.STDEV.S(D22:D50) -> -2.6280673 | G51: =((C51-C41)/C41)*100 -> -15.712271 | H51: =(G51-AVERAGE(G22:G50))/_xlfn.STDEV.S(G22:G50) -> -2.6280673
B52: 45000 | C52: 57.61 | D52: =100*C52/C42 -> 80.080623 | E52: =(D52-AVERAGE(D23:D51))/_xlfn.STDEV.S(D23:D51) -> -2.8964871 | G52: =((C52-C42)/C42)*100 -> -19.919377 | H52: =(G52-AVERAGE(G23:G51))/_xlfn.STDEV.S(G23:G51) -> -2.8964871
B53: 45001 | C53: 58.75 | D53: =100*C53/C43 -> 81.168831 | E53: =(D53-AVERAGE(D24:D52))/_xlfn.STDEV.S(D24:D52) -> -2.332116 | G53: =((C53-C43)/C43)*100 -> -18.831169 | H53: =(G53-AVERAGE(G24:G52))/_xlfn.STDEV.S(G24:G52) -> -2.332116
... B504: 45657 | C504: 165.16 | D504: =100*C504/C494 -> 92.708392 | E504: =(D504-AVERAGE(D475:D503))/_xlfn.STDEV.S(D475:D503) -> -1.9424231 | G504: =((C504-C494)/C494)*100 -> -7.2916082 | H504: =(G504-AVERAGE(G475:G503))/_xlfn.STDEV.S(G475:G503) -> -1.9424231

Sheet RSI
M1: =2/(15+1) -> 0.125
B2: Dates | C2: Prices | E2: Ln Var % | F2: Sum Rises | G2: Abs(Sum Drops) | H2: p = (rises/drops) | I2: RSI | J2: B | K2: S | M2: RSI 15d EMA | N2: RSI 10d st dev | O2: Dynamic B | P2: Dynamic S | AG2: Trading | AH2: Status | AI2: Buy/Sell | AJ2: Price | AK2: Perf Trade | AL2: Perf Cum | AN2: Stats | AQ2: Buy | AR2: Sell
B3: 44929 | C3: 62.81 | AN3: Tot Perf | AO3: =SUM(AK3:AK2518) -> 0.31958885
B4: 44930 | C4: 64.36 | E4: =LN(C4/C3) -> 0.024378026 | AN4: Max | AO4: =MAX(AK3:AK2518) -> 0.20089593
B5: 44931 | C5: 62.95 | E5: =LN(C5/C4) -> -0.022151562 | AN5: Min | AO5: =MIN(AK3:AK2518) -> -0.18163558
B6: 44932 | C6: 64.33 | E6: =LN(C6/C5) -> 0.021685325 | AN6: #Trade | AO6: =COUNTIF(AI3:AI2518,"=30")+COUNTIF(AI3:AI2518,"=70") -> 9
B7: 44935 | C7: 65.32 | E7: =LN(C7/C6) -> 0.015272183 | AN7: #Pos | AO7: =COUNTIFS(AK3:AK2518,">0") -> 6
B8: 44936 | C8: 66.52 | E8: =LN(C8/C7) -> 0.018204386 | AN8: #Neg | AO8: =COUNTIFS(AK3:AK2518,"<0") -> 2
B9: 44937 | C9: 67.68 | E9: =LN(C9/C8) -> 0.017288061
B10: 44938 | C10: 68.44 | E10: =LN(C10/C9) -> 0.011166734
B11: 44939 | C11: 69.71 | E11: =LN(C11/C10) -> 0.01838633
B12: 44943 | C12: 69.09 | E12: =LN(C12/C11) -> -0.008933777
B13: 44944 | C13: 68.03 | E13: =LN(C13/C12) -> -0.015461218
B14: 44945 | C14: 65.78 | E14: =LN(C14/C13) -> -0.033632944
B15: 44946 | C15: 67.07 | E15: =LN(C15/C14) -> 0.019421009
B16: 44949 | C16: 68.84 | E16: =LN(C16/C15) -> 0.026048121
B17: 44950 | C17: 67.7 | E17: =LN(C17/C16) -> -0.016698791 | F17: =SUMIF(E4:E17,">0",E4:E17) -> 0.17185018 | G17: =ABS(SUMIF(E4:E17,"<0",E4:E17)) -> 0.096878292 | H17: =F17/G17 -> 1.773877 | I17: =100-100/(1+H17) -> 63.949375 | J17: 30 | K17: 70 | AG17: =IF(I17<J17,"BUY",IF(I17<K17,"","SELL")) | AH17: =IF(AG17="",AH16,IF(AG17="BUY",1,-1)) -> 0 | AI17: =IF(AH17=AH16,-10,IF(AH17=-1,70,30)) -> -10 | AJ17: =IF(OR(AH17=0,AH17=AH16),AJ16,C17) -> 0 | AQ17: =IF(AH17=AH16,-10,IF(AH17=1,C17,-10)) -> -10 | AR17: =IF(AH17=AH16,-5,IF(AH17=-1,C17,-5)) -> -5
B18: 44951 | C18: 67.6 | E18: =LN(C18/C17) -> -0.0014781969 | F18: =SUMIF(E5:E18,">0",E5:E18) -> 0.14747215 | G18: =ABS(SUMIF(E5:E18,"<0",E5:E18)) -> 0.098356489 | H18: =F18/G18 -> 1.4993637 | I18: =100-100/(1+H18) -> 59.989817 | J18: 30 | K18: 70 | AG18: =IF(I18<J18,"BUY",IF(I18<K18,"","SELL")) | AH18: =IF(AG18="",AH17,IF(AG18="BUY",1,-1)) -> 0 | AI18: =IF(AH18=AH17,-10,IF(AH18=-1,70,30)) -> -10 | AJ18: =IF(OR(AH18=0,AH18=AH17),AJ17,C18) -> 0 | AK18: =IF(AJ18=AJ17,0,AH17*(AJ18/AJ17-1)) -> 0 | AL18: =AK18+AL17 -> 0 | AQ18: =IF(AH18=AH17,-10,IF(AH18=1,C18,-10)) -> -10 | AR18: =IF(AH18=AH17,-5,IF(AH18=-1,C18,-5)) -> -5
B19: 44952 | C19: 70.43 | E19: =LN(C19/C18) -> 0.041011326 | F19: =SUMIF(E6:E19,">0",E6:E19) -> 0.18848348 | G19: =ABS(SUMIF(E6:E19,"<0",E6:E19)) -> 0.076204927 | H19: =F19/G19 -> 2.4733765 | I19: =100-100/(1+H19) -> 71.209571 | J19: 30 | K19: 70 | AG19: =IF(I19<J19,"BUY",IF(I19<K19,"","SELL")) -> SELL | AH19: =IF(AG19="",AH18,IF(AG19="BUY",1,-1)) -> -1 | AI19: =IF(AH19=AH18,-10,IF(AH19=-1,70,30)) -> 70 | AJ19: =IF(OR(AH19=0,AH19=AH18),AJ18,C19) -> 70.43 | AK19: 0 | AL19: =AK19+AL18 -> 0 | AQ19: =IF(AH19=AH18,-10,IF(AH19=1,C19,-10)) -> -10 | AR19: =IF(AH19=AH18,-5,IF(AH19=-1,C19,-5)) -> 70.43
B20: 44953 | C20: 70.82 | E20: =LN(C20/C19) -> 0.0055221379 | F20: =SUMIF(E7:E20,">0",E7:E20) -> 0.17232029 | G20: =ABS(SUMIF(E7:E20,"<0",E7:E20)) -> 0.076204927 | H20: =F20/G20 -> 2.2612749 | I20: =100-100/(1+H20) -> 69.337145 | J20: 30 | K20: 70 | AG20: =IF(I20<J20,"BUY",IF(I20<K20,"","SELL")) | AH20: =IF(AG20="",AH19,IF(AG20="BUY",1,-1)) -> -1 | AI20: =IF(AH20=AH19,-10,IF(AH20=-1,70,30)) -> -10 | AJ20: =IF(OR(AH20=0,AH20=AH19),AJ19,C20) -> 70.43 | AK20: =IF(AJ20=AJ19,0,AH19*(AJ20/AJ19-1)) -> 0 | AL20: =AK20+AL19 -> 0 | AQ20: =IF(AH20=AH19,-10,IF(AH20=1,C20,-10)) -> -10 | AR20: =IF(AH20=AH19,-5,IF(AH20=-1,C20,-5)) -> -5
B21: 44956 | C21: 69.26 | E21: =LN(C21/C20) -> -0.022273908 | F21: =SUMIF(E8:E21,">0",E8:E21) -> 0.15704811 | G21: =ABS(SUMIF(E8:E21,"<0",E8:E21)) -> 0.098478835 | H21: =F21/G21 -> 1.5947397 | I21: =100-100/(1+H21) -> 61.460488 | J21: 30 | K21: 70 | AG21: =IF(I21<J21,"BUY",IF(I21<K21,"","SELL")) | AH21: =IF(AG21="",AH20,IF(AG21="BUY",1,-1)) -> -1 | AI21: =IF(AH21=AH20,-10,IF(AH21=-1,70,30)) -> -10 | AJ21: =IF(OR(AH21=0,AH21=AH20),AJ20,C21) -> 70.43 | AK21: =IF(AJ21=AJ20,0,AH20*(AJ21/AJ20-1)) -> 0 | AL21: =AK21+AL20 -> 0 | AQ21: =IF(AH21=AH20,-10,IF(AH21=1,C21,-10)) -> -10 | AR21: =IF(AH21=AH20,-5,IF(AH21=-1,C21,-5)) -> -5
B22: 44957 | C22: 70.78 | E22: =LN(C22/C21) -> 0.021708936 | F22: =SUMIF(E9:E22,">0",E9:E22) -> 0.16055266 | G22: =ABS(SUMIF(E9:E22,"<0",E9:E22)) -> 0.098478835 | H22: =F22/G22 -> 1.6303265 | I22: =100-100/(1+H22) -> 61.981906 | J22: 30 | K22: 70 | AG22: =IF(I22<J22,"BUY",IF(I22<K22,"","SELL")) | AH22: =IF(AG22="",AH21,IF(AG22="BUY",1,-1)) -> -1 | AI22: =IF(AH22=AH21,-10,IF(AH22=-1,70,30)) -> -10 | AJ22: =IF(OR(AH22=0,AH22=AH21),AJ21,C22) -> 70.43 | AK22: =IF(AJ22=AJ21,0,AH21*(AJ22/AJ21-1)) -> 0 | AL22: =AK22+AL21 -> 0 | AQ22: =IF(AH22=AH21,-10,IF(AH22=1,C22,-10)) -> -10 | AR22: =IF(AH22=AH21,-5,IF(AH22=-1,C22,-5)) -> -5
B23: 44958 | C23: 72.52 | E23: =LN(C23/C22) -> 0.024285911 | F23: =SUMIF(E10:E23,">0",E10:E23) -> 0.16755051 | G23: =ABS(SUMIF(E10:E23,"<0",E10:E23)) -> 0.098478835 | H23: =F23/G23 -> 1.7013859 | I23: =100-100/(1+H23) -> 62.981965 | J23: 30 | K23: 70 | AG23: =IF(I23<J23,"BUY",IF(I23<K23,"","SELL")) | AH23: =IF(AG23="",AH22,IF(AG23="BUY",1,-1)) -> -1 | AI23: =IF(AH23=AH22,-10,IF(AH23=-1,70,30)) -> -10 | AJ23: =IF(OR(AH23=0,AH23=AH22),AJ22,C23) -> 70.43 | AK23: =IF(AJ23=AJ22,0,AH22*(AJ23/AJ22-1)) -> 0 | AL23: =AK23+AL22 -> 0 | AQ23: =IF(AH23=AH22,-10,IF(AH23=1,C23,-10)) -> -10 | AR23: =IF(AH23=AH22,-5,IF(AH23=-1,C23,-5)) -> -5
B24: 44959 | C24: 72.15 | E24: =LN(C24/C23) -> -0.0051151007 | F24: =SUMIF(E11:E24,">0",E11:E24) -> 0.15638377 | G24: =ABS(SUMIF(E11:E24,"<0",E11:E24)) -> 0.10359394 | H24: =F24/G24 -> 1.5095842 | I24: =100-100/(1+H24) -> 60.152762 | J24: 30 | K24: 70 | AG24: =IF(I24<J24,"BUY",IF(I24<K24,"","SELL")) | AH24: =IF(AG24="",AH23,IF(AG24="BUY",1,-1)) -> -1 | AI24: =IF(AH24=AH23,-10,IF(AH24=-1,70,30)) -> -10 | AJ24: =IF(OR(AH24=0,AH24=AH23),AJ23,C24) -> 70.43 | AK24: =IF(AJ24=AJ23,0,AH23*(AJ24/AJ23-1)) -> 0 | AL24: =AK24+AL23 -> 0 | AQ24: =IF(AH24=AH23,-10,IF(AH24=1,C24,-10)) -> -10 | AR24: =IF(AH24=AH23,-5,IF(AH24=-1,C24,-5)) -> -5
B25: 44960 | C25: 73.4 | E25: =LN(C25/C24) -> 0.01717665 | F25: =SUMIF(E12:E25,">0",E12:E25) -> 0.15517409 | G25: =ABS(SUMIF(E12:E25,"<0",E12:E25)) -> 0.10359394 | H25: =F25/G25 -> 1.4979071 | I25: =100-100/(1+H25) -> 59.966486 | J25: 30 | K25: 70 | AG25: =IF(I25<J25,"BUY",IF(I25<K25,"","SELL")) | AH25: =IF(AG25="",AH24,IF(AG25="BUY",1,-1)) -> -1 | AI25: =IF(AH25=AH24,-10,IF(AH25=-1,70,30)) -> -10 | AJ25: =IF(OR(AH25=0,AH25=AH24),AJ24,C25) -> 70.43 | AK25: =IF(AJ25=AJ24,0,AH24*(AJ25/AJ24-1)) -> 0 | AL25: =AK25+AL24 -> 0 | AQ25: =IF(AH25=AH24,-10,IF(AH25=1,C25,-10)) -> -10 | AR25: =IF(AH25=AH24,-5,IF(AH25=-1,C25,-5)) -> -5
B26: 44963 | C26: 72.14 | E26: =LN(C26/C25) -> -0.01731526 | F26: =SUMIF(E13:E26,">0",E13:E26) -> 0.15517409 | G26: =ABS(SUMIF(E13:E26,"<0",E13:E26)) -> 0.11197542 | H26: =F26/G26 -> 1.3857871 | I26: =100-100/(1+H26) -> 58.085112 | J26: 30 | K26: 70 | R26: When RSI > 70, it is said that the security is overbought and it is expected to decline; | AG26: =IF(I26<J26,"BUY",IF(I26<K26,"","SELL")) | AH26: =IF(AG26="",AH25,IF(AG26="BUY",1,-1)) -> -1 | AI26: =IF(AH26=AH25,-10,IF(AH26=-1,70,30)) -> -10 | AJ26: =IF(OR(AH26=0,AH26=AH25),AJ25,C26) -> 70.43 | AK26: =IF(AJ26=AJ25,0,AH25*(AJ26/AJ25-1)) -> 0 | AL26: =AK26+AL25 -> 0 | AQ26: =IF(AH26=AH25,-10,IF(AH26=1,C26,-10)) -> -10 | AR26: =IF(AH26=AH25,-5,IF(AH26=-1,C26,-5)) -> -5
B27: 44964 | C27: 73.35 | E27: =LN(C27/C26) -> 0.016633829 | F27: =SUMIF(E14:E27,">0",E14:E27) -> 0.17180792 | G27: =ABS(SUMIF(E14:E27,"<0",E14:E27)) -> 0.0965142 | H27: =F27/G27 -> 1.780131 | I27: =100-100/(1+H27) -> 64.030472 | J27: 30 | K27: 70 | N27: =STDEV(I17:I27) -> 4.042907 | R27: when RSI < 30 it is said that the security is oversold and it is expected to rise. | AG27: =IF(I27<J27,"BUY",IF(I27<K27,"","SELL")) | AH27: =IF(AG27="",AH26,IF(AG27="BUY",1,-1)) -> -1 | AI27: =IF(AH27=AH26,-10,IF(AH27=-1,70,30)) -> -10 | AJ27: =IF(OR(AH27=0,AH27=AH26),AJ26,C27) -> 70.43 | AK27: =IF(AJ27=AJ26,0,AH26*(AJ27/AJ26-1)) -> 0 | AL27: =AK27+AL26 -> 0 | AQ27: =IF(AH27=AH26,-10,IF(AH27=1,C27,-10)) -> -10 | AR27: =IF(AH27=AH26,-5,IF(AH27=-1,C27,-5)) -> -5
B28: 44965 | C28: 73.89 | E28: =LN(C28/C27) -> 0.0073349962 | F28: =SUMIF(E15:E28,">0",E15:E28) -> 0.17914292 | G28: =ABS(SUMIF(E15:E28,"<0",E15:E28)) -> 0.062881257 | H28: =F28/G28 -> 2.848908 | I28: =100-100/(1+H28) -> 74.018605 | J28: 30 | K28: 70 | N28: =STDEV(I18:I28) -> 5.23905 | AG28: =IF(I28<J28,"BUY",IF(I28<K28,"","SELL")) -> SELL | AH28: =IF(AG28="",AH27,IF(AG28="BUY",1,-1)) -> -1 | AI28: =IF(AH28=AH27,-10,IF(AH28=-1,70,30)) -> -10 | AJ28: =IF(OR(AH28=0,AH28=AH27),AJ27,C28) -> 70.43 | AK28: =IF(AJ28=AJ27,0,AH27*(AJ28/AJ27-1)) -> 0 | AL28: =AK28+AL27 -> 0 | AQ28: =IF(AH28=AH27,-10,IF(AH28=1,C28,-10)) -> -10 | AR28: =IF(AH28=AH27,-5,IF(AH28=-1,C28,-5)) -> -5
B29: 44966 | C29: 68.4 | E29: =LN(C29/C28) -> -0.077204676 | F29: =SUMIF(E16:E29,">0",E16:E29) -> 0.15972191 | G29: =ABS(SUMIF(E16:E29,"<0",E16:E29)) -> 0.14008593 | H29: =F29/G29 -> 1.1401709 | I29: =100-100/(1+H29) -> 53.27476 | J29: 30 | K29: 70 | N29: =STDEV(I19:I29) -> 6.0693257 | R29: The RSI is often considered a divergence indicator. | AG29: =IF(I29<J29,"BUY",IF(I29<K29,"","SELL")) | AH29: =IF(AG29="",AH28,IF(AG29="BUY",1,-1)) -> -1 | AI29: =IF(AH29=AH28,-10,IF(AH29=-1,70,30)) -> -10 | AJ29: =IF(OR(AH29=0,AH29=AH28),AJ28,C29) -> 70.43 | AK29: =IF(AJ29=AJ28,0,AH28*(AJ29/AJ28-1)) -> 0 | AL29: =AK29+AL28 -> 0 | AQ29: =IF(AH29=AH28,-10,IF(AH29=1,C29,-10)) -> -10 | AR29: =IF(AH29=AH28,-5,IF(AH29=-1,C29,-5)) -> -5
B30: 44967 | C30: 70.66 | E30: =LN(C30/C29) -> 0.032506817 | F30: =SUMIF(E17:E30,">0",E17:E30) -> 0.1661806 | G30: =ABS(SUMIF(E17:E30,"<0",E17:E30)) -> 0.14008593 | H30: =F30/G30 -> 1.1862762 | I30: =100-100/(1+H30) -> 54.260124 | J30: 30 | K30: 70 | N30: =STDEV(I20:I30) -> 6.0168312 | R30: Remember that a bullish divergence is present when the price makes a new low but the oscillator does not. | AG30: =IF(I30<J30,"BUY",IF(I30<K30,"","SELL")) | AH30: =IF(AG30="",AH29,IF(AG30="BUY",1,-1)) -> -1 | AI30: =IF(AH30=AH29,-10,IF(AH30=-1,70,30)) -> -10 | AJ30: =IF(OR(AH30=0,AH30=AH29),AJ29,C30) -> 70.43 | AK30: =IF(AJ30=AJ29,0,AH29*(AJ30/AJ29-1)) -> 0 | AL30: =AK30+AL29 -> 0 | AQ30: =IF(AH30=AH29,-10,IF(AH30=1,C30,-10)) -> -10 | AR30: =IF(AH30=AH29,-5,IF(AH30=-1,C30,-5)) -> -5
B31: 44970 | C31: 71.07 | E31: =LN(C31/C30) -> 0.0057856649 | F31: =SUMIF(E18:E31,">0",E18:E31) -> 0.17196627 | G31: =ABS(SUMIF(E18:E31,"<0",E18:E31)) -> 0.12338714 | H31: =F31/G31 -> 1.393713 | I31: =100-100/(1+H31) -> 58.223898 | J31: 30 | K31: 70 | N31: =STDEV(I21:I31) -> 5.5341609 | R31: A bearish divergence is present, instead, when the price makes a new high but the oscillator does not. | AG31: =IF(I31<J31,"BUY",IF(I31<K31,"","SELL")) | AH31: =IF(AG31="",AH30,IF(AG31="BUY",1,-1)) -> -1 | AI31: =IF(AH31=AH30,-10,IF(AH31=-1,70,30)) -> -10 | AJ31: =IF(OR(AH31=0,AH31=AH30),AJ30,C31) -> 70.43 | AK31: =IF(AJ31=AJ30,0,AH30*(AJ31/AJ30-1)) -> 0 | AL31: =AK31+AL30 -> 0 | AQ31: =IF(AH31=AH30,-10,IF(AH31=1,C31,-10)) -> -10 | AR31: =IF(AH31=AH30,-5,IF(AH31=-1,C31,-5)) -> -5
B32: 44971 | C32: 71.66 | E32: =LN(C32/C31) -> 0.008267405 | F32: =SUMIF(E19:E32,">0",E19:E32) -> 0.18023367 | G32: =ABS(SUMIF(E19:E32,"<0",E19:E32)) -> 0.12190894 | H32: =F32/G32 -> 1.4784286 | I32: =100-100/(1+H32) -> 59.651854 | J32: 30 | K32: 70 | M32: =AVERAGE(I17:I32) -> 62.035896 | N32: =STDEV(I22:I32) -> 5.5383615 | O32: =M32+N32 -> 67.574258 | P32: =M32-N32 -> 56.497535 | AG32: =IF(I32<J32,"BUY",IF(I32<K32,"","SELL")) | AH32: =IF(AG32="",AH31,IF(AG32="BUY",1,-1)) -> -1 | AI32: =IF(AH32=AH31,-10,IF(AH32=-1,70,30)) -> -10 | AJ32: =IF(OR(AH32=0,AH32=AH31),AJ31,C32) -> 70.43 | AK32: =IF(AJ32=AJ31,0,AH31*(AJ32/AJ31-1)) -> 0 | AL32: =AK32+AL31 -> 0 | AQ32: =IF(AH32=AH31,-10,IF(AH32=1,C32,-10)) -> -10 | AR32: =IF(AH32=AH31,-5,IF(AH32=-1,C32,-5)) -> -5
B33: 44972 | C33: 72.43 | E33: =LN(C33/C32) -> 0.010687866 | F33: =SUMIF(E20:E33,">0",E20:E33) -> 0.14991021 | G33: =ABS(SUMIF(E20:E33,"<0",E20:E33)) -> 0.12190894 | H33: =F33/G33 -> 1.22969 | I33: =100-100/(1+H33) -> 55.150717 | J33: 30 | K33: 70 | M33: =(I33*$M$1)+(M32*(1-$M$1)) -> 61.175249 | N33: =STDEV(I23:I33) -> 5.7472769 | O33: =M33+N33 -> 66.922526 | P33: =M33-N33 -> 55.427972 | AG33: =IF(I33<J33,"BUY",IF(I33<K33,"","SELL")) | AH33: =IF(AG33="",AH32,IF(AG33="BUY",1,-1)) -> -1 | AI33: =IF(AH33=AH32,-10,IF(AH33=-1,70,30)) -> -10 | AJ33: =IF(OR(AH33=0,AH33=AH32),AJ32,C33) -> 70.43 | AK33: =IF(AJ33=AJ32,0,AH32*(AJ33/AJ32-1)) -> 0 | AL33: =AK33+AL32 -> 0 | AQ33: =IF(AH33=AH32,-10,IF(AH33=1,C33,-10)) -> -10 | AR33: =IF(AH33=AH32,-5,IF(AH33=-1,C33,-5)) -> -5
B34: 44973 | C34: 72.09 | E34: =LN(C34/C33) -> -0.0047052398 | F34: =SUMIF(E21:E34,">0",E21:E34) -> 0.14438808 | G34: =ABS(SUMIF(E21:E34,"<0",E21:E34)) -> 0.12661418 | H34: =F34/G34 -> 1.1403784 | I34: =100-100/(1+H34) -> 53.279288 | J34: 30 | K34: 70 | M34: =(I34*$M$1)+(M33*(1-$M$1)) -> 60.188254 | N34: =STDEV(I24:I34) -> 5.980559 | O34: =M34+N34 -> 66.168813 | P34: =M34-N34 -> 54.207695 | AG34: =IF(I34<J34,"BUY",IF(I34<K34,"","SELL")) | AH34: =IF(AG34="",AH33,IF(AG34="BUY",1,-1)) -> -1 | AI34: =IF(AH34=AH33,-10,IF(AH34=-1,70,30)) -> -10 | AJ34: =IF(OR(AH34=0,AH34=AH33),AJ33,C34) -> 70.43 | AK34: =IF(AJ34=AJ33,0,AH33*(AJ34/AJ33-1)) -> 0 | AL34: =AK34+AL33 -> 0 | AQ34: =IF(AH34=AH33,-10,IF(AH34=1,C34,-10)) -> -10 | AR34: =IF(AH34=AH33,-5,IF(AH34=-1,C34,-5)) -> -5
B35: 44974 | C35: 71.44 | E35: =LN(C35/C34) -> -0.0090574018 | F35: =SUMIF(E22:E35,">0",E22:E35) -> 0.14438808 | G35: =ABS(SUMIF(E22:E35,"<0",E22:E35)) -> 0.11339768 | H35: =F35/G35 -> 1.2732895 | I35: =100-100/(1+H35) -> 56.010882 | J35: 30 | K35: 70 | M35: =(I35*$M$1)+(M34*(1-$M$1)) -> 59.666082 | N35: =STDEV(I25:I35) -> 6.0377246 | O35: =M35+N35 -> 65.703807 | P35: =M35-N35 -> 53.628358 | AG35: =IF(I35<J35,"BUY",IF(I35<K35,"","SELL")) | AH35: =IF(AG35="",AH34,IF(AG35="BUY",1,-1)) -> -1 | AI35: =IF(AH35=AH34,-10,IF(AH35=-1,70,30)) -> -10 | AJ35: =IF(OR(AH35=0,AH35=AH34),AJ34,C35) -> 70.43 | AK35: =IF(AJ35=AJ34,0,AH34*(AJ35/AJ34-1)) -> 0 | AL35: =AK35+AL34 -> 0 | AQ35: =IF(AH35=AH34,-10,IF(AH35=1,C35,-10)) -> -10 | AR35: =IF(AH35=AH34,-5,IF(AH35=-1,C35,-5)) -> -5
B36: 44978 | C36: 69.35 | E36: =LN(C36/C35) -> -0.02969179 | F36: =SUMIF(E23:E36,">0",E23:E36) -> 0.12267914 | G36: =ABS(SUMIF(E23:E36,"<0",E23:E36)) -> 0.14308947 | H36: =F36/G36 -> 0.85735968 | I36: =100-100/(1+H36) -> 46.160132 | J36: 30 | K36: 70 | M36: =(I36*$M$1)+(M35*(1-$M$1)) -> 57.977839 | N36: =STDEV(I26:I36) -> 7.0957022 | O36: =M36+N36 -> 65.073541 | P36: =M36-N36 -> 50.882136 | AG36: =IF(I36<J36,"BUY",IF(I36<K36,"","SELL")) | AH36: =IF(AG36="",AH35,IF(AG36="BUY",1,-1)) -> -1 | AI36: =IF(AH36=AH35,-10,IF(AH36=-1,70,30)) -> -10 | AJ36: =IF(OR(AH36=0,AH36=AH35),AJ35,C36) -> 70.43 | AK36: =IF(AJ36=AJ35,0,AH35*(AJ36/AJ35-1)) -> 0 | AL36: =AK36+AL35 -> 0 | AQ36: =IF(AH36=AH35,-10,IF(AH36=1,C36,-10)) -> -10 | AR36: =IF(AH36=AH35,-5,IF(AH36=-1,C36,-5)) -> -5
B37: 44979 | C37: 70.27 | E37: =LN(C37/C36) -> 0.013178818 | F37: =SUMIF(E24:E37,">0",E24:E37) -> 0.11157205 | G37: =ABS(SUMIF(E24:E37,"<0",E24:E37)) -> 0.14308947 | H37: =F37/G37 -> 0.77973627 | I37: =100-100/(1+H37) -> 43.8119 | J37: 30 | K37: 70 | M37: =(I37*$M$1)+(M36*(1-$M$1)) -> 56.207096 | N37: =STDEV(I27:I37) -> 8.1918993 | O37: =M37+N37 -> 64.398995 | P37: =M37-N37 -> 48.015197 | AG37: =IF(I37<J37,"BUY",IF(I37<K37,"","SELL")) | AH37: =IF(AG37="",AH36,IF(AG37="BUY",1,-1)) -> -1 | AI37: =IF(AH37=AH36,-10,IF(AH37=-1,70,30)) -> -10 | AJ37: =IF(OR(AH37=0,AH37=AH36),AJ36,C37) -> 70.43 | AK37: =IF(AJ37=AJ36,0,AH36*(AJ37/AJ36-1)) -> 0 | AL37: =AK37+AL36 -> 0 | AQ37: =IF(AH37=AH36,-10,IF(AH37=1,C37,-10)) -> -10 | AR37: =IF(AH37=AH36,-5,IF(AH37=-1,C37,-5)) -> -5
B38: 44980 | C38: 71.21 | E38: =LN(C38/C37) -> 0.013288293 | F38: =SUMIF(E25:E38,">0",E25:E38) -> 0.12486034 | G38: =ABS(SUMIF(E25:E38,"<0",E25:E38)) -> 0.13797437 | H38: =F38/G38 -> 0.90495316 | I38: =100-100/(1+H38) -> 47.505271 | J38: 30 | K38: 70 | M38: =(I38*$M$1)+(M37*(1-$M$1)) -> 55.119368 | N38: =STDEV(I28:I38) -> 8.1212369 | O38: =M38+N38 -> 63.240605 | P38: =M38-N38 -> 46.998131 | AG38: =IF(I38<J38,"BUY",IF(I38<K38,"","SELL")) | AH38: =IF(AG38="",AH37,IF(AG38="BUY",1,-1)) -> -1 | AI38: =IF(AH38=AH37,-10,IF(AH38=-1,70,30)) -> -10 | AJ38: =IF(OR(AH38=0,AH38=AH37),AJ37,C38) -> 70.43 | AK38: =IF(AJ38=AJ37,0,AH37*(AJ38/AJ37-1)) -> 0 | AL38: =AK38+AL37 -> 0 | AQ38: =IF(AH38=AH37,-10,IF(AH38=1,C38,-10)) -> -10 | AR38: =IF(AH38=AH37,-5,IF(AH38=-1,C38,-5)) -> -5
B39: 44981 | C39: 70.87 | E39: =LN(C39/C38) -> -0.0047860452 | F39: =SUMIF(E26:E39,">0",E26:E39) -> 0.10768369 | G39: =ABS(SUMIF(E26:E39,"<0",E26:E39)) -> 0.14276041 | H39: =F39/G39 -> 0.75429657 | I39: =100-100/(1+H39) -> 42.997095 | J39: 30 | K39: 70 | M39: =(I39*$M$1)+(M38*(1-$M$1)) -> 53.604084 | N39: =STDEV(I29:I39) -> 5.7777234 | O39: =M39+N39 -> 59.381807 | P39: =M39-N39 -> 47.826361 | AG39: =IF(I39<J39,"BUY",IF(I39<K39,"","SELL")) | AH39: =IF(AG39="",AH38,IF(AG39="BUY",1,-1)) -> -1 | AI39: =IF(AH39=AH38,-10,IF(AH39=-1,70,30)) -> -10 | AJ39: =IF(OR(AH39=0,AH39=AH38),AJ38,C39) -> 70.43 | AK39: =IF(AJ39=AJ38,0,AH38*(AJ39/AJ38-1)) -> 0 | AL39: =AK39+AL38 -> 0 | AQ39: =IF(AH39=AH38,-10,IF(AH39=1,C39,-10)) -> -10 | AR39: =IF(AH39=AH38,-5,IF(AH39=-1,C39,-5)) -> -5
B40: 44984 | C40: 70.42 | E40: =LN(C40/C39) -> -0.0063698991 | F40: =SUMIF(E27:E40,">0",E27:E40) -> 0.10768369 | G40: =ABS(SUMIF(E27:E40,"<0",E27:E40)) -> 0.13181505 | H40: =F40/G40 -> 0.81693015 | I40: =100-100/(1+H40) -> 44.962111 | J40: 30 | K40: 70 | M40: =(I40*$M$1)+(M39*(1-$M$1)) -> 52.523837 | N40: =STDEV(I30:I40) -> 6.1066826 | O40: =M40+N40 -> 58.63052 | P40: =M40-N40 -> 46.417155 | AG40: =IF(I40<J40,"BUY",IF(I40<K40,"","SELL")) | AH40: =IF(AG40="",AH39,IF(AG40="BUY",1,-1)) -> -1 | AI40: =IF(AH40=AH39,-10,IF(AH40=-1,70,30)) -> -10 | AJ40: =IF(OR(AH40=0,AH40=AH39),AJ39,C40) -> 70.43 | AK40: =IF(AJ40=AJ39,0,AH39*(AJ40/AJ39-1)) -> 0 | AL40: =AK40+AL39 -> 0 | AQ40: =IF(AH40=AH39,-10,IF(AH40=1,C40,-10)) -> -10 | AR40: =IF(AH40=AH39,-5,IF(AH40=-1,C40,-5)) -> -5
B41: 44985 | C41: 70.9 | E41: =LN(C41/C40) -> 0.0067931198 | F41: =SUMIF(E28:E41,">0",E28:E41) -> 0.097842981 | G41: =ABS(SUMIF(E28:E41,"<0",E28:E41)) -> 0.13181505 | H41: =F41/G41 -> 0.74227472 | I41: =100-100/(1+H41) -> 42.60377 | J41: 30 | K41: 70 | M41: =(I41*$M$1)+(M40*(1-$M$1)) -> 51.283829 | N41: =STDEV(I31:I41) -> 6.5006122 | O41: =M41+N41 -> 57.784441 | P41: =M41-N41 -> 44.783217 | AG41: =IF(I41<J41,"BUY",IF(I41<K41,"","SELL")) | AH41: =IF(AG41="",AH40,IF(AG41="BUY",1,-1)) -> -1 | AI41: =IF(AH41=AH40,-10,IF(AH41=-1,70,30)) -> -10 | AJ41: =IF(OR(AH41=0,AH41=AH40),AJ40,C41) -> 70.43 | AK41: =IF(AJ41=AJ40,0,AH40*(AJ41/AJ40-1)) -> 0 | AL41: =AK41+AL40 -> 0 | AQ41: =IF(AH41=AH40,-10,IF(AH41=1,C41,-10)) -> -10 | AR41: =IF(AH41=AH40,-5,IF(AH41=-1,C41,-5)) -> -5
B42: 44986 | C42: 71.94 | E42: =LN(C42/C41) -> 0.014562005 | F42: =SUMIF(E29:E42,">0",E29:E42) -> 0.10506999 | G42: =ABS(SUMIF(E29:E42,"<0",E29:E42)) -> 0.13181505 | H42: =F42/G42 -> 0.7971016 | I42: =100-100/(1+H42) -> 44.354844 | J42: 30 | K42: 70 | M42: =(I42*$M$1)+(M41*(1-$M$1)) -> 50.417706 | N42: =STDEV(I32:I42) -> 6.0846403 | O42: =M42+N42 -> 56.502346 | P42: =M42-N42 -> 44.333065 | AG42: =IF(I42<J42,"BUY",IF(I42<K42,"","SELL")) | AH42: =IF(AG42="",AH41,IF(AG42="BUY",1,-1)) -> -1 | AI42: =IF(AH42=AH41,-10,IF(AH42=-1,70,30)) -> -10 | AJ42: =IF(OR(AH42=0,AH42=AH41),AJ41,C42) -> 70.43 | AK42: =IF(AJ42=AJ41,0,AH41*(AJ42/AJ41-1)) -> 0 | AL42: =AK42+AL41 -> 0 | AQ42: =IF(AH42=AH41,-10,IF(AH42=1,C42,-10)) -> -10 | AR42: =IF(AH42=AH41,-5,IF(AH42=-1,C42,-5)) -> -5
B43: 44987 | C43: 72.38 | E43: =LN(C43/C42) -> 0.0060975799 | F43: =SUMIF(E30:E43,">0",E30:E43) -> 0.11116757 | G43: =ABS(SUMIF(E30:E43,"<0",E30:E43)) -> 0.054610376 | H43: =F43/G43 -> 2.0356492 | I43: =100-100/(1+H43) -> 67.058118 | J43: 30 | K43: 70 | M43: =(I43*$M$1)+(M42*(1-$M$1)) -> 52.497757 | N43: =STDEV(I33:I43) -> 7.6240298 | O43: =M43+N43 -> 60.121787 | P43: =M43-N43 -> 44.873727 | AG43: =IF(I43<J43,"BUY",IF(I43<K43,"","SELL")) | AH43: =IF(AG43="",AH42,IF(AG43="BUY",1,-1)) -> -1 | AI43: =IF(AH43=AH42,-10,IF(AH43=-1,70,30)) -> -10 | AJ43: =IF(OR(AH43=0,AH43=AH42),AJ42,C43) -> 70.43 | AK43: =IF(AJ43=AJ42,0,AH42*(AJ43/AJ42-1)) -> 0 | AL43: =AK43+AL42 -> 0 | AQ43: =IF(AH43=AH42,-10,IF(AH43=1,C43,-10)) -> -10 | AR43: =IF(AH43=AH42,-5,IF(AH43=-1,C43,-5)) -> -5
B44: 44988 | C44: 73.11 | E44: =LN(C44/C43) -> 0.010035138 | F44: =SUMIF(E31:E44,">0",E31:E44) -> 0.08869589 | G44: =ABS(SUMIF(E31:E44,"<0",E31:E44)) -> 0.054610376 | H44: =F44/G44 -> 1.6241582 | I44: =100-100/(1+H44) -> 61.892542 | J44: 30 | K44: 70 | M44: =(I44*$M$1)+(M43*(1-$M$1)) -> 53.672105 | N44: =STDEV(I34:I44) -> 8.363692 | O44: =M44+N44 -> 62.035797 | P44: =M44-N44 -> 45.308413 | AG44: =IF(I44<J44,"BUY",IF(I44<K44,"","SELL")) | AH44: =IF(AG44="",AH43,IF(AG44="BUY",1,-1)) -> -1 | AI44: =IF(AH44=AH43,-10,IF(AH44=-1,70,30)) -> -10 | AJ44: =IF(OR(AH44=0,AH44=AH43),AJ43,C44) -> 70.43 | AK44: =IF(AJ44=AJ43,0,AH43*(AJ44/AJ43-1)) -> 0 | AL44: =AK44+AL43 -> 0 | AQ44: =IF(AH44=AH43,-10,IF(AH44=1,C44,-10)) -> -10 | AR44: =IF(AH44=AH43,-5,IF(AH44=-1,C44,-5)) -> -5
... B75: 45034 | C75: 65.34 | E75: =LN(C75/C74) -> 0.00137836 | F75: =SUMIF(E62:E75,">0",E62:E75) -> 0.14605458 | G75: =ABS(SUMIF(E62:E75,"<0",E62:E75)) -> 0.045681101 | H75: =F75/G75 -> 3.1972649 | I75: =100-100/(1+H75) -> 76.174961 | J75: 30 | K75: 70 | M75: =(I75*$M$1)+(M74*(1-$M$1)) -> 62.524025 | N75: =STDEV(I65:I75) -> 8.3422481 | O75: =M75+N75 -> 70.866273 | P75: =M75-N75 -> 54.181777 | AG75: =IF(I75<J75,"BUY",IF(I75<K75,"","SELL")) -> SELL | AH75: =IF(AG75="",AH74,IF(AG75="BUY",1,-1)) -> -1 | AI75: =IF(AH75=AH74,-10,IF(AH75=-1,70,30)) -> -10 | AJ75: =IF(OR(AH75=0,AH75=AH74),AJ74,C75) -> 64.8 | AK75: =IF(AJ75=AJ74,0,AH74*(AJ75/AJ74-1)) -> 0 | AL75: =AK75+AL74 -> 0.21877785 | AQ75: =IF(AH75=AH74,-10,IF(AH75=1,C75,-10)) -> -10 | AR75: =IF(AH75=AH74,-5,IF(AH75=-1,C75,-5)) -> -5
B76: 45035 | C76: 65.8 | E76: =LN(C76/C75) -> 0.0070154322 | F76: =SUMIF(E63:E76,">0",E63:E76) -> 0.12701644 | G76: =ABS(SUMIF(E63:E76,"<0",E63:E76)) -> 0.045681101 | H76: =F76/G76 -> 2.780503 | I76: =100-100/(1+H76) -> 73.548493 | J76: 30 | K76: 70 | M76: =(I76*$M$1)+(M75*(1-$M$1)) -> 63.902083 | N76: =STDEV(I66:I76) -> 7.7216143 | O76: =M76+N76 -> 71.623698 | P76: =M76-N76 -> 56.180469 | AG76: =IF(I76<J76,"BUY",IF(I76<K76,"","SELL")) -> SELL | AH76: =IF(AG76="",AH75,IF(AG76="BUY",1,-1)) -> -1 | AI76: =IF(AH76=AH75,-10,IF(AH76=-1,70,30)) -> -10 | AJ76: =IF(OR(AH76=0,AH76=AH75),AJ75,C76) -> 64.8 | AK76: =IF(AJ75=AJ74,0,AH74*(AJ75/AJ74-1)) -> 0 | AL76: =AK76+AL75 -> 0.21877785 | AQ76: =IF(AH76=AH75,-10,IF(AH76=1,C76,-10)) -> -10 | AR76: =IF(AH76=AH75,-5,IF(AH76=-1,C76,-5)) -> -5
B77: 45036 | C77: 64.29 | E77: =LN(C77/C76) -> -0.02321574 | F77: =SUMIF(E64:E77,">0",E64:E77) -> 0.1140771 | G77: =ABS(SUMIF(E64:E77,"<0",E64:E77)) -> 0.068896841 | H77: =F77/G77 -> 1.6557668 | I77: =100-100/(1+H77) -> 62.346092 | J77: 30 | K77: 70 | M77: =(I77*$M$1)+(M76*(1-$M$1)) -> 63.707584 | N77: =STDEV(I67:I77) -> 7.7685137 | O77: =M77+N77 -> 71.476098 | P77: =M77-N77 -> 55.939071 | AG77: =IF(I77<J77,"BUY",IF(I77<K77,"","SELL")) | AH77: =IF(AG77="",AH76,IF(AG77="BUY",1,-1)) -> -1 | AI77: =IF(AH77=AH76,-10,IF(AH77=-1,70,30)) -> -10 | AJ77: =IF(OR(AH77=0,AH77=AH76),AJ76,C77) -> 64.8 | AK77: =IF(AJ77=AJ76,0,AH76*(AJ77/AJ76-1)) -> 0 | AL77: =AK77+AL76 -> 0.21877785 | AQ77: =IF(AH77=AH76,-10,IF(AH77=1,C77,-10)) -> -10 | AR77: =IF(AH77=AH76,-5,IF(AH77=-1,C77,-5)) -> -5
B78: 45037 | C78: 63.54 | E78: =LN(C78/C77) -> -0.011734469 | F78: =SUMIF(E65:E78,">0",E65:E78) -> 0.08662975 | G78: =ABS(SUMIF(E65:E78,"<0",E65:E78)) -> 0.080631311 | H78: =F78/G78 -> 1.0743934 | I78: =100-100/(1+H78) -> 51.793137 | J78: 30 | K78: 70 | M78: =(I78*$M$1)+(M77*(1-$M$1)) -> 62.218278 | N78: =STDEV(I68:I78) -> 8.7567093 | O78: =M78+N78 -> 70.974988 | P78: =M78-N78 -> 53.461569 | AG78: =IF(I78<J78,"BUY",IF(I78<K78,"","SELL")) | AH78: =IF(AG78="",AH77,IF(AG78="BUY",1,-1)) -> -1 | AI78: =IF(AH78=AH77,-10,IF(AH78=-1,70,30)) -> -10 | AJ78: =IF(OR(AH78=0,AH78=AH77),AJ77,C78) -> 64.8 | AK78: =IF(AJ78=AJ77,0,AH77*(AJ78/AJ77-1)) -> 0 | AL78: =AK78+AL77 -> 0.21877785 | AQ78: =IF(AH78=AH77,-10,IF(AH78=1,C78,-10)) -> -10 | AR78: =IF(AH78=AH77,-5,IF(AH78=-1,C78,-5)) -> -5
B79: 45040 | C79: 63.3 | E79: =LN(C79/C78) -> -0.0037842997 | F79: =SUMIF(E66:E79,">0",E66:E79) -> 0.08662975 | G79: =ABS(SUMIF(E66:E79,"<0",E66:E79)) -> 0.072309696 | H79: =F79/G79 -> 1.1980378 | I79: =100-100/(1+H79) -> 54.504877 | J79: 30 | K79: 70 | M79: =(I79*$M$1)+(M78*(1-$M$1)) -> 61.254103 | N79: =STDEV(I69:I79) -> 9.6541969 | O79: =M79+N79 -> 70.9083 | P79: =M79-N79 -> 51.599906 | AG79: =IF(I79<J79,"BUY",IF(I79<K79,"","SELL")) | AH79: =IF(AG79="",AH78,IF(AG79="BUY",1,-1)) -> -1 | AI79: =IF(AH79=AH78,-10,IF(AH79=-1,70,30)) -> -10 | AJ79: =IF(OR(AH79=0,AH79=AH78),AJ78,C79) -> 64.8 | AK79: =IF(AJ79=AJ78,0,AH78*(AJ79/AJ78-1)) -> 0 | AL79: =AK79+AL78 -> 0.21877785 | AQ79: =IF(AH79=AH78,-10,IF(AH79=1,C79,-10)) -> -10 | AR79: =IF(AH79=AH78,-5,IF(AH79=-1,C79,-5)) -> -5
B80: 45041 | C80: 61.63 | E80: =LN(C80/C79) -> -0.026736564 | F80: =SUMIF(E67:E80,">0",E67:E80) -> 0.08662975 | G80: =ABS(SUMIF(E67:E80,"<0",E67:E80)) -> 0.094870889 | H80: =F80/G80 -> 0.91313311 | I80: =100-100/(1+H80) -> 47.729722 | J80: 30 | K80: 70 | M80: =(I80*$M$1)+(M79*(1-$M$1)) -> 59.563556 | N80: =STDEV(I70:I80) -> 11.329343 | O80: =M80+N80 -> 70.892898 | P80: =M80-N80 -> 48.234213 | AG80: =IF(I80<J80,"BUY",IF(I80<K80,"","SELL")) | AH80: =IF(AG80="",AH79,IF(AG80="BUY",1,-1)) -> -1 | AI80: =IF(AH80=AH79,-10,IF(AH80=-1,70,30)) -> -10 | AJ80: =IF(OR(AH80=0,AH80=AH79),AJ79,C80) -> 64.8 | AK80: =IF(AJ80=AJ79,0,AH79*(AJ80/AJ79-1)) -> 0 | AL80: =AK80+AL79 -> 0.21877785 | AQ80: =IF(AH80=AH79,-10,IF(AH80=1,C80,-10)) -> -10 | AR80: =IF(AH80=AH79,-5,IF(AH80=-1,C80,-5)) -> -5
B81: 45042 | C81: 61.38 | E81: =LN(C81/C80) -> -0.0040647158 | F81: =SUMIF(E68:E81,">0",E68:E81) -> 0.08662975 | G81: =ABS(SUMIF(E68:E81,"<0",E68:E81)) -> 0.086955536 | H81: =F81/G81 -> 0.99625342 | I81: =100-100/(1+H81) -> 49.90616 | J81: 30 | K81: 70 | M81: =(I81*$M$1)+(M80*(1-$M$1)) -> 58.356381 | N81: =STDEV(I71:I81) -> 12.158572 | O81: =M81+N81 -> 70.514953 | P81: =M81-N81 -> 46.197809 | AG81: =IF(I81<J81,"BUY",IF(I81<K81,"","SELL")) | AH81: =IF(AG81="",AH80,IF(AG81="BUY",1,-1)) -> -1 | AI81: =IF(AH81=AH80,-10,IF(AH81=-1,70,30)) -> -10 | AJ81: =IF(OR(AH81=0,AH81=AH80),AJ80,C81) -> 64.8 | AK81: =IF(AJ81=AJ80,0,AH80*(AJ81/AJ80-1)) -> 0 | AL81: =AK81+AL80 -> 0.21877785 | AQ81: =IF(AH81=AH80,-10,IF(AH81=1,C81,-10)) -> -10 | AR81: =IF(AH81=AH80,-5,IF(AH81=-1,C81,-5)) -> -5
B82: 45043 | C82: 62.69 | E82: =LN(C82/C81) -> 0.021117896 | F82: =SUMIF(E69:E82,">0",E69:E82) -> 0.10774765 | G82: =ABS(SUMIF(E69:E82,"<0",E69:E82)) -> 0.078286143 | H82: =F82/G82 -> 1.376331 | I82: =100-100/(1+H82) -> 57.91832 | J82: 30 | K82: 70 | M82: =(I82*$M$1)+(M81*(1-$M$1)) -> 58.301623 | N82: =STDEV(I72:I82) -> 12.334914 | O82: =M82+N82 -> 70.636538 | P82: =M82-N82 -> 45.966709 | AG82: =IF(I82<J82,"BUY",IF(I82<K82,"","SELL")) | AH82: =IF(AG82="",AH81,IF(AG82="BUY",1,-1)) -> -1 | AI82: =IF(AH82=AH81,-10,IF(AH82=-1,70,30)) -> -10 | AJ82: =IF(OR(AH82=0,AH82=AH81),AJ81,C82) -> 64.8 | AK82: =IF(AJ82=AJ81,0,AH81*(AJ82/AJ81-1)) -> 0 | AL82: =AK82+AL81 -> 0.21877785 | AQ82: =IF(AH82=AH81,-10,IF(AH82=1,C82,-10)) -> -10 | AR82: =IF(AH82=AH81,-5,IF(AH82=-1,C82,-5)) -> -5
B83: 45044 | C83: 63.39 | E83: =LN(C83/C82) -> 0.011104175 | F83: =SUMIF(E70:E83,">0",E70:E83) -> 0.10288016 | G83: =ABS(SUMIF(E70:E83,"<0",E70:E83)) -> 0.078286143 | H83: =F83/G83 -> 1.3141555 | I83: =100-100/(1+H83) -> 56.787692 | J83: 30 | K83: 70 | M83: =(I83*$M$1)+(M82*(1-$M$1)) -> 58.112382 | N83: =STDEV(I73:I83) -> 11.695121 | O83: =M83+N83 -> 69.807503 | P83: =M83-N83 -> 46.417261 | AG83: =IF(I83<J83,"BUY",IF(I83<K83,"","SELL")) | AH83: =IF(AG83="",AH82,IF(AG83="BUY",1,-1)) -> -1 | AI83: =IF(AH83=AH82,-10,IF(AH83=-1,70,30)) -> -10 | AJ83: =IF(OR(AH83=0,AH83=AH82),AJ82,C83) -> 64.8 | AK83: =IF(AJ83=AJ82,0,AH82*(AJ83/AJ82-1)) -> 0 | AL83: =AK83+AL82 -> 0.21877785 | AQ83: =IF(AH83=AH82,-10,IF(AH83=1,C83,-10)) -> -10 | AR83: =IF(AH83=AH82,-5,IF(AH83=-1,C83,-5)) -> -5
B84: 45047 | C84: 63.72 | E84: =LN(C84/C83) -> 0.0051923647 | F84: =SUMIF(E71:E84,">0",E71:E84) -> 0.087588536 | G84: =ABS(SUMIF(E71:E84,"<0",E71:E84)) -> 0.078286143 | H84: =F84/G84 -> 1.1188255 | I84: =100-100/(1+H84) -> 52.804042 | J84: 30 | K84: 70 | M84: =(I84*$M$1)+(M83*(1-$M$1)) -> 57.44884 | N84: =STDEV(I74:I84) -> 10.646209 | O84: =M84+N84 -> 68.095049 | P84: =M84-N84 -> 46.802631 | AG84: =IF(I84<J84,"BUY",IF(I84<K84,"","SELL")) | AH84: =IF(AG84="",AH83,IF(AG84="BUY",1,-1)) -> -1 | AI84: =IF(AH84=AH83,-10,IF(AH84=-1,70,30)) -> -10 | AJ84: =IF(OR(AH84=0,AH84=AH83),AJ83,C84) -> 64.8 | AK84: =IF(AJ84=AJ83,0,AH83*(AJ84/AJ83-1)) -> 0 | AL84: =AK84+AL83 -> 0.21877785 | AQ84: =IF(AH84=AH83,-10,IF(AH84=1,C84,-10)) -> -10 | AR84: =IF(AH84=AH83,-5,IF(AH84=-1,C84,-5)) -> -5
B85: 45048 | C85: 61.26 | E85: =LN(C85/C84) -> -0.039371384 | F85: =SUMIF(E72:E85,">0",E72:E85) -> 0.087588536 | G85: =ABS(SUMIF(E72:E85,"<0",E72:E85)) -> 0.10890717 | H85: =F85/G85 -> 0.80424947 | I85: =100-100/(1+H85) -> 44.575292 | J85: 30 | K85: 70 | M85: =(I85*$M$1)+(M84*(1-$M$1)) -> 55.839646 | N85: =STDEV(I75:I85) -> 10.062158 | O85: =M85+N85 -> 65.901804 | P85: =M85-N85 -> 45.777488 | AG85: =IF(I85<J85,"BUY",IF(I85<K85,"","SELL")) | AH85: =IF(AG85="",AH84,IF(AG85="BUY",1,-1)) -> -1 | AI85: =IF(AH85=AH84,-10,IF(AH85=-1,70,30)) -> -10 | AJ85: =IF(OR(AH85=0,AH85=AH84),AJ84,C85) -> 64.8 | AK85: =IF(AJ85=AJ84,0,AH84*(AJ85/AJ84-1)) -> 0 | AL85: =AK85+AL84 -> 0.21877785 | AQ85: =IF(AH85=AH84,-10,IF(AH85=1,C85,-10)) -> -10 | AR85: =IF(AH85=AH84,-5,IF(AH85=-1,C85,-5)) -> -5
B86: 45049 | C86: 60.93 | E86: =LN(C86/C85) -> -0.0054014371 | F86: =SUMIF(E73:E86,">0",E73:E86) -> 0.052728671 | G86: =ABS(SUMIF(E73:E86,"<0",E73:E86)) -> 0.11430861 | H86: =F86/G86 -> 0.46128346 | I86: =100-100/(1+H86) -> 31.567007 | J86: 30 | K86: 70 | M86: =(I86*$M$1)+(M85*(1-$M$1)) -> 52.805566 | N86: =STDEV(I76:I86) -> 10.580934 | O86: =M86+N86 -> 63.3865 | P86: =M86-N86 -> 42.224633 | AG86: =IF(I86<J86,"BUY",IF(I86<K86,"","SELL")) | AH86: =IF(AG86="",AH85,IF(AG86="BUY",1,-1)) -> -1 | AI86: =IF(AH86=AH85,-10,IF(AH86=-1,70,30)) -> -10 | AJ86: =IF(OR(AH86=0,AH86=AH85),AJ85,C86) -> 64.8 | AK86: =IF(AJ86=AJ85,0,AH85*(AJ86/AJ85-1)) -> 0 | AL86: =AK86+AL85 -> 0.21877785 | AQ86: =IF(AH86=AH85,-10,IF(AH86=1,C86,-10)) -> -10 | AR86: =IF(AH86=AH85,-5,IF(AH86=-1,C86,-5)) -> -5
B87: 45050 | C87: 58.04 | E87: =LN(C87/C86) -> -0.048593236 | F87: =SUMIF(E74:E87,">0",E74:E87) -> 0.04949317 | G87: =ABS(SUMIF(E74:E87,"<0",E74:E87)) -> 0.16290185 | H87: =F87/G87 -> 0.30382203 | I87: =100-100/(1+H87) -> 23.302416 | J87: 30 | K87: 70 | M87: =(I87*$M$1)+(M86*(1-$M$1)) -> 49.117672 | N87: =STDEV(I77:I87) -> 11.636773 | O87: =M87+N87 -> 60.754446 | P87: =M87-N87 -> 37.480899 | AG87: =IF(I87<J87,"BUY",IF(I87<K87,"","SELL")) -> BUY | AH87: =IF(AG87="",AH86,IF(AG87="BUY",1,-1)) -> 1 | AI87: =IF(AH87=AH86,-10,IF(AH87=-1,70,30)) -> 30 | AJ87: =IF(OR(AH87=0,AH87=AH86),AJ86,C87) -> 58.04 | AK87: =IF(AJ87=AJ86,0,AH86*(AJ87/AJ86-1)) -> 0.10432099 | AL87: =AK87+AL86 -> 0.32309884 | AQ87: =IF(AH87=AH86,-10,IF(AH87=1,C87,-10)) -> 58.04 | AR87: =IF(AH87=AH86,-5,IF(AH87=-1,C87,-5)) -> -5
B88: 45051 | C88: 60.53 | E88: =LN(C88/C87) -> 0.042006682 | F88: =SUMIF(E75:E88,">0",E75:E88) -> 0.08781491 | G88: =ABS(SUMIF(E75:E88,"<0",E75:E88)) -> 0.16290185 | H88: =F88/G88 -> 0.53906639 | I88: =100-100/(1+H88) -> 35.025545 | J88: 30 | K88: 70 | M88: =(I88*$M$1)+(M87*(1-$M$1)) -> 47.356157 | N88: =STDEV(I78:I88) -> 11.290786 | O88: =M88+N88 -> 58.646942 | P88: =M88-N88 -> 36.065371 | AG88: =IF(I88<J88,"BUY",IF(I88<K88,"","SELL")) | AH88: =IF(AG88="",AH87,IF(AG88="BUY",1,-1)) -> 1 | AI88: =IF(AH88=AH87,-10,IF(AH88=-1,70,30)) -> -10 | AJ88: =IF(OR(AH88=0,AH88=AH87),AJ87,C88) -> 58.04 | AK88: =IF(AJ88=AJ87,0,AH87*(AJ88/AJ87-1)) -> 0 | AL88: =AK88+AL87 -> 0.32309884 | AQ88: =IF(AH88=AH87,-10,IF(AH88=1,C88,-10)) -> -10 | AR88: =IF(AH88=AH87,-5,IF(AH88=-1,C88,-5)) -> -5
... B114: 45090 | C114: 76.01 | E114: =LN(C114/C113) -> 0.031676554 | F114: =SUMIF(E101:E114,">0",E101:E114) -> 0.18820649 | G114: =ABS(SUMIF(E101:E114,"<0",E101:E114)) -> 0.021212202 | H114: =F114/G114 -> 8.8725576 | I114: =100-100/(1+H114) -> 89.870913 | J114: 30 | K114: 70 | M114: =(I114*$M$1)+(M113*(1-$M$1)) -> 72.410439 | N114: =STDEV(I104:I114) -> 8.4507233 | O114: =M114+N114 -> 80.861162 | P114: =M114-N114 -> 63.959716 | AG114: =IF(I114<J114,"BUY",IF(I114<K114,"","SELL")) -> SELL | AH114: =IF(AG114="",AH113,IF(AG114="BUY",1,-1)) -> -1 | AI114: =IF(AH114=AH113,-10,IF(AH114=-1,70,30)) -> -10 | AJ114: =IF(OR(AH114=0,AH114=AH113),AJ113,C114) -> 69.7 | AK114: =IF(AJ114=AJ113,0,AH113*(AJ114/AJ113-1)) -> 0 | AL114: =AK114+AL113 -> 0.52399477 | AQ114: =IF(AH114=AH113,-10,IF(AH114=1,C114,-10)) -> -10 | AR114: =IF(AH114=AH113,-5,IF(AH114=-1,C114,-5)) -> -5
B115: 45091 | C115: 76.15 | E115: =LN(C115/C114) -> 0.0018401688 | F115: =SUMIF(E102:E115,">0",E102:E115) -> 0.19004666 | G115: =ABS(SUMIF(E101:E115,"<0",E102:E115)) -> 0.019811969 | H115: =F115/G115 -> 9.5925175 | I115: =100-100/(1+H115) -> 90.559374 | J115: 30 | K115: 70 | M115: =(I115*$M$1)+(M114*(1-$M$1)) -> 74.679056 | N115: =STDEV(I105:I115) -> 9.0555425 | O115: =M115+N115 -> 83.734598 | P115: =M115-N115 -> 65.623513 | AG115: =IF(I115<J115,"BUY",IF(I115<K115,"","SELL")) -> SELL | AH115: =IF(AG115="",AH114,IF(AG115="BUY",1,-1)) -> -1 | AI115: =IF(AH115=AH114,-10,IF(AH115=-1,70,30)) -> -10 | AJ115: =IF(OR(AH115=0,AH115=AH114),AJ114,C115) -> 69.7 | AK115: =IF(AJ115=AJ114,0,AH114*(AJ115/AJ114-1)) -> 0 | AL115: =AK115+AL114 -> 0.52399477 | AQ115: =IF(AH115=AH114,-10,IF(AH115=1,C115,-10)) -> -10 | AR115: =IF(AH115=AH114,-5,IF(AH115=-1,C115,-5)) -> -5
B116: 45092 | C116: 77.39 | E116: =LN(C116/C115) -> 0.016152494 | F116: =SUMIF(E103:E116,">0",E103:E116) -> 0.18638718 | G116: =ABS(SUMIF(E103:E117,"<0",E103:E116)) -> 0.0040137297 | H116: =F116/G116 -> 46.437402 | I116: =100-100/(1+H116) -> 97.891959 | J116: 30 | K116: 70 | M116: =(I116*$M$1)+(M115*(1-$M$1)) -> 77.580669 | N116: =STDEV(I106:I116) -> 9.5202098 | O116: =M116+N116 -> 87.100878 | P116: =M116-N116 -> 68.060459 | AG116: =IF(I116<J116,"BUY",IF(I116<K116,"","SELL")) -> SELL | AH116: =IF(AG116="",AH115,IF(AG116="BUY",1,-1)) -> -1 | AI116: =IF(AH116=AH115,-10,IF(AH116=-1,70,30)) -> -10 | AJ116: =IF(OR(AH116=0,AH116=AH115),AJ115,C116) -> 69.7 | AK116: =IF(AJ116=AJ115,0,AH115*(AJ116/AJ115-1)) -> 0 | AL116: =AK116+AL115 -> 0.52399477 | AQ116: =IF(AH116=AH115,-10,IF(AH116=1,C116,-10)) -> -10 | AR116: =IF(AH116=AH115,-5,IF(AH116=-1,C116,-5)) -> -5
B117: 45093 | C117: 77.08 | E117: =LN(C117/C116) -> -0.0040137297 | F117: =SUMIF(E104:E117,">0",E104:E117) -> 0.16802955 | G117: =ABS(SUMIF(E104:E117,"<0",E104:E117)) -> 0.0040137297 | H117: =F117/G117 -> 41.863693 | I117: =100-100/(1+H117) -> 97.667023 | J117: 30 | K117: 70 | M117: =(I117*$M$1)+(M116*(1-$M$1)) -> 80.091463 | N117: =STDEV(I107:I117) -> 9.2235163 | O117: =M117+N117 -> 89.314979 | P117: =M117-N117 -> 70.867947 | AG117: =IF(I117<J117,"BUY",IF(I117<K117,"","SELL")) -> SELL | AH117: =IF(AG117="",AH116,IF(AG117="BUY",1,-1)) -> -1 | AI117: =IF(AH117=AH116,-10,IF(AH117=-1,70,30)) -> -10 | AJ117: =IF(OR(AH117=0,AH117=AH116),AJ116,C117) -> 69.7 | AK117: =IF(AJ117=AJ116,0,AH116*(AJ117/AJ116-1)) -> 0 | AL117: =AK117+AL116 -> 0.52399477 | AQ117: =IF(AH117=AH116,-10,IF(AH117=1,C117,-10)) -> -10 | AR117: =IF(AH117=AH116,-5,IF(AH117=-1,C117,-5)) -> -5
B118: 45097 | C118: 76.4 | E118: =LN(C118/C117) -> -0.0088611474 | F118: =SUMIF(E105:E118,">0",E105:E118) -> 0.14745394 | G118: =ABS(SUMIF(E105:E118,"<0",E105:E118)) -> 0.012874877 | H118: =F118/G118 -> 11.452842 | I118: =100-100/(1+H118) -> 91.969705 | J118: 30 | K118: 70 | M118: =(I118*$M$1)+(M117*(1-$M$1)) -> 81.576243 | N118: =STDEV(I108:I118) -> 8.8713021 | O118: =M118+N118 -> 90.447545 | P118: =M118-N118 -> 72.704941 | AG118: =IF(I118<J118,"BUY",IF(I118<K118,"","SELL")) -> SELL | AH118: =IF(AG118="",AH117,IF(AG118="BUY",1,-1)) -> -1 | AI118: =IF(AH118=AH117,-10,IF(AH118=-1,70,30)) -> -10 | AJ118: =IF(OR(AH118=0,AH118=AH117),AJ117,C118) -> 69.7 | AK118: =IF(AJ118=AJ117,0,AH117*(AJ118/AJ117-1)) -> 0 | AL118: =AK118+AL117 -> 0.52399477 | AQ118: =IF(AH118=AH117,-10,IF(AH118=1,C118,-10)) -> -10 | AR118: =IF(AH118=AH117,-5,IF(AH118=-1,C118,-5)) -> -5
B119: 45098 | C119: 76.41 | E119: =LN(C119/C118) -> 0.00013088149 | F119: =SUMIF(E106:E119,">0",E106:E119) -> 0.14653715 | G119: =ABS(SUMIF(E106:E119,"<0",E106:E119)) -> 0.012874877 | H119: =F119/G119 -> 11.381635 | I119: =100-100/(1+H119) -> 91.923522 | J119: 30 | K119: 70 | M119: =(I119*$M$1)+(M118*(1-$M$1)) -> 82.869653 | N119: =STDEV(I109:I119) -> 8.1115581 | O119: =M119+N119 -> 90.981211 | P119: =M119-N119 -> 74.758095 | AG119: =IF(I119<J119,"BUY",IF(I119<K119,"","SELL")) -> SELL | AH119: =IF(AG119="",AH118,IF(AG119="BUY",1,-1)) -> -1 | AI119: =IF(AH119=AH118,-10,IF(AH119=-1,70,30)) -> -10 | AJ119: =IF(OR(AH119=0,AH119=AH118),AJ118,C119) -> 69.7 | AK119: =IF(AJ119=AJ118,0,AH118*(AJ119/AJ118-1)) -> 0 | AL119: =AK119+AL118 -> 0.52399477 | AQ119: =IF(AH119=AH118,-10,IF(AH119=1,C119,-10)) -> -10 | AR119: =IF(AH119=AH118,-5,IF(AH119=-1,C119,-5)) -> -5
B120: 45099 | C120: 74.87 | E120: =LN(C120/C119) -> -0.020360301 | F120: =SUMIF(E107:E120,">0",E107:E120) -> 0.12948075 | G120: =ABS(SUMIF(E107:E120,"<0",E107:E120)) -> 0.033235179 | H120: =F120/G120 -> 3.8958945 | I120: =100-100/(1+H120) -> 79.574723 | J120: 30 | K120: 70 | M120: =(I120*$M$1)+(M119*(1-$M$1)) -> 82.457787 | N120: =STDEV(I110:I120) -> 8.0942795 | O120: =M120+N120 -> 90.552066 | P120: =M120-N120 -> 74.363507 | AG120: =IF(I120<J120,"BUY",IF(I120<K120,"","SELL")) -> SELL | AH120: =IF(AG120="",AH119,IF(AG120="BUY",1,-1)) -> -1 | AI120: =IF(AH120=AH119,-10,IF(AH120=-1,70,30)) -> -10 | AJ120: =IF(OR(AH120=0,AH120=AH119),AJ119,C120) -> 69.7 | AK120: =IF(AJ120=AJ119,0,AH119*(AJ120/AJ119-1)) -> 0 | AL120: =AK120+AL119 -> 0.52399477 | AQ120: =IF(AH120=AH119,-10,IF(AH120=1,C120,-10)) -> -10 | AR120: =IF(AH120=AH119,-5,IF(AH120=-1,C120,-5)) -> -5
B121: 45100 | C121: 73 | E121: =LN(C121/C120) -> -0.025293835 | F121: =SUMIF(E108:E121,">0",E108:E121) -> 0.10478814 | G121: =ABS(SUMIF(E108:E121,"<0",E108:E121)) -> 0.058529014 | H121: =F121/G121 -> 1.7903623 | I121: =100-100/(1+H121) -> 64.162359 | J121: 30 | K121: 70 | M121: =(I121*$M$1)+(M120*(1-$M$1)) -> 80.170858 | N121: =STDEV(I111:I121) -> 10.346952 | O121: =M121+N121 -> 90.517811 | P121: =M121-N121 -> 69.823906 | AG121: =IF(I121<J121,"BUY",IF(I121<K121,"","SELL")) | AH121: =IF(AG121="",AH120,IF(AG121="BUY",1,-1)) -> -1 | AI121: =IF(AH121=AH120,-10,IF(AH121=-1,70,30)) -> -10 | AJ121: =IF(OR(AH121=0,AH121=AH120),AJ120,C121) -> 69.7 | AK121: =IF(AJ121=AJ120,0,AH120*(AJ121/AJ120-1)) -> 0 | AL121: =AK121+AL120 -> 0.52399477 | AQ121: =IF(AH121=AH120,-10,IF(AH121=1,C121,-10)) -> -10 | AR121: =IF(AH121=AH120,-5,IF(AH121=-1,C121,-5)) -> -5
B122: 45103 | C122: 73.67 | E122: =LN(C122/C121) -> 0.0091362195 | F122: =SUMIF(E109:E122,">0",E109:E122) -> 0.10251196 | G122: =ABS(SUMIF(E109:E122,"<0",E109:E122)) -> 0.058529014 | H122: =F122/G122 -> 1.7514726 | I122: =100-100/(1+H122) -> 63.655826 | J122: 30 | K122: 70 | M122: =(I122*$M$1)+(M121*(1-$M$1)) -> 78.106479 | N122: =STDEV(I112:I122) -> 12.175403 | O122: =M122+N122 -> 90.281882 | P122: =M122-N122 -> 65.931076 | AG122: =IF(I122<J122,"BUY",IF(I122<K122,"","SELL")) | AH122: =IF(AG122="",AH121,IF(AG122="BUY",1,-1)) -> -1 | AI122: =IF(AH122=AH121,-10,IF(AH122=-1,70,30)) -> -10 | AJ122: =IF(OR(AH122=0,AH122=AH121),AJ121,C122) -> 69.7 | AK122: =IF(AJ122=AJ121,0,AH121*(AJ122/AJ121-1)) -> 0 | AL122: =AK122+AL121 -> 0.52399477 | AQ122: =IF(AH122=AH121,-10,IF(AH122=1,C122,-10)) -> -10 | AR122: =IF(AH122=AH121,-5,IF(AH122=-1,C122,-5)) -> -5
B123: 45104 | C123: 74.76 | E123: =LN(C123/C122) -> 0.014687322 | F123: =SUMIF(E110:E123,">0",E110:E123) -> 0.11111852 | G123: =ABS(SUMIF(E110:E123,"<0",E110:E123)) -> 0.058529014 | H123: =F123/G123 -> 1.8985203 | I123: =100-100/(1+H123) -> 65.499638 | J123: 30 | K123: 70 | M123: =(I123*$M$1)+(M122*(1-$M$1)) -> 76.530624 | N123: =STDEV(I113:I123) -> 13.358445 | O123: =M123+N123 -> 89.889069 | P123: =M123-N123 -> 63.172179 | AG123: =IF(I123<J123,"BUY",IF(I123<K123,"","SELL")) | AH123: =IF(AG123="",AH122,IF(AG123="BUY",1,-1)) -> -1 | AI123: =IF(AH123=AH122,-10,IF(AH123=-1,70,30)) -> -10 | AJ123: =IF(OR(AH123=0,AH123=AH122),AJ122,C123) -> 69.7 | AK123: =IF(AJ123=AJ122,0,AH122*(AJ123/AJ122-1)) -> 0 | AL123: =AK123+AL122 -> 0.52399477 | AQ123: =IF(AH123=AH122,-10,IF(AH123=1,C123,-10)) -> -10 | AR123: =IF(AH123=AH122,-5,IF(AH123=-1,C123,-5)) -> -5
B124: 45105 | C124: 75.14 | E124: =LN(C124/C123) -> 0.0050700576 | F124: =SUMIF(E111:E124,">0",E111:E124) -> 0.10706635 | G124: =ABS(SUMIF(E111:E124,"<0",E111:E124)) -> 0.058529014 | H124: =F124/G124 -> 1.8292867 | I124: =100-100/(1+H124) -> 64.655403 | J124: 30 | K124: 70 | M124: =(I124*$M$1)+(M123*(1-$M$1)) -> 75.046221 | N124: =STDEV(I114:I124) -> 14.362682 | O124: =M124+N124 -> 89.408903 | P124: =M124-N124 -> 60.68354 | AG124: =IF(I124<J124,"BUY",IF(I124<K124,"","SELL")) | AH124: =IF(AG124="",AH123,IF(AG124="BUY",1,-1)) -> -1 | AI124: =IF(AH124=AH123,-10,IF(AH124=-1,70,30)) -> -10 | AJ124: =IF(OR(AH124=0,AH124=AH123),AJ123,C124) -> 69.7 | AK124: =IF(AJ124=AJ123,0,AH123*(AJ124/AJ123-1)) -> 0 | AL124: =AK124+AL123 -> 0.52399477 | AQ124: =IF(AH124=AH123,-10,IF(AH124=1,C124,-10)) -> -10 | AR124: =IF(AH124=AH123,-5,IF(AH124=-1,C124,-5)) -> -5
B125: 45106 | C125: 75.81 | E125: =LN(C125/C124) -> 0.0088771699 | F125: =SUMIF(E112:E125,">0",E112:E125) -> 0.099730318 | G125: =ABS(SUMIF(E112:E125,"<0",E112:E125)) -> 0.058529014 | H125: =F125/G125 -> 1.7039467 | I125: =100-100/(1+H125) -> 63.017022 | J125: 30 | K125: 70 | M125: =(I125*$M$1)+(M124*(1-$M$1)) -> 73.542572 | N125: =STDEV(I115:I125) -> 15.077799 | O125: =M125+N125 -> 88.62037 | P125: =M125-N125 -> 58.464773 | AG125: =IF(I125<J125,"BUY",IF(I125<K125,"","SELL")) | AH125: =IF(AG125="",AH124,IF(AG125="BUY",1,-1)) -> -1 | AI125: =IF(AH125=AH124,-10,IF(AH125=-1,70,30)) -> -10 | AJ125: =IF(OR(AH125=0,AH125=AH124),AJ124,C125) -> 69.7 | AK125: =IF(AJ125=AJ124,0,AH124*(AJ125/AJ124-1)) -> 0 | AL125: =AK125+AL124 -> 0.52399477 | AQ125: =IF(AH125=AH124,-10,IF(AH125=1,C125,-10)) -> -10 | AR125: =IF(AH125=AH124,-5,IF(AH125=-1,C125,-5)) -> -5
B126: 45107 | C126: 76.81 | E126: =LN(C126/C125) -> 0.01310463 | F126: =SUMIF(E113:E126,">0",E113:E126) -> 0.10967842 | G126: =ABS(SUMIF(E113:E126,"<0",E113:E126)) -> 0.058529014 | H126: =F126/G126 -> 1.8739154 | I126: =100-100/(1+H126) -> 65.204265 | J126: 30 | K126: 70 | M126: =(I126*$M$1)+(M125*(1-$M$1)) -> 72.500283 | N126: =STDEV(I116:I126) -> 15.096117 | O126: =M126+N126 -> 87.5964 | P126: =M126-N126 -> 57.404166 | AG126: =IF(I126<J126,"BUY",IF(I126<K126,"","SELL")) | AH126: =IF(AG126="",AH125,IF(AG126="BUY",1,-1)) -> -1 | AI126: =IF(AH126=AH125,-10,IF(AH126=-1,70,30)) -> -10 | AJ126: =IF(OR(AH126=0,AH126=AH125),AJ125,C126) -> 69.7 | AK126: =IF(AJ126=AJ125,0,AH125*(AJ126/AJ125-1)) -> 0 | AL126: =AK126+AL125 -> 0.52399477 | AQ126: =IF(AH126=AH125,-10,IF(AH126=1,C126,-10)) -> -10 | AR126: =IF(AH126=AH125,-5,IF(AH126=-1,C126,-5)) -> -5
B127: 45110 | C127: 77.07 | E127: =LN(C127/C126) -> 0.0033792598 | F127: =SUMIF(E114:E127,">0",E114:E127) -> 0.10405476 | G127: =ABS(SUMIF(E114:E127,"<0",E114:E127)) -> 0.058529014 | H127: =F127/G127 -> 1.7778321 | I127: =100-100/(1+H127) -> 64.000704 | J127: 30 | K127: 70 | M127: =(I127*$M$1)+(M126*(1-$M$1)) -> 71.437836 | N127: =STDEV(I117:I127) -> 13.769735 | O127: =M127+N127 -> 85.20757 | P127: =M127-N127 -> 57.668101 | AG127: =IF(I127<J127,"BUY",IF(I127<K127,"","SELL")) | AH127: =IF(AG127="",AH126,IF(AG127="BUY",1,-1)) -> -1 | AI127: =IF(AH127=AH126,-10,IF(AH127=-1,70,30)) -> -10 | AJ127: =IF(OR(AH127=0,AH127=AH126),AJ126,C127) -> 69.7 | AK127: =IF(AJ127=AJ126,0,AH126*(AJ127/AJ126-1)) -> 0 | AL127: =AK127+AL126 -> 0.52399477 | AQ127: =IF(AH127=AH126,-10,IF(AH127=1,C127,-10)) -> -10 | AR127: =IF(AH127=AH126,-5,IF(AH127=-1,C127,-5)) -> -5
B128: 45112 | C128: 76.03 | E128: =LN(C128/C127) -> -0.013586101 | F128: =SUMIF(E115:E128,">0",E115:E128) -> 0.072378203 | G128: =ABS(SUMIF(E115:E128,"<0",E115:E128)) -> 0.072115114 | H128: =F128/G128 -> 1.0036482 | I128: =100-100/(1+H128) -> 50.091038 | J128: 30 | K128: 70 | M128: =(I128*$M$1)+(M127*(1-$M$1)) -> 68.769486 | N128: =STDEV(I118:I128) -> 12.956472 | O128: =M128+N128 -> 81.725958 | P128: =M128-N128 -> 55.813014 | AG128: =IF(I128<J128,"BUY",IF(I128<K128,"","SELL")) | AH128: =IF(AG128="",AH127,IF(AG128="BUY",1,-1)) -> -1 | AI128: =IF(AH128=AH127,-10,IF(AH128=-1,70,30)) -> -10 | AJ128: =IF(OR(AH128=0,AH128=AH127),AJ127,C128) -> 69.7 | AK128: =IF(AJ128=AJ127,0,AH127*(AJ128/AJ127-1)) -> 0 | AL128: =AK128+AL127 -> 0.52399477 | AQ128: =IF(AH128=AH127,-10,IF(AH128=1,C128,-10)) -> -10 | AR128: =IF(AH128=AH127,-5,IF(AH128=-1,C128,-5)) -> -5
... B504: 45657 | C504: 165.16 | E504: =LN(C504/C503) -> -0.0081406667 | F504: =SUMIF(E491:E504,">0",E491:E504) -> 0.075195648 | G504: =ABS(SUMIF(E491:E504,"<0",E491:E504)) -> 0.1314084 | H504: =F504/G504 -> 0.57222861 | I504: =100-100/(1+H504) -> 36.396018 | J504: 30 | K504: 70 | M504: =(I504*$M$1)+(M503*(1-$M$1)) -> 49.371756 | N504: =STDEV(I494:I504) -> 5.8840288 | O504: =M504+N504 -> 55.255784 | P504: =M504-N504 -> 43.487727 | AG504: =IF(I504<J504,"BUY",IF(I504<K504,"","SELL")) | AH504: =IF(AG504="",AH503,IF(AG504="BUY",1,-1)) -> -1 | AI504: =IF(AH504=AH503,-10,IF(AH504=-1,70,30)) -> -10 | AJ504: =IF(OR(AH504=0,AH504=AH503),AJ503,C504) -> 111.51 | AK504: =IF(AJ504=AJ503,0,AH503*(AJ504/AJ503-1)) -> 0 | AL504: =AK504+AL503 -> 0.31958885 | AQ504: =IF(AH504=AH503,-10,IF(AH504=1,C504,-10)) -> -10 | AR504: =IF(AH504=AH503,-5,IF(AH504=-1,C504,-5)) -> -5

Sheet STOC + MACD
Z1: =2/(12+1) -> 0.15384615 | AA1: =2/(26+1) -> 0.074074074 | AC1: 0.2
B2: Dates | C2: Prices | D2: STOC | E2: Signal | F2: B | G2: S | X2: Dates | Y2: Prices | Z2: EMA 12d | AA2: EMA 26d | AB2: MACD | AC2: Signal | AD2: Diff | AE2: Diff Norm
B3: 44929 | C3: 62.81 | F3: 20 | G3: 80 | X3: 44929 | Y3: 62.81 | Z3: =$Y$3 -> 62.81 | AA3: =$Y$3 -> 62.81
B4: 44930 | C4: 64.36 | F4: 20 | G4: 80 | X4: 44930 | Y4: 64.36 | Z4: =$Z$1*Y4+(1-$Z$1)*Z3 -> 63.048462 | AA4: =$AA$1*Z4+(1-$AA$1)*AA3 -> 62.827664 | AB4: =Z4-AA4 -> 0.22079772
B5: 44931 | C5: 62.95 | F5: 20 | G5: 80 | X5: 44931 | Y5: 62.95 | Z5: =$Z$1*Y5+(1-$Z$1)*Z4 -> 63.033314 | AA5: =$AA$1*Z5+(1-$AA$1)*AA4 -> 62.842897 | AB5: =Z5-AA5 -> 0.19041647 | AC5: =AC$1*AB5+(1-AC$1)*AC4 -> 0.038083295 | AD5: =AB5-AC5 -> 0.15233318 | BH5: The trading protocol that uses the MACD simply follows from a visual inspec tion of the graph:
B6: 44932 | C6: 64.33 | F6: 20 | G6: 80 | X6: 44932 | Y6: 64.33 | Z6: =$Z$1*Y6+(1-$Z$1)*Z5 -> 63.232804 | AA6: =$AA$1*Z6+(1-$AA$1)*AA5 -> 62.871779 | AB6: =Z6-AA6 -> 0.36102471 | AC6: =AC$1*AB6+(1-AC$1)*AC5 -> 0.10267158 | AD6: =AB6-AC6 -> 0.25835313 | BH6: a buy signal occurs when the first line crosses the second one in the lower part of the graph and
B7: 44935 | C7: 65.32 | F7: 20 | G7: 80 | X7: 44935 | Y7: 65.32 | Z7: =$Z$1*Y7+(1-$Z$1)*Z6 -> 63.553911 | AA7: =$AA$1*Z7+(1-$AA$1)*AA6 -> 62.922307 | AB7: =Z7-AA7 -> 0.63160353 | AC7: =AC$1*AB7+(1-AC$1)*AC6 -> 0.20845797 | AD7: =AB7-AC7 -> 0.42314556 | BH7: a sell signal occurs when the first line crosses the second one in the upper part of the graph.
B8: 44936 | C8: 66.52 | F8: 20 | G8: 80 | X8: 44936 | Y8: 66.52 | Z8: =$Z$1*Y8+(1-$Z$1)*Z7 -> 64.010232 | AA8: =$AA$1*Z8+(1-$AA$1)*AA7 -> 63.002894 | AB8: =Z8-AA8 -> 1.0073379 | AC8: =AC$1*AB8+(1-AC$1)*AC7 -> 0.36823395 | AD8: =AB8-AC8 -> 0.63910394
B9: 44937 | C9: 67.68 | F9: 20 | G9: 80 | X9: 44937 | Y9: 67.68 | Z9: =$Z$1*Y9+(1-$Z$1)*Z8 -> 64.574812 | AA9: =$AA$1*Z9+(1-$AA$1)*AA8 -> 63.119333 | AB9: =Z9-AA9 -> 1.4554792 | AC9: =AC$1*AB9+(1-AC$1)*AC8 -> 0.585683 | AD9: =AB9-AC9 -> 0.8697962 | BH9: In addition, as it happens with all the oscillators, divergences can be used, in this case between the histogram and the price curve:
B10: 44938 | C10: 68.44 | F10: 20 | G10: 80 | X10: 44938 | Y10: 68.44 | Z10: =$Z$1*Y10+(1-$Z$1)*Z9 -> 65.169456 | AA10: =$AA$1*Z10+(1-$AA$1)*AA9 -> 63.271194 | AB10: =Z10-AA10 -> 1.8982625 | AC10: =AC$1*AB10+(1-AC$1)*AC9 -> 0.84819891 | AD10: =AB10-AC10 -> 1.0500636 | BH10: a bullish divergence occurs when the stock price reaches a new low but not so the MACD histogram;
B11: 44939 | C11: 69.71 | F11: 20 | G11: 80 | X11: 44939 | Y11: 69.71 | Z11: =$Z$1*Y11+(1-$Z$1)*Z10 -> 65.868001 | AA11: =$AA$1*Z11+(1-$AA$1)*AA10 -> 63.46355 | AB11: =Z11-AA11 -> 2.4044516 | AC11: =AC$1*AB11+(1-AC$1)*AC10 -> 1.1594494 | AD11: =AB11-AC11 -> 1.2450021 | BH11: a bearish divergence occurs when the stock price reaches a new high but not so the MACD histogram.
B12: 44943 | C12: 69.09 | F12: 20 | G12: 80 | X12: 44943 | Y12: 69.09 | Z12: =$Z$1*Y12+(1-$Z$1)*Z11 -> 66.363694 | AA12: =$AA$1*Z12+(1-$AA$1)*AA11 -> 63.678375 | AB12: =Z12-AA12 -> 2.6853182 | AC12: =AC$1*AB12+(1-AC$1)*AC11 -> 1.4646232 | AD12: =AB12-AC12 -> 1.220695
B13: 44944 | C13: 68.03 | F13: 20 | G13: 80 | X13: 44944 | Y13: 68.03 | Z13: =$Z$1*Y13+(1-$Z$1)*Z12 -> 66.620048 | AA13: =$AA$1*Z13+(1-$AA$1)*AA12 -> 63.896277 | AB13: =Z13-AA13 -> 2.7237713 | AC13: =AC$1*AB13+(1-AC$1)*AC12 -> 1.7164528 | AD13: =AB13-AC13 -> 1.0073185
B14: 44945 | C14: 65.78 | F14: 20 | G14: 80 | X14: 44945 | Y14: 65.78 | Z14: =$Z$1*Y14+(1-$Z$1)*Z13 -> 66.49081 | AA14: =$AA$1*Z14+(1-$AA$1)*AA13 -> 64.088465 | AB14: =Z14-AA14 -> 2.4023455 | AC14: =AC$1*AB14+(1-AC$1)*AC13 -> 1.8536314 | AD14: =AB14-AC14 -> 0.54871413
B15: 44946 | C15: 67.07 | F15: 20 | G15: 80 | X15: 44946 | Y15: 67.07 | Z15: =$Z$1*Y15+(1-$Z$1)*Z14 -> 66.579916 | AA15: =$AA$1*Z15+(1-$AA$1)*AA14 -> 64.273017 | AB15: =Z15-AA15 -> 2.3068996 | AC15: =AC$1*AB15+(1-AC$1)*AC14 -> 1.944285 | AD15: =AB15-AC15 -> 0.36261463
B16: 44949 | C16: 68.84 | F16: 20 | G16: 80 | X16: 44949 | Y16: 68.84 | Z16: =$Z$1*Y16+(1-$Z$1)*Z15 -> 66.927621 | AA16: =$AA$1*Z16+(1-$AA$1)*AA15 -> 64.469654 | AB16: =Z16-AA16 -> 2.4579674 | AC16: =AC$1*AB16+(1-AC$1)*AC15 -> 2.0470215 | AD16: =AB16-AC16 -> 0.41094593
B17: 44950 | C17: 67.7 | F17: 20 | G17: 80 | X17: 44950 | Y17: 67.7 | Z17: =$Z$1*Y17+(1-$Z$1)*Z16 -> 67.046449 | AA17: =$AA$1*Z17+(1-$AA$1)*AA16 -> 64.660528 | AB17: =Z17-AA17 -> 2.3859212 | AC17: =AC$1*AB17+(1-AC$1)*AC16 -> 2.1148014 | AD17: =AB17-AC17 -> 0.27111976
B18: 44951 | C18: 67.6 | F18: 20 | G18: 80 | X18: 44951 | Y18: 67.6 | Z18: =$Z$1*Y18+(1-$Z$1)*Z17 -> 67.131611 | AA18: =$AA$1*Z18+(1-$AA$1)*AA17 -> 64.843571 | AB18: =Z18-AA18 -> 2.2880397 | AC18: =AC$1*AB18+(1-AC$1)*AC17 -> 2.1494491 | AD18: =AB18-AC18 -> 0.13859063
B19: 44952 | C19: 70.43 | F19: 20 | G19: 80 | X19: 44952 | Y19: 70.43 | Z19: =$Z$1*Y19+(1-$Z$1)*Z18 -> 67.639055 | AA19: =$AA$1*Z19+(1-$AA$1)*AA18 -> 65.050644 | AB19: =Z19-AA19 -> 2.5884113 | AC19: =AC$1*AB19+(1-AC$1)*AC18 -> 2.2372415 | AD19: =AB19-AC19 -> 0.35116979
B20: 44953 | C20: 70.82 | F20: 20 | G20: 80 | X20: 44953 | Y20: 70.82 | Z20: =$Z$1*Y20+(1-$Z$1)*Z19 -> 68.128431 | AA20: =$AA$1*Z20+(1-$AA$1)*AA19 -> 65.278628 | AB20: =Z20-AA20 -> 2.8498032 | AC20: =AC$1*AB20+(1-AC$1)*AC19 -> 2.3597539 | AD20: =AB20-AC20 -> 0.49004933
B21: 44956 | C21: 69.26 | F21: 20 | G21: 80 | X21: 44956 | Y21: 69.26 | Z21: =$Z$1*Y21+(1-$Z$1)*Z20 -> 68.302519 | AA21: =$AA$1*Z21+(1-$AA$1)*AA20 -> 65.50262 | AB21: =Z21-AA21 -> 2.7998988 | AC21: =AC$1*AB21+(1-AC$1)*AC20 -> 2.4477829 | AD21: =AB21-AC21 -> 0.35211594
B22: 44957 | C22: 70.78 | D22: =(C22-MIN(C3:C22))/(MAX(C3:C22)-MIN(C3:C22))*100 -> 99.500624 | F22: 20 | G22: 80 | X22: 44957 | Y22: 70.78 | Z22: =$Z$1*Y22+(1-$Z$1)*Z21 -> 68.68367 | AA22: =$AA$1*Z22+(1-$AA$1)*AA21 -> 65.738253 | AB22: =Z22-AA22 -> 2.9454164 | AC22: =AC$1*AB22+(1-AC$1)*AC21 -> 2.5473096 | AD22: =AB22-AC22 -> 0.39810686
B23: 44958 | C23: 72.52 | D23: =100*(C23-MIN(C4:C23))/(MAX(C4:C23)-MIN(C4:C23)) -> 100 | F23: 20 | G23: 80 | X23: 44958 | Y23: 72.52 | Z23: =$Z$1*Y23+(1-$Z$1)*Z22 -> 69.273874 | AA23: =$AA$1*Z23+(1-$AA$1)*AA22 -> 66.000151 | AB23: =Z23-AA23 -> 3.2737232 | AC23: =AC$1*AB23+(1-AC$1)*AC22 -> 2.6925923 | AD23: =AB23-AC23 -> 0.58113093
B24: 44959 | C24: 72.15 | D24: =100*(C24-MIN(C5:C24))/(MAX(C5:C24)-MIN(C5:C24)) -> 96.133751 | F24: 20 | G24: 80 | X24: 44959 | Y24: 72.15 | Z24: =$Z$1*Y24+(1-$Z$1)*Z23 -> 69.716355 | AA24: =$AA$1*Z24+(1-$AA$1)*AA23 -> 66.275426 | AB24: =Z24-AA24 -> 3.4409297 | AC24: =AC$1*AB24+(1-AC$1)*AC23 -> 2.8422598 | AD24: =AB24-AC24 -> 0.59866993
B25: 44960 | C25: 73.4 | D25: =100*(C25-MIN(C6:C25))/(MAX(C6:C25)-MIN(C6:C25)) -> 100 | F25: 20 | G25: 80 | X25: 44960 | Y25: 73.4 | Z25: =$Z$1*Y25+(1-$Z$1)*Z24 -> 70.28307 | AA25: =$AA$1*Z25+(1-$AA$1)*AA24 -> 66.572288 | AB25: =Z25-AA25 -> 3.7107817 | AC25: =AC$1*AB25+(1-AC$1)*AC24 -> 3.0159642 | AD25: =AB25-AC25 -> 0.69481757
B26: 44963 | C26: 72.14 | D26: =100*(C26-MIN(C7:C26))/(MAX(C7:C26)-MIN(C7:C26)) -> 84.405941 | E26: =AVERAGE(D22:D26) -> 96.008063 | F26: 20 | G26: 80 | X26: 44963 | Y26: 72.14 | Z26: =$Z$1*Y26+(1-$Z$1)*Z25 -> 70.568751 | AA26: =$AA$1*Z26+(1-$AA$1)*AA25 -> 66.868322 | AB26: =Z26-AA26 -> 3.700429 | AC26: =AC$1*AB26+(1-AC$1)*AC25 -> 3.1528571 | AD26: =AB26-AC26 -> 0.54757185
B27: 44964 | C27: 73.35 | D27: =100*(C27-MIN(C8:C27))/(MAX(C8:C27)-MIN(C8:C27)) -> 99.343832 | E27: =AVERAGE(D23:D27) -> 95.976705 | F27: 20 | G27: 80 | X27: 44964 | Y27: 73.35 | Z27: =$Z$1*Y27+(1-$Z$1)*Z26 -> 70.996636 | AA27: =$AA$1*Z27+(1-$AA$1)*AA26 -> 67.174123 | AB27: =Z27-AA27 -> 3.8225124 | AC27: =AC$1*AB27+(1-AC$1)*AC26 -> 3.2867882 | AD27: =AB27-AC27 -> 0.53572421
B28: 44965 | C28: 73.89 | D28: =100*(C28-MIN(C9:C28))/(MAX(C9:C28)-MIN(C9:C28)) -> 100 | E28: =AVERAGE(D24:D28) -> 95.976705 | F28: 20 | G28: 80 | X28: 44965 | Y28: 73.89 | Z28: =$Z$1*Y28+(1-$Z$1)*Z27 -> 71.441769 | AA28: =$AA$1*Z28+(1-$AA$1)*AA27 -> 67.490245 | AB28: =Z28-AA28 -> 3.9515235 | AC28: =AC$1*AB28+(1-AC$1)*AC27 -> 3.4197352 | AD28: =AB28-AC28 -> 0.53178823
B29: 44966 | C29: 68.4 | D29: =100*(C29-MIN(C10:C29))/(MAX(C10:C29)-MIN(C10:C29)) -> 32.305795 | E29: =AVERAGE(D25:D29) -> 83.211114 | F29: 20 | G29: 80 | X29: 44966 | Y29: 68.4 | Z29: =$Z$1*Y29+(1-$Z$1)*Z28 -> 70.973804 | AA29: =$AA$1*Z29+(1-$AA$1)*AA28 -> 67.748287 | AB29: =Z29-AA29 -> 3.2255176 | AC29: =AC$1*AB29+(1-AC$1)*AC28 -> 3.3808917 | AD29: =AB29-AC29 -> -0.15537409
B30: 44967 | C30: 70.66 | D30: =100*(C30-MIN(C11:C30))/(MAX(C11:C30)-MIN(C11:C30)) -> 60.172626 | E30: =AVERAGE(D26:D30) -> 75.245639 | F30: 20 | G30: 80 | X30: 44967 | Y30: 70.66 | Z30: =$Z$1*Y30+(1-$Z$1)*Z29 -> 70.925527 | AA30: =$AA$1*Z30+(1-$AA$1)*AA29 -> 67.983638 | AB30: =Z30-AA30 -> 2.9418889 | AC30: =AC$1*AB30+(1-AC$1)*AC29 -> 3.2930912 | AD30: =AB30-AC30 -> -0.35120223
B31: 44970 | C31: 71.07 | D31: =100*(C31-MIN(C12:C31))/(MAX(C12:C31)-MIN(C12:C31)) -> 65.228113 | E31: =AVERAGE(D27:D31) -> 71.410073 | F31: 20 | G31: 80 | X31: 44970 | Y31: 71.07 | Z31: =$Z$1*Y31+(1-$Z$1)*Z30 -> 70.947753 | AA31: =$AA$1*Z31+(1-$AA$1)*AA30 -> 68.203202 | AB31: =Z31-AA31 -> 2.7445515 | AC31: =AC$1*AB31+(1-AC$1)*AC30 -> 3.1833832 | AD31: =AB31-AC31 -> -0.43883176
B32: 44971 | C32: 71.66 | D32: =100*(C32-MIN(C13:C32))/(MAX(C13:C32)-MIN(C13:C32)) -> 72.503083 | E32: =AVERAGE(D28:D32) -> 66.041924 | F32: 20 | G32: 80 | X32: 44971 | Y32: 71.66 | Z32: =$Z$1*Y32+(1-$Z$1)*Z31 -> 71.05733 | AA32: =$AA$1*Z32+(1-$AA$1)*AA31 -> 68.414619 | AB32: =Z32-AA32 -> 2.642711 | AC32: =AC$1*AB32+(1-AC$1)*AC31 -> 3.0752488 | AD32: =AB32-AC32 -> -0.43253779
B33: 44972 | C33: 72.43 | D33: =100*(C33-MIN(C14:C33))/(MAX(C14:C33)-MIN(C14:C33)) -> 81.997534 | E33: =AVERAGE(D29:D33) -> 62.44143 | F33: 20 | G33: 80 | X33: 44972 | Y33: 72.43 | Z33: =$Z$1*Y33+(1-$Z$1)*Z32 -> 71.26851 | AA33: =$AA$1*Z33+(1-$AA$1)*AA32 -> 68.626018 | AB33: =Z33-AA33 -> 2.6424917 | AC33: =AC$1*AB33+(1-AC$1)*AC32 -> 2.9886974 | AD33: =AB33-AC33 -> -0.34620567
B34: 44973 | C34: 72.09 | D34: =100*(C34-MIN(C15:C34))/(MAX(C15:C34)-MIN(C15:C34)) -> 73.607038 | E34: =AVERAGE(D30:D34) -> 70.701679 | F34: 20 | G34: 80 | X34: 44973 | Y34: 72.09 | Z34: =$Z$1*Y34+(1-$Z$1)*Z33 -> 71.394893 | AA34: =$AA$1*Z34+(1-$AA$1)*AA33 -> 68.83112 | AB34: =Z34-AA34 -> 2.563773 | AC34: =AC$1*AB34+(1-AC$1)*AC33 -> 2.9037125 | AD34: =AB34-AC34 -> -0.33993953
B35: 44974 | C35: 71.44 | D35: =100*(C35-MIN(C16:C35))/(MAX(C16:C35)-MIN(C16:C35)) -> 61.049285 | E35: =AVERAGE(D31:D35) -> 70.877011 | F35: 20 | G35: 80 | X35: 44974 | Y35: 71.44 | Z35: =$Z$1*Y35+(1-$Z$1)*Z34 -> 71.401832 | AA35: =$AA$1*Z35+(1-$AA$1)*AA34 -> 69.021543 | AB35: =Z35-AA35 -> 2.3802894 | AC35: =AC$1*AB35+(1-AC$1)*AC34 -> 2.7990279 | AD35: =AB35-AC35 -> -0.4187385
B36: 44978 | C36: 69.35 | D36: =100*(C36-MIN(C17:C36))/(MAX(C17:C36)-MIN(C17:C36)) -> 27.82194 | E36: =AVERAGE(D32:D36) -> 63.395776 | F36: 20 | G36: 80 | X36: 44978 | Y36: 69.35 | Z36: =$Z$1*Y36+(1-$Z$1)*Z35 -> 71.086166 | AA36: =$AA$1*Z36+(1-$AA$1)*AA35 -> 69.174478 | AB36: =Z36-AA36 -> 1.9116878 | AC36: =AC$1*AB36+(1-AC$1)*AC35 -> 2.6215598 | AD36: =AB36-AC36 -> -0.70987205
B37: 44979 | C37: 70.27 | D37: =100*(C37-MIN(C18:C37))/(MAX(C18:C37)-MIN(C18:C37)) -> 42.448331 | E37: =AVERAGE(D33:D37) -> 57.384825 | F37: 20 | G37: 80 | X37: 44979 | Y37: 70.27 | Z37: =$Z$1*Y37+(1-$Z$1)*Z36 -> 70.960602 | AA37: =$AA$1*Z37+(1-$AA$1)*AA36 -> 69.306784 | AB37: =Z37-AA37 -> 1.6538183 | AC37: =AC$1*AB37+(1-AC$1)*AC36 -> 2.4280115 | AD37: =AB37-AC37 -> -0.77419321
... B91: 45056 | C91: 63.64 | D91: =100*(C91-MIN(C72:C91))/(MAX(C72:C91)-MIN(C72:C91)) -> 72.164948 | E91: =AVERAGE(D87:D91) -> 41.494845 | F91: 20 | G91: 80 | X91: 45056 | Y91: 63.64 | Z91: =$Z$1*Y91+(1-$Z$1)*Z90 -> 62.07042 | AA91: =$AA$1*Z91+(1-$AA$1)*AA90 -> 62.709843 | AB91: =Z91-AA91 -> -0.63942303 | AC91: =AC$1*AB91+(1-AC$1)*AC90 -> -0.71821833 | AD91: =AB91-AC91 -> 0.078795299
B92: 45057 | C92: 63.72 | D92: =100*(C92-MIN(C73:C92))/(MAX(C73:C92)-MIN(C73:C92)) -> 73.195876 | E92: =AVERAGE(D88:D92) -> 56.134021 | F92: 20 | G92: 80 | X92: 45057 | Y92: 63.72 | Z92: =$Z$1*Y92+(1-$Z$1)*Z91 -> 62.324201 | AA92: =$AA$1*Z92+(1-$AA$1)*AA91 -> 62.681277 | AB92: =Z92-AA92 -> -0.35707542 | AC92: =AC$1*AB92+(1-AC$1)*AC91 -> -0.64598975 | AD92: =AB92-AC92 -> 0.28891433 | AE92: =(AD92-AVERAGE(AD3:AD92))/_xlfn.STDEV.S(AD3:AD92) -> 0.2927182
B93: 45058 | C93: 62.51 | D93: =100*(C93-MIN(C74:C93))/(MAX(C74:C93)-MIN(C74:C93)) -> 57.603093 | E93: =AVERAGE(D89:D93) -> 61.237113 | F93: 20 | G93: 80 | X93: 45058 | Y93: 62.51 | Z93: =$Z$1*Y93+(1-$Z$1)*Z92 -> 62.352786 | AA93: =$AA$1*Z93+(1-$AA$1)*AA92 -> 62.656944 | AB93: =Z93-AA93 -> -0.30415835 | AC93: =AC$1*AB93+(1-AC$1)*AC92 -> -0.57762347 | AD93: =AB93-AC93 -> 0.27346512 | AE93: =(AD93-AVERAGE(AD4:AD93))/_xlfn.STDEV.S(AD4:AD93) -> 0.27683645
B94: 45061 | C94: 63.18 | D94: =100*(C94-MIN(C75:C94))/(MAX(C75:C94)-MIN(C75:C94)) -> 66.237113 | E94: =AVERAGE(D90:D94) -> 64.716495 | F94: 20 | G94: 80 | X94: 45061 | Y94: 63.18 | Z94: =$Z$1*Y94+(1-$Z$1)*Z93 -> 62.480049 | AA94: =$AA$1*Z94+(1-$AA$1)*AA93 -> 62.643841 | AB94: =Z94-AA94 -> -0.16379131 | AC94: =AC$1*AB94+(1-AC$1)*AC93 -> -0.49485704 | AD94: =AB94-AC94 -> 0.33106573 | AE94: =(AD94-AVERAGE(AD5:AD94))/_xlfn.STDEV.S(AD5:AD94) -> 0.32807251
B95: 45062 | C95: 62.04 | D95: =100*(C95-MIN(C76:C95))/(MAX(C76:C95)-MIN(C76:C95)) -> 51.546392 | E95: =AVERAGE(D91:D95) -> 64.149485 | F95: 20 | G95: 80 | X95: 45062 | Y95: 62.04 | Z95: =$Z$1*Y95+(1-$Z$1)*Z94 -> 62.41235 | AA95: =$AA$1*Z95+(1-$AA$1)*AA94 -> 62.626693 | AB95: =Z95-AA95 -> -0.21434373 | AC95: =AC$1*AB95+(1-AC$1)*AC94 -> -0.43875438 | AD95: =AB95-AC95 -> 0.22441064 | AE95: =(AD95-AVERAGE(AD6:AD95))/_xlfn.STDEV.S(AD6:AD95) -> 0.22818798
B96: 45063 | C96: 63.42 | D96: =100*(C96-MIN(C77:C96))/(MAX(C77:C96)-MIN(C77:C96)) -> 86.08 | E96: =AVERAGE(D92:D96) -> 66.932495 | F96: 20 | G96: 80 | X96: 45063 | Y96: 63.42 | Z96: =$Z$1*Y96+(1-$Z$1)*Z95 -> 62.567373 | AA96: =$AA$1*Z96+(1-$AA$1)*AA95 -> 62.622299 | AB96: =Z96-AA96 -> -0.05492647 | AC96: =AC$1*AB96+(1-AC$1)*AC95 -> -0.3619888 | AD96: =AB96-AC96 -> 0.30706233 | AE96: =(AD96-AVERAGE(AD7:AD96))/_xlfn.STDEV.S(AD7:AD96) -> 0.30443243
B97: 45064 | C97: 63.74 | D97: =100*(C97-MIN(C78:C97))/(MAX(C78:C97)-MIN(C78:C97)) -> 100 | E97: =AVERAGE(D93:D97) -> 72.29332 | F97: 20 | G97: 80 | X97: 45064 | Y97: 63.74 | Z97: =$Z$1*Y97+(1-$Z$1)*Z96 -> 62.747777 | AA97: =$AA$1*Z97+(1-$AA$1)*AA96 -> 62.631594 | AB97: =Z97-AA97 -> 0.11618308 | AC97: =AC$1*AB97+(1-AC$1)*AC96 -> -0.26635442 | AD97: =AB97-AC97 -> 0.3825375 | AE97: =(AD97-AVERAGE(AD8:AD97))/_xlfn.STDEV.S(AD8:AD97) -> 0.37502742
B98: 45065 | C98: 63.85 | D98: =100*(C98-MIN(C79:C98))/(MAX(C79:C98)-MIN(C79:C98)) -> 100 | E98: =AVERAGE(D94:D98) -> 80.772701 | F98: 20 | G98: 80 | X98: 45065 | Y98: 63.85 | Z98: =$Z$1*Y98+(1-$Z$1)*Z97 -> 62.91735 | AA98: =$AA$1*Z98+(1-$AA$1)*AA97 -> 62.652761 | AB98: =Z98-AA98 -> 0.26458877 | AC98: =AC$1*AB98+(1-AC$1)*AC97 -> -0.16016578 | AD98: =AB98-AC98 -> 0.42475455 | AE98: =(AD98-AVERAGE(AD9:AD98))/_xlfn.STDEV.S(AD9:AD98) -> 0.41694536
B99: 45068 | C99: 66 | D99: =100*(C99-MIN(C80:C99))/(MAX(C80:C99)-MIN(C80:C99)) -> 100 | E99: =AVERAGE(D95:D99) -> 87.525278 | F99: 20 | G99: 80 | X99: 45068 | Y99: 66 | Z99: =$Z$1*Y99+(1-$Z$1)*Z98 -> 63.391604 | AA99: =$AA$1*Z99+(1-$AA$1)*AA98 -> 62.70749 | AB99: =Z99-AA99 -> 0.68411357 | AC99: =AC$1*AB99+(1-AC$1)*AC98 -> 0.0086900882 | AD99: =AB99-AC99 -> 0.67542349 | AE99: =(AD99-AVERAGE(AD10:AD99))/_xlfn.STDEV.S(AD10:AD99) -> 0.65310745
B100: 45069 | C100: 64.32 | D100: =100*(C100-MIN(C81:C100))/(MAX(C81:C100)-MIN(C81:C100)) -> 78.894472 | E100: =AVERAGE(D96:D100) -> 92.994894 | F100: 20 | G100: 80 | X100: 45069 | Y100: 64.32 | Z100: =$Z$1*Y100+(1-$Z$1)*Z99 -> 63.534434 | AA100: =$AA$1*Z100+(1-$AA$1)*AA99 -> 62.768745 | AB100: =Z100-AA100 -> 0.7656887 | AC100: =AC$1*AB100+(1-AC$1)*AC99 -> 0.16008981 | AD100: =AB100-AC100 -> 0.60559889 | AE100: =(AD100-AVERAGE(AD11:AD100))/_xlfn.STDEV.S(AD11:AD100) -> 0.59487114
B101: 45070 | C101: 62.97 | D101: =100*(C101-MIN(C82:C101))/(MAX(C82:C101)-MIN(C82:C101)) -> 61.934673 | E101: =AVERAGE(D97:D101) -> 88.165829 | F101: 20 | G101: 80 | X101: 45070 | Y101: 62.97 | Z101: =$Z$1*Y101+(1-$Z$1)*Z100 -> 63.447598 | AA101: =$AA$1*Z101+(1-$AA$1)*AA100 -> 62.81903 | AB101: =Z101-AA101 -> 0.62856734 | AC101: =AC$1*AB101+(1-AC$1)*AC100 -> 0.25378532 | AD101: =AB101-AC101 -> 0.37478202 | AE101: =(AD101-AVERAGE(AD12:AD101))/_xlfn.STDEV.S(AD12:AD101) -> 0.39091892
B102: 45071 | C102: 64.23 | D102: =100*(C102-MIN(C83:C102))/(MAX(C83:C102)-MIN(C83:C102)) -> 77.763819 | E102: =AVERAGE(D98:D102) -> 83.718593 | F102: 20 | G102: 80 | X102: 45071 | Y102: 64.23 | Z102: =$Z$1*Y102+(1-$Z$1)*Z101 -> 63.567967 | AA102: =$AA$1*Z102+(1-$AA$1)*AA101 -> 62.874507 | AB102: =Z102-AA102 -> 0.6934601 | AC102: =AC$1*AB102+(1-AC$1)*AC101 -> 0.34172027 | AD102: =AB102-AC102 -> 0.35173982 | AE102: =(AD102-AVERAGE(AD13:AD102))/_xlfn.STDEV.S(AD13:AD102) -> 0.38106346
B103: 45072 | C103: 65.42 | D103: =100*(C103-MIN(C84:C103))/(MAX(C84:C103)-MIN(C84:C103)) -> 92.713568 | E103: =AVERAGE(D99:D103) -> 82.261307 | F103: 20 | G103: 80 | X103: 45072 | Y103: 65.42 | Z103: =$Z$1*Y103+(1-$Z$1)*Z102 -> 63.852895 | AA103: =$AA$1*Z103+(1-$AA$1)*AA102 -> 62.94698 | AB103: =Z103-AA103 -> 0.90591499 | AC103: =AC$1*AB103+(1-AC$1)*AC102 -> 0.45455922 | AD103: =AB103-AC103 -> 0.45135577 | AE103: =(AD103-AVERAGE(AD14:AD103))/_xlfn.STDEV.S(AD14:AD103) -> 0.4835671
... B504: 45657 | C504: 165.16 | D504: =100*(C504-MIN(C485:C504))/(MAX(C485:C504)-MIN(C485:C504)) -> 0 | E504: =AVERAGE(D500:D504) -> 30.760967 | F504: 20 | G504: 80 | X504: 45657 | Y504: 165.16 | Z504: =$Z$1*Y504+(1-$Z$1)*Z503 -> 170.82057 | AA504: =$AA$1*Z504+(1-$AA$1)*AA503 -> 169.08966 | AB504: =Z504-AA504 -> 1.7309111 | AC504: =AC$1*AB504+(1-AC$1)*AC503 -> 4.9201972 | AD504: =AB504-AC504 -> -3.1892862 | AE504: =(AD504-AVERAGE(AD415:AD504))/_xlfn.STDEV.S(AD415:AD504) -> -2.1675028

Sheet Forecasts 1
B2: Counter | C2: Qtrs | D2: Qtrs | E2: APO US eps (mod) | F2: APO US eps (real) | G2: QoQ growth | H2: YoY growth | I2: Ln(Qtrs) | X2: Season growth | AM2: Qtrs | AN2: APO US eps T12m | AO2: QoQ growth T12m | AP2: Ln T12m | AQ2: Trend form | AR2: Trend eps | BJ2: Forecast with Holt's Method
B3: 1 | C3: Q1 2011 | D3: 40633 | E3: 0.33 | F3: 0.33 | I3: =ABS(LN(ABS(E3))) -> 1.1086626 | J3: =EXP(I3) -> 3.030303 | AL3: 1 | AM3: Q1 2011 | BJ3: Eps with Holt's Method
B4: 2 | C4: Q2 2011 | D4: 40724 | E4: =AVERAGE($F$3,$F$6) -> 0.19 | F4: -0.46 | G4: =E4/E3-1 -> -0.42424242 | I4: =ABS(LN(ABS(E4))) -> 1.6607312 | J4: =EXP(I4) -> 5.2631579 | AL4: 2 | AM4: Q2 2011 | BI4: Q1 2011
B5: 3 | C5: Q3 2011 | D5: 40816 | E5: =AVERAGE($F$3,$F$6) -> 0.19 | F5: -3.86 | G5: =-(E5/E4-1) -> 0 | I5: =ABS(LN(ABS(E5))) -> 1.6607312 | J5: =EXP(I5) -> 5.2631579 | AL5: 3 | AM5: Q3 2011 | BI5: Q2 2011 | BJ5: =E3 -> 0.33
B6: 4 | C6: Q4 2011 | D6: 40908 | E6: 0.05 | F6: 0.05 | G6: =E6/E5-1 -> -0.73684211 | I6: =ABS(LN(ABS(E6))) -> 2.9957323 | J6: =EXP(I6) -> 20 | X6: =SLOPE(I3:I6,B3:B6) -> 0.56612089 | AL6: 4 | AM6: Q4 2011 | AN6: =SUM(E3:E6) -> 0.76 | AP6: =LN(AN6) -> -0.27443685 | AQ6: =FORECAST(B6,$AP$6:$AP$70,$AL$6:$AL$70) -> 0.18613384 | AR6: =EXP(AQ6) -> 1.2045835 | BI6: Q3 2011 | BJ6: =0.7*E4+0.3*BJ5 -> 0.232
B7: 5 | C7: Q1 2012 | D7: 40999 | E7: 0.66 | F7: 0.66 | G7: =E7/E6-1 -> 12.2 | H7: =E7/E3-1 -> 1 | I7: =ABS(LN(ABS(E7))) -> 0.41551544 | J7: =EXP(I7) -> 1.5151515 | X7: =SLOPE(I4:I7,B4:B7) -> -0.24006462 | AL7: 5 | AM7: Q1 2012 | AN7: =SUM(E4:E7) -> 1.09 | AO7: =(AN7/AN6)-1 -> 0.43421053 | AP7: =LN(AN7) -> 0.086177696 | AQ7: =FORECAST(B7,$AP$6:$AP$70,$AL$6:$AL$70) -> 0.22125888 | AR7: =EXP(AQ7) -> 1.2476464 | BI7: Q4 2011 | BJ7: =0.7*E5+0.3*BJ6 -> 0.2026
B8: 6 | C8: Q2 2012 | D8: 41090 | E8: =AVERAGE($F$7,$F$9) -> 0.605 | F8: -0.38 | G8: =E8/E7-1 -> -0.083333333 | H8: =E8/E4-1 -> 2.1842105 | I8: =ABS(LN(ABS(E8))) -> 0.50252682 | J8: =EXP(I8) -> 1.6528926 | X8: =SLOPE(I5:I8,B5:B8) -> -0.605483 | AL8: 6 | AM8: Q2 2012 | AN8: =SUM(E5:E8) -> 1.505 | AO8: =(AN8/AN7)-1 -> 0.38073394 | AP8: =LN(AN8) -> 0.4087929 | AQ8: =FORECAST(B8,$AP$6:$AP$70,$AL$6:$AL$70) -> 0.25638392 | AR8: =EXP(AQ8) -> 1.2922488 | BI8: Q1 2012 | BJ8: =0.7*E6+0.3*BJ7 -> 0.09578
B9: 7 | C9: Q3 2012 | D9: 41182 | E9: 0.55 | F9: 0.55 | G9: =E9/E8-1 -> -0.090909091 | H9: =E9/E5-1 -> 1.8947368 | I9: =ABS(LN(ABS(E9))) -> 0.597837 | J9: =EXP(I9) -> 1.8181818 | X9: =SLOPE(I6:I9,B6:B9) -> -0.71066744 | AL9: 7 | AM9: Q3 2012 | AN9: =SUM(E6:E9) -> 1.865 | AO9: =(AN9/AN8)-1 -> 0.23920266 | AP9: =LN(AN9) -> 0.62326105 | AQ9: =FORECAST(B9,$AP$6:$AP$70,$AL$6:$AL$70) -> 0.29150897 | AR9: =EXP(AQ9) -> 1.3384456 | BI9: Q2 2012 | BJ9: =0.7*E7+0.3*BJ8 -> 0.490734
B10: 8 | C10: Q4 2012 | D10: 41274 | E10: 1.12 | F10: 1.12 | G10: =E10/E9-1 -> 1.0363636 | H10: =E10/E6-1 -> 21.4 | I10: =ABS(LN(ABS(E10))) -> 0.11332869 | J10: =EXP(I10) -> 1.12 | X10: =SLOPE(I7:I10,B7:B10) -> -0.08112501 | AL10: 8 | AM10: Q4 2012 | AN10: =SUM(E7:E10) -> 2.935 | AO10: =(AN10/AN9)-1 -> 0.57372654 | AP10: =LN(AN10) -> 1.0767075 | AQ10: =FORECAST(B10,$AP$6:$AP$70,$AL$6:$AL$70) -> 0.32663401 | AR10: =EXP(AQ10) -> 1.386294 | BI10: Q3 2012 | BJ10: =0.7*E8+0.3*BJ9 -> 0.5707202
B11: 9 | C11: Q1 2013 | D11: 41364 | E11: 1.6 | F11: 1.6 | G11: =E11/E10-1 -> 0.42857143 | H11: =E11/E7-1 -> 1.4242424 | I11: =ABS(LN(ABS(E11))) -> 0.47000363 | J11: =EXP(I11) -> 1.6 | X11: =SLOPE(I8:I11,B8:B11) -> -0.058207789 | AL11: 9 | AM11: Q1 2013 | AN11: =SUM(E8:E11) -> 3.875 | AO11: =(AN11/AN10)-1 -> 0.32027257 | AP11: =LN(AN11) -> 1.3545457 | AQ11: =FORECAST(B11,$AP$6:$AP$70,$AL$6:$AL$70) -> 0.36175905 | AR11: =EXP(AQ11) -> 1.4358529 | BI11: Q4 2012 | BJ11: =0.7*E9+0.3*BJ10 -> 0.55621606
B12: 10 | C12: Q2 2013 | D12: 41455 | E12: 0.32 | F12: 0.32 | G12: =E12/E11-1 -> -0.8 | H12: =E12/E8-1 -> -0.47107438 | I12: =ABS(LN(ABS(E12))) -> 1.1394343 | J12: =EXP(I12) -> 3.125 | X12: =SLOPE(I9:I12,B9:B12) -> 0.19814668 | AL12: 10 | AM12: Q2 2013 | AN12: =SUM(E9:E12) -> 3.59 | AO12: =(AN12/AN11)-1 -> -0.073548387 | AP12: =LN(AN12) -> 1.2781522 | AQ12: =FORECAST(B12,$AP$6:$AP$70,$AL$6:$AL$70) -> 0.39688409 | AR12: =EXP(AQ12) -> 1.4871835 | BI12: Q1 2013 | BJ12: =0.7*E10+0.3*BJ11 -> 0.95086482
B13: 11 | C13: Q3 2013 | D13: 41547 | E13: 1.13 | F13: 1.13 | G13: =E13/E12-1 -> 2.53125 | H13: =E13/E9-1 -> 1.0545455 | I13: =ABS(LN(ABS(E13))) -> 0.12221763 | J13: =EXP(I13) -> 1.13 | X13: =SLOPE(I10:I13,B10:B13) -> 0.06960975 | AL13: 11 | AM13: Q3 2013 | AN13: =SUM(E10:E13) -> 4.17 | AO13: =(AN13/AN12)-1 -> 0.16155989 | AP13: =LN(AN13) -> 1.427916 | AQ13: =FORECAST(B13,$AP$6:$AP$70,$AL$6:$AL$70) -> 0.43200914 | AR13: =EXP(AQ13) -> 1.5403492 | BI13: Q2 2013 | BJ13: =0.7*E11+0.3*BJ12 -> 1.4052594
B14: 12 | C14: Q4 2013 | D14: 41639 | E14: 0.94 | F14: 0.94 | G14: =E14/E13-1 -> -0.16814159 | H14: =E14/E10-1 -> -0.16071429 | I14: =ABS(LN(ABS(E14))) -> 0.061875404 | J14: =EXP(I14) -> 1.0638298 | X14: =SLOPE(I11:I14,B11:B14) -> -0.22416013 | AL14: 12 | AM14: Q4 2013 | AN14: =SUM(E11:E14) -> 3.99 | AO14: =(AN14/AN13)-1 -> -0.043165468 | AP14: =LN(AN14) -> 1.3837912 | AQ14: =FORECAST(B14,$AP$6:$AP$70,$AL$6:$AL$70) -> 0.46713418 | AR14: =EXP(AQ14) -> 1.5954155 | BI14: Q3 2013 | BJ14: =0.7*E12+0.3*BJ13 -> 0.64557783
B15: 13 | C15: Q1 2014 | D15: 41729 | E15: 0.32 | F15: 0.32 | G15: =E15/E14-1 -> -0.65957447 | H15: =E15/E11-1 -> -0.8 | I15: =ABS(LN(ABS(E15))) -> 1.1394343 | J15: =EXP(I15) -> 3.125 | X15: =SLOPE(I12:I15,B12:B15) -> -0.0060342229 | AL15: 13 | AM15: Q1 2014 | AN15: =SUM(E12:E15) -> 2.71 | AO15: =(AN15/AN14)-1 -> -0.32080201 | AP15: =LN(AN15) -> 0.99694863 | AQ15: =FORECAST(B15,$AP$6:$AP$70,$AL$6:$AL$70) -> 0.50225922 | AR15: =EXP(AQ15) -> 1.6524503 | BI15: Q4 2013 | BJ15: =0.7*E13+0.3*BJ14 -> 0.98467335
B16: 14 | C16: Q2 2014 | D16: 41820 | E16: 0.33 | F16: 0.33 | G16: =E16/E15-1 -> 0.03125 | H16: =E16/E12-1 -> 0.03125 | I16: =ABS(LN(ABS(E16))) -> 1.1086626 | J16: =EXP(I16) -> 3.030303 | X16: =SLOPE(I13:I16,B13:B16) -> 0.40368939 | AL16: 14 | AM16: Q2 2014 | AN16: =SUM(E13:E16) -> 2.72 | AO16: =(AN16/AN15)-1 -> 0.0036900369 | AP16: =LN(AN16) -> 1.0006319 | AQ16: =FORECAST(B16,$AP$6:$AP$70,$AL$6:$AL$70) -> 0.53738427 | AR16: =EXP(AQ16) -> 1.7115241 | BI16: Q1 2014 | BJ16: =0.7*E14+0.3*BJ15 -> 0.95340201
B17: 15 | C17: Q3 2014 | D17: 41912 | E17: =AVERAGE($F$16,$F$18) -> 0.185 | F17: -0.05 | G17: =E17/E16-1 -> -0.43939394 | H17: =E17/E13-1 -> -0.83628319 | I17: =ABS(LN(ABS(E17))) -> 1.6873995 | J17: =EXP(I17) -> 5.4054054 | X17: =SLOPE(I14:I17,B14:B17) -> 0.48458005 | AL17: 15 | AM17: Q3 2014 | AN17: =SUM(E14:E17) -> 1.775 | AO17: =(AN17/AN16)-1 -> -0.34742647 | AP17: =LN(AN17) -> 0.57380042 | AQ17: =FORECAST(B17,$AP$6:$AP$70,$AL$6:$AL$70) -> 0.57250931 | AR17: =EXP(AQ17) -> 1.7727098 | BI17: Q2 2014 | BJ17: =0.7*E15+0.3*BJ16 -> 0.5100206
B18: 16 | C18: Q4 2014 | D18: 42004 | E18: 0.04 | F18: 0.04 | G18: =E18/E17-1 -> -0.78378378 | H18: =E18/E14-1 -> -0.95744681 | I18: =ABS(LN(ABS(E18))) -> 3.2188758 | J18: =EXP(I18) -> 25 | X18: =SLOPE(I15:I18,B15:B18) -> 0.68170615 | AL18: 16 | AM18: Q4 2014 | AN18: =SUM(E15:E18) -> 0.875 | AO18: =(AN18/AN17)-1 -> -0.50704225 | AP18: =LN(AN18) -> -0.13353139 | AQ18: =FORECAST(B18,$AP$6:$AP$70,$AL$6:$AL$70) -> 0.60763435 | AR18: =EXP(AQ18) -> 1.8360827 | BI18: Q3 2014 | BJ18: =0.7*E16+0.3*BJ17 -> 0.38400618
B19: 17 | C19: Q1 2015 | D19: 42094 | E19: 0.09 | F19: 0.09 | G19: =E19/E18-1 -> 1.25 | H19: =E19/E15-1 -> -0.71875 | I19: =ABS(LN(ABS(E19))) -> 2.4079456 | J19: =EXP(I19) -> 11.111111 | X19: =SLOPE(I16:I19,B16:B19) -> 0.54293253 | AL19: 17 | AM19: Q1 2015 | AN19: =SUM(E16:E19) -> 0.645 | AO19: =(AN19/AN18)-1 -> -0.26285714 | AP19: =LN(AN19) -> -0.43850496 | AQ19: =FORECAST(B19,$AP$6:$AP$70,$AL$6:$AL$70) -> 0.6427594 | AR19: =EXP(AQ19) -> 1.9017212 | BI19: Q4 2014 | BJ19: =0.7*E17+0.3*BJ18 -> 0.24470185
B20: 18 | C20: Q2 2015 | D20: 42185 | E20: 0.3 | F20: 0.3 | G20: =E20/E19-1 -> 2.3333333 | H20: =E20/E16-1 -> -0.090909091 | I20: =ABS(LN(ABS(E20))) -> 1.2039728 | J20: =EXP(I20) -> 3.3333333 | X20: =SLOPE(I17:I20,B17:B20) -> -0.22612102 | AL20: 18 | AM20: Q2 2015 | AN20: =SUM(E17:E20) -> 0.615 | AO20: =(AN20/AN19)-1 -> -0.046511628 | AP20: =LN(AN20) -> -0.48613301 | AQ20: =FORECAST(B20,$AP$6:$AP$70,$AL$6:$AL$70) -> 0.67788444 | AR20: =EXP(AQ20) -> 1.9697063 | BI20: Q1 2015 | BJ20: =0.7*E18+0.3*BJ19 -> 0.10141056
B21: 19 | C21: Q3 2015 | D21: 42277 | E21: 0.2 | F21: 0.2 | G21: =E21/E20-1 -> -0.33333333 | H21: =E21/E17-1 -> 0.081081081 | I21: =ABS(LN(ABS(E21))) -> 1.6094379 | J21: =EXP(I21) -> 5 | X21: =SLOPE(I18:I21,B18:B21) -> -0.60322865 | AL21: 19 | AM21: Q3 2015 | AN21: =SUM(E18:E21) -> 0.63 | AO21: =(AN21/AN20)-1 -> 0.024390244 | AP21: =LN(AN21) -> -0.46203546 | AQ21: =FORECAST(B21,$AP$6:$AP$70,$AL$6:$AL$70) -> 0.71300948 | AR21: =EXP(AQ21) -> 2.0401217 | BI21: Q2 2015 | BJ21: =0.7*E19+0.3*BJ20 -> 0.093423167
B22: 20 | C22: Q4 2015 | D22: 42369 | E22: 0.02 | F22: 0.02 | G22: =E22/E21-1 -> -0.9 | H22: =E22/E18-1 -> -0.5 | I22: =ABS(LN(ABS(E22))) -> 3.912023 | J22: =EXP(I22) -> 50 | X22: =SLOPE(I19:I22,B19:B22) -> 0.49176973 | AL22: 20 | AM22: Q4 2015 | AN22: =SUM(E19:E22) -> 0.61 | AO22: =(AN22/AN21)-1 -> -0.031746032 | AP22: =LN(AN22) -> -0.49429632 | AQ22: =FORECAST(B22,$AP$6:$AP$70,$AL$6:$AL$70) -> 0.74813452 | AR22: =EXP(AQ22) -> 2.1130545 | BI22: Q3 2015 | BJ22: =0.7*E20+0.3*BJ21 -> 0.23802695
B23: 21 | C23: Q1 2016 | D23: 42460 | E23: =AVERAGE($F$22,$F$24) -> 0.465 | F23: -0.19 | G23: =E23/E22-1 -> 22.25 | H23: =E23/E19-1 -> 4.1666667 | I23: =ABS(LN(ABS(E23))) -> 0.76571787 | J23: =EXP(I23) -> 2.1505376 | X23: =SLOPE(I20:I23,B20:B23) -> 0.09878203 | AL23: 21 | AM23: Q1 2016 | AN23: =SUM(E20:E23) -> 0.985 | AO23: =(AN23/AN22)-1 -> 0.6147541 | AP23: =LN(AN23) -> -0.015113638 | AQ23: =FORECAST(B23,$AP$6:$AP$70,$AL$6:$AL$70) -> 0.78325957 | AR23: =EXP(AQ23) -> 2.1885945 | BI23: Q4 2015 | BJ23: =0.7*E21+0.3*BJ22 -> 0.21140809
B24: 22 | C24: Q2 2016 | D24: 42551 | E24: 0.91 | F24: 0.91 | G24: =E24/E23-1 -> 0.95698925 | H24: =E24/E20-1 -> 2.0333333 | I24: =ABS(LN(ABS(E24))) -> 0.094310679 | J24: =EXP(I24) -> 1.0989011 | X24: =SLOPE(I21:I24,B21:B24) -> -0.76916868 | AL24: 22 | AM24: Q2 2016 | AN24: =SUM(E21:E24) -> 1.595 | AO24: =(AN24/AN23)-1 -> 0.61928934 | AP24: =LN(AN24) -> 0.46687374 | AQ24: =FORECAST(B24,$AP$6:$AP$70,$AL$6:$AL$70) -> 0.81838461 | AR24: =EXP(AQ24) -> 2.2668351 | BI24: Q1 2016 | BJ24: =0.7*E22+0.3*BJ23 -> 0.077422426
B25: 23 | C25: Q3 2016 | D25: 42643 | E25: 0.5 | F25: 0.5 | G25: =E25/E24-1 -> -0.45054945 | H25: =E25/E21-1 -> 1.5 | I25: =ABS(LN(ABS(E25))) -> 0.69314718 | J25: =EXP(I25) -> 2 | X25: =SLOPE(I22:I25,B22:B25) -> -1.0328035 | AL25: 23 | AM25: Q3 2016 | AN25: =SUM(E22:E25) -> 1.895 | AO25: =(AN25/AN24)-1 -> 0.18808777 | AP25: =LN(AN25) -> 0.63921884 | AQ25: =FORECAST(B25,$AP$6:$AP$70,$AL$6:$AL$70) -> 0.85350965 | AR25: =EXP(AQ25) -> 2.3478726 | BI25: Q2 2016 | BJ25: =0.7*E23+0.3*BJ24 -> 0.34872673
B26: 24 | C26: Q4 2016 | D26: 42735 | E26: 0.87 | F26: 0.87 | G26: =E26/E25-1 -> 0.74 | H26: =E26/E22-1 -> 42.5 | I26: =ABS(LN(ABS(E26))) -> 0.13926207 | J26: =EXP(I26) -> 1.1494253 | X26: =SLOPE(I23:I26,B23:B26) -> -0.12805309 | AL26: 24 | AM26: Q4 2016 | AN26: =SUM(E23:E26) -> 2.745 | AO26: =(AN26/AN25)-1 -> 0.44854881 | AP26: =LN(AN26) -> 1.0097811 | AQ26: =FORECAST(B26,$AP$6:$AP$70,$AL$6:$AL$70) -> 0.8886347 | AR26: =EXP(AQ26) -> 2.4318072 | BI26: Q3 2016 | BJ26: =0.7*E24+0.3*BJ25 -> 0.74161802
B27: 25 | C27: Q1 2017 | D27: 42825 | E27: 0.3 | F27: 0.3 | G27: =E27/E26-1 -> -0.65517241 | H27: =E27/E23-1 -> -0.35483871 | I27: =ABS(LN(ABS(E27))) -> 1.2039728 | J27: =EXP(I27) -> 3.3333333 | X27: =SLOPE(I24:I27,B24:B27) -> 0.27751013 | AL27: 25 | AM27: Q1 2017 | AN27: =SUM(E24:E27) -> 2.58 | AO27: =(AN27/AN26)-1 -> -0.06010929 | AP27: =LN(AN27) -> 0.9477894 | AQ27: =FORECAST(B27,$AP$6:$AP$70,$AL$6:$AL$70) -> 0.92375974 | AR27: =EXP(AQ27) -> 2.5187424 | BI27: Q4 2016 | BJ27: =0.7*E25+0.3*BJ26 -> 0.57248541
B28: 26 | C28: Q2 2017 | D28: 42916 | E28: 0.44 | F28: 0.44 | G28: =E28/E27-1 -> 0.46666667 | H28: =E28/E24-1 -> -0.51648352 | I28: =ABS(LN(ABS(E28))) -> 0.82098055 | J28: =EXP(I28) -> 2.2727273 | X28: =SLOPE(I25:I28,B25:B28) -> 0.14482109 | AL28: 26 | AM28: Q2 2017 | AN28: =SUM(E25:E28) -> 2.11 | AO28: =(AN28/AN27)-1 -> -0.18217054 | AP28: =LN(AN28) -> 0.74668795 | AQ28: =FORECAST(B28,$AP$6:$AP$70,$AL$6:$AL$70) -> 0.95888478 | AR28: =EXP(AQ28) -> 2.6087855 | BI28: Q1 2017 | BJ28: =0.7*E26+0.3*BJ27 -> 0.78074562
B29: 27 | C29: Q3 2017 | D29: 43008 | E29: 1 | F29: 1 | G29: =E29/E28-1 -> 1.2727273 | H29: =E29/E25-1 -> 1 | I29: =ABS(LN(ABS(E29))) -> 0 | J29: =EXP(I29) -> 1 | X29: =SLOPE(I26:I29,B26:B29) -> -0.080077845 | AL29: 27 | AM29: Q3 2017 | AN29: =SUM(E26:E29) -> 2.61 | AO29: =(AN29/AN28)-1 -> 0.23696682 | AP29: =LN(AN29) -> 0.95935022 | AQ29: =FORECAST(B29,$AP$6:$AP$70,$AL$6:$AL$70) -> 0.99400983 | AR29: =EXP(AQ29) -> 2.7020475 | BI29: Q2 2017 | BJ29: =0.7*E27+0.3*BJ28 -> 0.44422369
B30: 28 | C30: Q4 2017 | D30: 43100 | E30: 0.92 | F30: 0.92 | G30: =E30/E29-1 -> -0.08 | H30: =E30/E26-1 -> 0.057471264 | I30: =ABS(LN(ABS(E30))) -> 0.083381609 | J30: =EXP(I30) -> 1.0869565 | X30: =SLOPE(I27:I30,B27:B30) -> -0.41827541 | AL30: 28 | AM30: Q4 2017 | AN30: =SUM(E27:E30) -> 2.66 | AO30: =(AN30/AN29)-1 -> 0.019157088 | AP30: =LN(AN30) -> 0.97832612 | AQ30: =FORECAST(B30,$AP$6:$AP$70,$AL$6:$AL$70) -> 1.0291349 | AR30: =EXP(AQ30) -> 2.7986436 | BI30: Q3 2017 | BJ30: =0.7*E28+0.3*BJ29 -> 0.44126711
B31: 29 | C31: Q1 2018 | D31: 43190 | E31: =AVERAGE($F$30,$F$32) -> 0.585 | F31: -0.34 | G31: =E31/E30-1 -> -0.36413043 | H31: =E31/E27-1 -> 0.95 | I31: =ABS(LN(ABS(E31))) -> 0.53614343 | J31: =EXP(I31) -> 1.7094017 | X31: =SLOPE(I28:I31,B28:B31) -> -0.077112975 | AL31: 29 | AM31: Q1 2018 | AN31: =SUM(E28:E31) -> 2.945 | AO31: =(AN31/AN30)-1 -> 0.10714286 | AP31: =LN(AN31) -> 1.0801088 | AQ31: =FORECAST(B31,$AP$6:$AP$70,$AL$6:$AL$70) -> 1.0642599 | AR31: =EXP(AQ31) -> 2.8986929 | BI31: Q4 2017 | BJ31: =0.7*E29+0.3*BJ30 -> 0.83238013
B32: 30 | C32: Q2 2018 | D32: 43281 | E32: 0.25 | F32: 0.25 | G32: =E32/E31-1 -> -0.57264957 | H32: =E32/E28-1 -> -0.43181818 | I32: =ABS(LN(ABS(E32))) -> 1.3862944 | J32: =EXP(I32) -> 4 | X32: =SLOPE(I29:I32,B29:B32) -> 0.46116449 | AL32: 30 | AM32: Q2 2018 | AN32: =SUM(E29:E32) -> 2.755 | AO32: =(AN32/AN31)-1 -> -0.064516129 | AP32: =LN(AN32) -> 1.0134174 | AQ32: =FORECAST(B32,$AP$6:$AP$70,$AL$6:$AL$70) -> 1.099385 | AR32: =EXP(AQ32) -> 3.0023189 | BI32: Q1 2018 | BJ32: =0.7*E30+0.3*BJ31 -> 0.89371404
B33: 31 | C33: Q3 2018 | D33: 43373 | E33: 0.77 | F33: 0.77 | G33: =E33/E32-1 -> 2.08 | H33: =E33/E29-1 -> -0.23 | I33: =ABS(LN(ABS(E33))) -> 0.26136476 | J33: =EXP(I33) -> 1.2987013 | X33: =SLOPE(I30:I33,B30:B33) -> 0.13841004 | AL33: 31 | AM33: Q3 2018 | AN33: =SUM(E30:E33) -> 2.525 | AO33: =(AN33/AN32)-1 -> -0.083484574 | AP33: =LN(AN33) -> 0.92624106 | AQ33: =FORECAST(B33,$AP$6:$AP$70,$AL$6:$AL$70) -> 1.13451 | AR33: =EXP(AQ33) -> 3.1096494 | BI33: Q2 2018 | BJ33: =0.7*E31+0.3*BJ32 -> 0.67761421
B34: 32 | C34: Q4 2018 | D34: 43465 | E34: =AVERAGE($F$33,$F$35) -> 0.72 | F34: -1 | G34: =E34/E33-1 -> -0.064935065 | H34: =E34/E30-1 -> -0.2173913 | I34: =ABS(LN(ABS(E34))) -> 0.32850407 | J34: =EXP(I34) -> 1.3888889 | X34: =SLOPE(I31:I34,B31:B34) -> -0.17478477 | AL34: 32 | AM34: Q4 2018 | AN34: =SUM(E31:E34) -> 2.325 | AO34: =(AN34/AN33)-1 -> -0.079207921 | AP34: =LN(AN34) -> 0.84372004 | AQ34: =FORECAST(B34,$AP$6:$AP$70,$AL$6:$AL$70) -> 1.169635 | AR34: =EXP(AQ34) -> 3.220817 | BI34: Q3 2018 | BJ34: =0.7*E32+0.3*BJ33 -> 0.37828426
B35: 33 | C35: Q1 2019 | D35: 43555 | E35: 0.67 | F35: 0.67 | G35: =E35/E34-1 -> -0.069444444 | H35: =E35/E31-1 -> 0.14529915 | I35: =ABS(LN(ABS(E35))) -> 0.40047757 | J35: =EXP(I35) -> 1.4925373 | X35: =SLOPE(I32:I35,B32:B35) -> -0.28903111 | AL35: 33 | AM35: Q1 2019 | AN35: =SUM(E32:E35) -> 2.41 | AO35: =(AN35/AN34)-1 -> 0.03655914 | AP35: =LN(AN35) -> 0.87962675 | AQ35: =FORECAST(B35,$AP$6:$AP$70,$AL$6:$AL$70) -> 1.2047601 | AR35: =EXP(AQ35) -> 3.3359586 | BI35: Q4 2018 | BJ35: =0.7*E33+0.3*BJ34 -> 0.65248528
B36: 34 | C36: Q2 2019 | D36: 43646 | E36: 0.75 | F36: 0.75 | G36: =E36/E35-1 -> 0.11940299 | H36: =E36/E32-1 -> 2 | I36: =ABS(LN(ABS(E36))) -> 0.28768207 | J36: =EXP(I36) -> 1.3333333 | X36: =SLOPE(I33:I36,B33:B36) -> 0.015092542 | AL36: 34 | AM36: Q2 2019 | AN36: =SUM(E33:E36) -> 2.91 | AO36: =(AN36/AN35)-1 -> 0.20746888 | AP36: =LN(AN36) -> 1.0681531 | AQ36: =FORECAST(B36,$AP$6:$AP$70,$AL$6:$AL$70) -> 1.2398851 | AR36: =EXP(AQ36) -> 3.4552165 | BI36: Q1 2019 | BJ36: =0.7*E34+0.3*BJ35 -> 0.69974558
B37: 35 | C37: Q3 2019 | D37: 43738 | E37: 1.64 | F37: 1.64 | G37: =E37/E36-1 -> 1.1866667 | H37: =E37/E33-1 -> 1.1298701 | I37: =ABS(LN(ABS(E37))) -> 0.49469624 | J37: =EXP(I37) -> 1.64 | X37: =SLOPE(I34:I37,B34:B37) -> 0.038578103 | AL37: 35 | AM37: Q3 2019 | AN37: =SUM(E34:E37) -> 3.78 | AO37: =(AN37/AN36)-1 -> 0.29896907 | AP37: =LN(AN37) -> 1.329724 | AQ37: =FORECAST(B37,$AP$6:$AP$70,$AL$6:$AL$70) -> 1.2750102 | AR37: =EXP(AQ37) -> 3.5787378 | BI37: Q2 2019 | BJ37: =0.7*E35+0.3*BJ36 -> 0.67892368
B38: 36 | C38: Q4 2019 | D38: 43830 | E38: 0.68 | F38: 0.68 | G38: =E38/E37-1 -> -0.58536585 | H38: =E38/E34-1 -> -0.055555556 | I38: =ABS(LN(ABS(E38))) -> 0.38566248 | J38: =EXP(I38) -> 1.4705882 | X38: =SLOPE(I35:I38,B35:B38) -> 0.016256891 | AL38: 36 | AM38: Q4 2019 | AN38: =SUM(E35:E38) -> 3.74 | AO38: =(AN38/AN37)-1 -> -0.010582011 | AP38: =LN(AN38) -> 1.3190856 | AQ38: =FORECAST(B38,$AP$6:$AP$70,$AL$6:$AL$70) -> 1.3101352 | AR38: =EXP(AQ38) -> 3.7066749 | BI38: Q3 2019 | BJ38: =0.7*E36+0.3*BJ37 -> 0.7286771
B39: 37 | C39: Q1 2020 | D39: 43921 | E39: =AVERAGE(F38,F40) -> 1.26 | F39: -4.47 | G39: =E39/E38-1 -> 0.85294118 | H39: =E39/E35-1 -> 0.88059701 | I39: =ABS(LN(ABS(E39))) -> 0.23111172 | J39: =EXP(I39) -> 1.26 | X39: =SLOPE(I36:I39,B36:B39) -> -0.027874482 | AL39: 37 | AM39: Q1 2020 | AN39: =SUM(E36:E39) -> 4.33 | AO39: =(AN39/AN38)-1 -> 0.15775401 | AP39: =LN(AN39) -> 1.4655675 | AQ39: =FORECAST(B39,$AP$6:$AP$70,$AL$6:$AL$70) -> 1.3452603 | AR39: =EXP(AQ39) -> 3.8391856 | BI39: Q4 2019 | BJ39: =0.7*E37+0.3*BJ38 -> 1.3666031
B40: 38 | C40: Q2 2020 | D40: 44012 | E40: 1.84 | F40: 1.84 | G40: =E40/E39-1 -> 0.46031746 | H40: =E40/E36-1 -> 1.4533333 | I40: =ABS(LN(ABS(E40))) -> 0.60976557 | J40: =EXP(I40) -> 1.84 | X40: =SLOPE(I37:I40,B37:B40) -> 0.019065723 | AL40: 38 | AM40: Q2 2020 | AN40: =SUM(E37:E40) -> 5.42 | AO40: =(AN40/AN39)-1 -> 0.2517321 | AP40: =LN(AN40) -> 1.6900958 | AQ40: =FORECAST(B40,$AP$6:$AP$70,$AL$6:$AL$70) -> 1.3803853 | AR40: =EXP(AQ40) -> 3.9764334 | BI40: Q1 2020 | BJ40: =0.7*E38+0.3*BJ39 -> 0.88598094
B41: 39 | C41: Q3 2020 | D41: 44104 | E41: 1.11 | F41: 1.11 | G41: =E41/E40-1 -> -0.39673913 | H41: =E41/E37-1 -> -0.32317073 | I41: =ABS(LN(ABS(E41))) -> 0.10436002 | J41: =EXP(I41) -> 1.11 | X41: =SLOPE(I38:I41,B38:B41) -> -0.046525355 | AL41: 39 | AM41: Q3 2020 | AN41: =SUM(E38:E41) -> 4.89 | AO41: =(AN41/AN40)-1 -> -0.097785978 | AP41: =LN(AN41) -> 1.5871923 | AQ41: =FORECAST(B41,$AP$6:$AP$70,$AL$6:$AL$70) -> 1.4155103 | AR41: =EXP(AQ41) -> 4.1185878 | BI41: Q2 2020 | BJ41: =0.7*E39+0.3*BJ40 -> 1.1477943
B42: 40 | C42: Q4 2020 | D42: 44196 | E42: 1.8 | F42: 1.8 | G42: =E42/E41-1 -> 0.62162162 | H42: =E42/E38-1 -> 1.6470588 | I42: =ABS(LN(ABS(E42))) -> 0.58778666 | J42: =EXP(I42) -> 1.8 | X42: =SLOPE(I39:I42,B39:B42) -> 0.056461928 | AL42: 40 | AM42: Q4 2020 | AN42: =SUM(E39:E42) -> 6.01 | AO42: =(AN42/AN41)-1 -> 0.22903885 | AP42: =LN(AN42) -> 1.7934247 | AQ42: =FORECAST(B42,$AP$6:$AP$70,$AL$6:$AL$70) -> 1.4506354 | AR42: =EXP(AQ42) -> 4.2658241 | BI42: Q3 2020 | BJ42: =0.7*E40+0.3*BJ41 -> 1.6323383
B43: 41 | C43: Q1 2021 | D43: 44286 | E43: 2.8909 | F43: 2.8909 | G43: =E43/E42-1 -> 0.60605556 | H43: =E43/E39-1 -> 1.2943651 | I43: =ABS(LN(ABS(E43))) -> 1.0615679 | J43: =EXP(I43) -> 2.8909 | X43: =SLOPE(I40:I43,B40:B43) -> 0.18388336 | AL43: 41 | AM43: Q1 2021 | AN43: =SUM(E40:E43) -> 7.6409 | AO43: =(AN43/AN42)-1 -> 0.27136439 | AP43: =LN(AN43) -> 2.0335154 | AQ43: =FORECAST(B43,$AP$6:$AP$70,$AL$6:$AL$70) -> 1.4857604 | AR43: =EXP(AQ43) -> 4.4183239 | BI43: Q4 2020 | BJ43: =0.7*E41+0.3*BJ42 -> 1.2667015
B44: 42 | C44: Q2 2021 | D44: 44377 | E44: 2.7 | F44: 2.7 | G44: =E44/E43-1 -> -0.066034799 | H44: =E44/E40-1 -> 0.4673913 | I44: =ABS(LN(ABS(E44))) -> 0.99325177 | J44: =EXP(I44) -> 2.7 | X44: =SLOPE(I41:I44,B41:B44) -> 0.31404565 | AL44: 42 | AM44: Q2 2021 | AN44: =SUM(E41:E44) -> 8.5009 | AO44: =(AN44/AN43)-1 -> 0.11255219 | AP44: =LN(AN44) -> 2.140172 | AQ44: =FORECAST(B44,$AP$6:$AP$70,$AL$6:$AL$70) -> 1.5208855 | AR44: =EXP(AQ44) -> 4.5762756 | BI44: Q1 2021 | BJ44: =0.7*E42+0.3*BJ43 -> 1.6400104
B45: 43 | C45: Q3 2021 | D45: 44469 | E45: 1.0073 | F45: 1.0073 | G45: =E45/E44-1 -> -0.62692593 | H45: =E45/E41-1 -> -0.092522523 | I45: =ABS(LN(ABS(E45))) -> 0.007273484 | J45: =EXP(I45) -> 1.0073 | X45: =SLOPE(I42:I45,B42:B45) -> -0.18098556 | AL45: 43 | AM45: Q3 2021 | AN45: =SUM(E42:E45) -> 8.3982 | AO45: =(AN45/AN44)-1 -> -0.012081074 | AP45: =LN(AN45) -> 2.1280174 | AQ45: =FORECAST(B45,$AP$6:$AP$70,$AL$6:$AL$70) -> 1.5560105 | AR45: =EXP(AQ45) -> 4.7398738 | BI45: Q2 2021 | BJ45: =0.7*E43+0.3*BJ44 -> 2.5156331
B46: 44 | C46: Q4 2021 | D46: 44561 | E46: 0.9103 | F46: 0.9103 | G46: =E46/E45-1 -> -0.096297032 | H46: =E46/E42-1 -> -0.49427778 | I46: =ABS(LN(ABS(E46))) -> 0.093981063 | J46: =EXP(I46) -> 1.0985389 | X46: =SLOPE(I43:I46,B43:B46) -> -0.38887387 | AL46: 44 | AM46: Q4 2021 | AN46: =SUM(E43:E46) -> 7.5085 | AO46: =(AN46/AN45)-1 -> -0.10593937 | AP46: =LN(AN46) -> 2.0160357 | AQ46: =FORECAST(B46,$AP$6:$AP$70,$AL$6:$AL$70) -> 1.5911356 | AR46: =EXP(AQ46) -> 4.9093206 | BI46: Q3 2021 | BJ46: =0.7*E44+0.3*BJ45 -> 2.6446899
B47: 45 | C47: Q1 2022 | D47: 44651 | E47: =AVERAGE($F$46,$F$50) -> 0.9946 | F47: -0.7048 | G47: =E47/E46-1 -> 0.092606833 | H47: =E47/E43-1 -> -0.65595489 | I47: =ABS(LN(ABS(E47))) -> 0.0054146327 | J47: =EXP(I47) -> 1.0054293 | X47: =SLOPE(I44:I47,B44:B47) -> -0.28768038 | AL47: 45 | AM47: Q1 2022 | AN47: =SUM(E44:E47) -> 5.6122 | AO47: =(AN47/AN46)-1 -> -0.25255377 | AP47: =LN(AN47) -> 1.7249428 | AQ47: =FORECAST(B47,$AP$6:$AP$70,$AL$6:$AL$70) -> 1.6262606 | AR47: =EXP(AQ47) -> 5.0848249 | BI47: Q4 2021 | BJ47: =0.7*E45+0.3*BJ46 -> 1.498517
B48: 46 | C48: Q2 2022 | D48: 44742 | E48: =AVERAGE($F$46,$F$50) -> 0.9946 | F48: -2.8188 | G48: =-(E48/E47-1) -> 0 | H48: =E48/E44-1 -> -0.63162963 | I48: =ABS(LN(ABS(E48))) -> 0.0054146327 | J48: =EXP(I48) -> 1.0054293 | X48: =SLOPE(I45:I48,B45:B48) -> -0.0094142985 | AL48: 46 | AM48: Q2 2022 | AN48: =SUM(E45:E48) -> 3.9068 | AO48: =(AN48/AN47)-1 -> -0.3038737 | AP48: =LN(AN48) -> 1.3627186 | AQ48: =FORECAST(B48,$AP$6:$AP$70,$AL$6:$AL$70) -> 1.6613856 | AR48: =EXP(AQ48) -> 5.2666034 | BI48: Q1 2022 | BJ48: =0.7*E46+0.3*BJ47 -> 1.0867651
B49: 47 | C49: Q3 2022 | D49: 44834 | E49: =AVERAGE($F$46,$F$50) -> 0.9946 | F49: -0.9829 | G49: =-(E49/E48-1) -> 0 | H49: =E49/E45-1 -> -0.012607962 | I49: =ABS(LN(ABS(E49))) -> 0.0054146327 | J49: =EXP(I49) -> 1.0054293 | X49: =SLOPE(I46:I49,B46:B49) -> -0.026569929 | AL49: 47 | AM49: Q3 2022 | AN49: =SUM(E46:E49) -> 3.8941 | AO49: =(AN49/AN48)-1 -> -0.0032507423 | AP49: =LN(AN49) -> 1.3594626 | AQ49: =FORECAST(B49,$AP$6:$AP$70,$AL$6:$AL$70) -> 1.6965107 | AR49: =EXP(AQ49) -> 5.4548803 | BI49: Q2 2022 | BJ49: =0.7*E47+0.3*BJ48 -> 1.0222495
B50: 48 | C50: Q4 2022 | D50: 44926 | E50: 1.0789 | F50: 1.0789 | G50: =E50/E49-1 -> 0.084757692 | H50: =E50/E46-1 -> 0.18521367 | I50: =ABS(LN(ABS(E50))) -> 0.075942004 | J50: =EXP(I50) -> 1.0789 | X50: =SLOPE(I47:I50,B47:B50) -> 0.021158211 | AL50: 48 | AM50: Q4 2022 | AN50: =SUM(E47:E50) -> 4.0627 | AO50: =(AN50/AN49)-1 -> 0.043296269 | AP50: =LN(AN50) -> 1.4018478 | AQ50: =FORECAST(B50,$AP$6:$AP$70,$AL$6:$AL$70) -> 1.7316357 | AR50: =EXP(AQ50) -> 5.649888 | BI50: Q3 2022 | BJ50: =0.7*E48+0.3*BJ49 -> 1.0028949
B51: 49 | C51: Q1 2023 | D51: 45016 | E51: 1.67 | F51: 1.67 | G51: =E51/E50-1 -> 0.54787283 | H51: =E51/E47-1 -> 0.67906696 | I51: =ABS(LN(ABS(E51))) -> 0.51282363 | J51: =EXP(I51) -> 1.67 | X51: =SLOPE(I48:I51,B48:B51) -> 0.15927544 | AL51: 49 | AM51: Q1 2023 | AN51: =SUM(E48:E51) -> 4.7381 | AO51: =(AN51/AN50)-1 -> 0.16624412 | AP51: =LN(AN51) -> 1.5556362 | AQ51: =FORECAST(B51,$AP$6:$AP$70,$AL$6:$AL$70) -> 1.7667608 | AR51: =EXP(AQ51) -> 5.8518671 | BI51: Q4 2022 | BJ51: =0.7*E49+0.3*BJ50 -> 0.99708846
B52: 50 | C52: Q2 2023 | D52: 45107 | E52: 1 | F52: 1 | G52: =E52/E51-1 -> -0.4011976 | H52: =E52/E48-1 -> 0.0054293183 | I52: =ABS(LN(ABS(E52))) -> 0 | J52: =EXP(I52) -> 1 | X52: =SLOPE(I49:I52,B49:B52) -> 0.042063772 | AL52: 50 | AM52: Q2 2023 | AN52: =SUM(E49:E52) -> 4.7435 | AO52: =(AN52/AN51)-1 -> 0.0011396973 | AP52: =LN(AN52) -> 1.5567753 | AQ52: =FORECAST(B52,$AP$6:$AP$70,$AL$6:$AL$70) -> 1.8018858 | AR52: =EXP(AQ52) -> 6.0610667 | BI52: Q1 2023 | BJ52: =0.7*E50+0.3*BJ51 -> 1.0543565
B53: 51 | C53: Q3 2023 | D53: 45199 | E53: 1.1 | F53: 1.1 | G53: =E53/E52-1 -> 0.1 | H53: =E53/E49-1 -> 0.10597225 | I53: =ABS(LN(ABS(E53))) -> 0.09531018 | J53: =EXP(I53) -> 1.1 | X53: =SLOPE(I50:I53,B50:B53) -> -0.04547191 | AL53: 51 | AM53: Q3 2023 | AN53: =SUM(E50:E53) -> 4.8489 | AO53: =(AN53/AN52)-1 -> 0.02221988 | AP53: =LN(AN53) -> 1.5787519 | AQ53: =FORECAST(B53,$AP$6:$AP$70,$AL$6:$AL$70) -> 1.8370109 | AR53: =EXP(AQ53) -> 6.2777451 | BI53: Q2 2023 | BJ53: =0.7*E51+0.3*BJ52 -> 1.485307
B54: 52 | C54: Q4 2023 | D54: 45291 | E54: 4.8141 | F54: 4.8141 | G54: =E54/E53-1 -> 3.3764545 | H54: =E54/E50-1 -> 3.4620447 | I54: =ABS(LN(ABS(E54))) -> 1.5715491 | J54: =EXP(I54) -> 4.8141 | X54: =SLOPE(I51:I54,B51:B54) -> 0.32714866 | AL54: 52 | AM54: Q4 2023 | AN54: =SUM(E51:E54) -> 8.5841 | AO54: =(AN54/AN53)-1 -> 0.77031904 | AP54: =LN(AN54) -> 2.1499117 | AQ54: =FORECAST(B54,$AP$6:$AP$70,$AL$6:$AL$70) -> 1.8721359 | AR54: =EXP(AQ54) -> 6.5021696 | BI54: Q3 2023 | BJ54: =0.7*E52+0.3*BJ53 -> 1.1455921
B55: 53 | C55: Q1 2024 | D55: 45382 | E55: 2.38 | F55: 2.38 | G55: =E55/E54-1 -> -0.50561891 | H55: =E55/E51-1 -> 0.4251497 | I55: =ABS(LN(ABS(E55))) -> 0.86710049 | J55: =EXP(I55) -> 2.38 | X55: =SLOPE(I52:I55,B52:B55) -> 0.40775404 | AL55: 53 | AM55: Q1 2024 | AN55: =SUM(E52:E55) -> 9.2941 | AO55: =(AN55/AN54)-1 -> 0.082711059 | AP55: =LN(AN55) -> 2.2293798 | AQ55: =FORECAST(B55,$AP$6:$AP$70,$AL$6:$AL$70) -> 1.9072609 | AR55: =EXP(AQ55) -> 6.734617 | BI55: Q4 2023 | BJ55: =0.7*E53+0.3*BJ54 -> 1.1136776
B56: 54 | C56: Q2 2024 | D56: 45473 | E56: 1.41 | F56: 1.41 | G56: =E56/E55-1 -> -0.40756303 | H56: =E56/E52-1 -> 0.41 | I56: =ABS(LN(ABS(E56))) -> 0.3435897 | J56: =EXP(I56) -> 1.41 | X56: =SLOPE(I53:I56,B53:B56) -> 0.004038995 | AL56: 54 | AM56: Q2 2024 | AN56: =SUM(E53:E56) -> 9.7041 | AO56: =(AN56/AN55)-1 -> 0.044114008 | AP56: =LN(AN56) -> 2.2725485 | AQ56: =FORECAST(B56,$AP$6:$AP$70,$AL$6:$AL$70) -> 1.942386 | AR56: =EXP(AQ56) -> 6.9753743 | BI56: Q1 2024 | BJ56: =0.7*E54+0.3*BJ55 -> 3.7039733
B57: 55 | C57: Q3 2024 | D57: 45565 | E57: 1.3444 | F57: 1.3444 | G57: =E57/E56-1 -> -0.046524823 | H57: =E57/E53-1 -> 0.22218182 | I57: =ABS(LN(ABS(E57))) -> 0.29594782 | J57: =EXP(I57) -> 1.3444 | X57: =SLOPE(I54:I57,B54:B57) -> -0.43503147 | AL57: 55 | AM57: Q3 2024 | AN57: =SUM(E54:E57) -> 9.9485 | AO57: =(AN57/AN56)-1 -> 0.025185231 | AP57: =LN(AN57) -> 2.2974218 | AQ57: =FORECAST(B57,$AP$6:$AP$70,$AL$6:$AL$70) -> 1.977511 | AR57: =EXP(AQ57) -> 7.2247384 | BI57: Q2 2024 | BJ57: =0.7*E55+0.3*BJ56 -> 2.777192
B58: 56 | C58: Q4 2024 | D58: 45657 | E58: 2.5034 | F58: 2.5034 | G58: =E58/E57-1 -> 0.86209461 | H58: =E58/E54-1 -> -0.47998587 | I58: =ABS(LN(ABS(E58))) -> 0.91764981 | J58: =EXP(I58) -> 2.5034 | X58: =SLOPE(I55:I58,B55:B58) -> 0.010400607 | AL58: 56 | AM58: Q4 2024 | AN58: =SUM(E55:E58) -> 7.6378 | AO58: =(AN58/AN57)-1 -> -0.23226617 | AP58: =LN(AN58) -> 2.0331096 | AQ58: =FORECAST(B58,$AP$6:$AP$70,$AL$6:$AL$70) -> 2.0126361 | AR58: =EXP(AQ58) -> 7.4830171 | BI58: Q3 2024 | BJ58: =0.7*E56+0.3*BJ57 -> 1.8201576
B59: 57 | C59: Q1 2025 | D59: 45747 | E59: 1.939 | F59: 1.939 | G59: =E59/E58-1 -> -0.22545338 | H59: =E59/E55-1 -> -0.18529412 | I59: =ABS(LN(ABS(E59))) -> 0.66217238 | J59: =EXP(I59) -> 1.939 | X59: =SLOPE(I56:I59,B56:B59) -> 0.157745 | AL59: 57 | AM59: Q1 2025 | AN59: =SUM(E56:E59) -> 7.1968 | AO59: =(AN59/AN58)-1 -> -0.05773914 | AP59: =LN(AN59) -> 1.9736365 | AQ59: =FORECAST(B59,$AP$6:$AP$70,$AL$6:$AL$70) -> 2.0477611 | AR59: =EXP(AQ59) -> 7.7505291 | BI59: Q4 2024 | BJ59: =0.7*E57+0.3*BJ58 -> 1.4871273
B60: 58 | C60: Q2 2025 | D60: 45838 | E60: 2.031 | F60: 2.031 | G60: =E60/E59-1 -> 0.047447138 | H60: =E60/E56-1 -> 0.44042553 | I60: =ABS(LN(ABS(E60))) -> 0.70852828 | J60: =EXP(I60) -> 2.031 | X60: =SLOPE(I57:I60,B57:B60) -> 0.098226397 | AL60: 58 | AM60: Q2 2025 | AN60: =SUM(E57:E60) -> 7.8178 | AO60: =(AN60/AN59)-1 -> 0.08628835 | AP60: =LN(AN60) -> 2.0564032 | AQ60: =FORECAST(B60,$AP$6:$AP$70,$AL$6:$AL$70) -> 2.0828862 | AR60: =EXP(AQ60) -> 8.0276044 | BI60: Q1 2025 | BJ60: =0.7*E58+0.3*BJ59 -> 2.1985182
B61: 59 | C61: Q3 2025 | D61: 45930 | E61: 2.143 | F61: 2.143 | G61: =E61/E60-1 -> 0.055145249 | H61: =E61/E57-1 -> 0.59401964 | I61: =ABS(LN(ABS(E61))) -> 0.76220672 | J61: =EXP(I61) -> 2.143 | X61: =SLOPE(I58:I61,B58:B61) -> -0.041997337 | AL61: 59 | AM61: Q3 2025 | AN61: =SUM(E58:E61) -> 8.6164 | AO61: =(AN61/AN60)-1 -> 0.1021515 | AP61: =LN(AN61) -> 2.1536674 | AQ61: =FORECAST(B61,$AP$6:$AP$70,$AL$6:$AL$70) -> 2.1180112 | AR61: =EXP(AQ61) -> 8.314585 | BI61: Q2 2025 | BJ61: =0.7*E59+0.3*BJ60 -> 2.0168555
... B70: 68 | C70: Q4 2027 | D70: 46752 | E70: 3.063 | F70: 3.063 | G70: =E70/E69-1 -> 0.045392491 | H70: =E70/E66-1 -> 0.16730183 | I70: =ABS(LN(ABS(E70))) -> 1.1193948 | J70: =EXP(I70) -> 3.063 | X70: =SLOPE(I67:I70,B67:B70) -> 0.050433142 | AL70: 68 | AM70: Q4 2027 | AN70: =SUM(E67:E70) -> 11.403 | AO70: =(AN70/AN69)-1 -> 0.040040131 | AP70: =LN(AN70) -> 2.4338765 | AQ70: =FORECAST(B70,$AP$6:$AP$70,$AL$6:$AL$70) -> 2.4341366 | AR70: =EXP(AQ70) -> 11.405966 | BI70: Q3 2027 | BJ70: =0.7*E68+0.3*BJ69 -> 2.7260648
B71: 69 | C71: Q1 2028 | D71: 46843 | BI71: Q4 2027 | BJ71: =0.7*E69+0.3*BJ70 -> 2.8688194
B72: 70 | C72: Q2 2028 | D72: 46934 | AM72: Yrs | AN72: Eps | AO72: Growth | AP72: Ln(Eps) | AQ72: Trend | AR72: Trend Eps | BI72: Q1 2028 | BJ72: =_xlfn.FORECAST.ETS(D71,E3:E70,D3:D70, 1, 1) -> 3.2825797
B73: 71 | C73: Q3 2028 | D73: 47026 | AL73: 1 | AM73: 2022 | AN73: =SUM(AN47:AN50) -> 17.4758 | AP73: =LN(AN73) -> 2.8608171 | AQ73: =FORECAST(AL73,$AP$73:$AP$78,$AL$73:$AL$78) -> 2.9906197 | AR73: =EXP(AQ73) -> 19.89801 | BI73: Q2 2028 | BJ73: =_xlfn.FORECAST.ETS(D72,E4:E71,D4:D71, 1, 1) -> 2.9165517
B74: 72 | C74: Q4 2028 | D74: 47118 | AL74: 2 | AM74: 2023 | AN74: =SUM(AN51:AN54) -> 22.9146 | AO74: =AN74/AN73-1 -> 0.31121894 | AP74: =LN(AN74) -> 3.1317743 | AQ74: =FORECAST(AL74,$AP$73:$AP$78,$AL$73:$AL$78) -> 3.1558559 | AR74: =EXP(AQ74) -> 23.473118 | BI74: Q3 2028 | BJ74: =_xlfn.FORECAST.ETS(D73,E5:E72,D5:D72, 1, 1) -> 2.9569218
